Workbook

Sheet Pivot Tables & Dashboards
O5: For each brand, how many products have a discount greater than 30%?
B6: Product count and average price by SUBCATEGORY and SUBSUBCATEGORY. | F6: How many products fall into each price band: €0–15, €15–30, €30–50, €50+?
O7: Brand | P7: Discount >30%
B8: Row Labels | C8: Average Price | D8: Product | O8: Adidas Performance | P8: 24
B9: Polo Shirts | C9: 19.602149 | D9: 498 | G9: Price Distribution | H9: Total Order | O9: Nike | P9: 17
B10: Basic Polos | C10: 20.142273 | D10: 154 | G10: 0–15 | H10: 438 | O10: Tommy Hilfiger | P10: 16
B11: Pique Polos | C11: 19.787616 | D11: 172 | G11: 15-30 | H11: 422 | O11: Lacoste | P11: 8
B12: Slim Fit Polos | C12: 18.933081 | D12: 172 | G12: 30-50 | H12: 103 | O12: Cars Jeans | P12: 8
B13: T-Shirts | C13: 18.610453 | D13: 486 | G13: >50 | H13: 103 | O13: Jack & Jones Junior | P13: 7
B14: Basic T-Shirts | C14: 17.934355 | D14: 124 | O14: Only & Sons | P14: 6
B15: Long Sleeve T-Shirts | C15: 19.650776 | D15: 116 | O15: Salomon | P15: 5
B16: Print T-Shirts | C16: 17.535259 | D16: 116 | O16: New Look | P16: 5
B17: Slim Fit T-Shirts | C17: 19.286462 | D17: 130 | O17: Produkt | P17: 5
B18: Grand Total | C18: 19.112348 | D18: 984 | O18: Anthracite | P18: 5
O19: Anerkjendt | P19: 5
O20: Fila | P20: 4
O21: Puma | P21: 4
O22: Element | P22: 4
O23: Boss | P23: 4
O24: Carhartt Wip | P24: 4
O25: Bershka | P25: 3
O26: Levi's | P26: 3
O27: Urban Classics | P27: 3
O28: Seidensticker | P28: 3
O29: Dickies | P29: 3
O30: Craft | P30: 3
... O142: Iriedaily | P142: 1

Sheet Product Lookup & Search
B2: SKU and return the product name, brand, and current price.
B4: Sku | C4: Product name | D4: Brand | E4: Current Price
B5: ZL100271 | C5: {=_xlfn.XLOOKUP(B5,Real_Sales[[#All],[Sku]],Real_Sales[[#All],[Product_name]])} -> Essential T-SHIRT - RED | D5: {=_xlfn.XLOOKUP('Product Lookup & Search'!B5,Real_Sales[[#All],[Sku]],Real_Sales[[#All],[Brand]])} -> Only & Sons | E5: {=_xlfn.XLOOKUP(B5,Real_Sales[[#All],[Sku]],Real_Sales[[#All],[Price_retail]])} -> 36.16
B6: ZL100216 | C6: {=_xlfn.XLOOKUP(B6,Real_Sales[[#All],[Sku]],Real_Sales[[#All],[Product_name]])} -> Print T-SHIRT - GREY MELANGE | D6: {=_xlfn.XLOOKUP('Product Lookup & Search'!B6,Real_Sales[[#All],[Sku]],Real_Sales[[#All],[Brand]])} -> Lacoste | E6: {=_xlfn.XLOOKUP(B6,Real_Sales[[#All],[Sku]],Real_Sales[[#All],[Price_retail]])} -> 8.99
B7: ZL100525 | C7: {=_xlfn.XLOOKUP(B7,Real_Sales[[#All],[Sku]],Real_Sales[[#All],[Product_name]])} -> Basic T-SHIRT - DENIM BLUE | D7: {=_xlfn.XLOOKUP('Product Lookup & Search'!B7,Real_Sales[[#All],[Sku]],Real_Sales[[#All],[Brand]])} -> Adidas Performance | E7: {=_xlfn.XLOOKUP(B7,Real_Sales[[#All],[Sku]],Real_Sales[[#All],[Price_retail]])} -> 8.99
B8: ZL100393 | C8: {=_xlfn.XLOOKUP(B8,Real_Sales[[#All],[Sku]],Real_Sales[[#All],[Product_name]])} -> Slim Fit T-SHIRT - BORDEAUX | D8: {=_xlfn.XLOOKUP('Product Lookup & Search'!B8,Real_Sales[[#All],[Sku]],Real_Sales[[#All],[Brand]])} -> Urban Classics | E8: {=_xlfn.XLOOKUP(B8,Real_Sales[[#All],[Sku]],Real_Sales[[#All],[Price_retail]])} -> 8.99
B9: ZL100303 | C9: {=_xlfn.XLOOKUP(B9,Real_Sales[[#All],[Sku]],Real_Sales[[#All],[Product_name]])} -> Essential POLO - BORDEAUX | D9: {=_xlfn.XLOOKUP('Product Lookup & Search'!B9,Real_Sales[[#All],[Sku]],Real_Sales[[#All],[Brand]])} -> Blend She | E9: {=_xlfn.XLOOKUP(B9,Real_Sales[[#All],[Sku]],Real_Sales[[#All],[Price_retail]])} -> 8.99
B10: ZL100738 | C10: {=_xlfn.XLOOKUP(B10,Real_Sales[[#All],[Sku]],Real_Sales[[#All],[Product_name]])} -> Slim Fit T-SHIRT - OLIVE | D10: {=_xlfn.XLOOKUP('Product Lookup & Search'!B10,Real_Sales[[#All],[Sku]],Real_Sales[[#All],[Brand]])} -> Seidensticker | E10: {=_xlfn.XLOOKUP(B10,Real_Sales[[#All],[Sku]],Real_Sales[[#All],[Price_retail]])} -> 8.99
B11: ZL100247 | C11: {=_xlfn.XLOOKUP(B11,Real_Sales[[#All],[Sku]],Real_Sales[[#All],[Product_name]])} -> Slim Fit T-SHIRT - MINT | D11: {=_xlfn.XLOOKUP('Product Lookup & Search'!B11,Real_Sales[[#All],[Sku]],Real_Sales[[#All],[Brand]])} -> Fila | E11: {=_xlfn.XLOOKUP(B11,Real_Sales[[#All],[Sku]],Real_Sales[[#All],[Price_retail]])} -> 8.99
B12: ZL100887 | C12: {=_xlfn.XLOOKUP(B12,Real_Sales[[#All],[Sku]],Real_Sales[[#All],[Product_name]])} -> Regular Fit T-SHIRT - DARK BLUE | D12: {=_xlfn.XLOOKUP('Product Lookup & Search'!B12,Real_Sales[[#All],[Sku]],Real_Sales[[#All],[Brand]])} -> Nike | E12: {=_xlfn.XLOOKUP(B12,Real_Sales[[#All],[Sku]],Real_Sales[[#All],[Price_retail]])} -> 10.71
B13: ZL100887 | C13: {=_xlfn.XLOOKUP(B13,Real_Sales[[#All],[Sku]],Real_Sales[[#All],[Product_name]])} -> Regular Fit T-SHIRT - DARK BLUE | D13: {=_xlfn.XLOOKUP('Product Lookup & Search'!B13,Real_Sales[[#All],[Sku]],Real_Sales[[#All],[Brand]])} -> Nike | E13: {=_xlfn.XLOOKUP(B13,Real_Sales[[#All],[Sku]],Real_Sales[[#All],[Price_retail]])} -> 10.71
B14: ZL100656 | C14: {=_xlfn.XLOOKUP(B14,Real_Sales[[#All],[Sku]],Real_Sales[[#All],[Product_name]])} -> Regular Fit T-SHIRT - DENIM BLUE | D14: {=_xlfn.XLOOKUP('Product Lookup & Search'!B14,Real_Sales[[#All],[Sku]],Real_Sales[[#All],[Brand]])} -> Denim & Supply | E14: {=_xlfn.XLOOKUP(B14,Real_Sales[[#All],[Sku]],Real_Sales[[#All],[Price_retail]])} -> 10.72

Sheet Pricing & Discount Analysis
B2: Count Discounted Products | E2: =COUNTIF(Real_Sales[Price_label],"Sale") -> 406
B5: What is the average, minimum, and maximum current price per brand?
B7: Row Labels | C7: Average Reteil Price | D7: Max Retail Price | E7: Min Retail Price | H7: Which 10 products have the largest absolute price drop ?
B8: Adidas Originals | C8: 11.3025 | D8: 13.82 | E8: 8.99
B9: Adidas Performance | C9: 20.888205 | D9: 85.77 | E9: 8.99 | H9: Brand | I9: Discount
B10: Alpha Industries | C10: 11.27 | D10: 13.55 | E10: 8.99 | H10: Produkt | I10: 0.70020747
B11: Anerkjendt | C11: 21.293 | D11: 38.33 | E11: 8.99 | H11: Zign | I11: 0.70007987
B12: Anthracite | C12: 18.758 | D12: 28.26 | E12: 8.99 | H12: Selected Homme | I12: 0.62836723
B13: Anti Fashion | C13: 19.099 | D13: 32.12 | E13: 8.99 | H13: Denim & Supply | I13: 0.60552017
B14: Armani Exchange | C14: 10.3 | D14: 11.61 | E14: 8.99 | H14: Lacoste | I14: 0.59798842
B15: Baldessarini | C15: 24.445 | D15: 35.22 | E15: 13.67 | H15: Mango Man | I15: 0.5850682
B16: Barbour | C16: 15.725 | D16: 20.64 | E16: 10.81 | H16: Produkt | I16: 0.58324382
B17: Ben Sherman | C17: 24.793333 | D17: 37.35 | E17: 15.41 | H17: Adidas Performance | I17: 0.5810093
B18: Bershka | C18: 17.995 | D18: 26.41 | E18: 8.99 | H18: Petrol Industries | I18: 0.57685769
B19: Billabong | C19: 13.92 | D19: 18.85 | E19: 8.99 | H19: Tommy Hilfiger | I19: 0.57616417
B20: Björn Borg | C20: 18.184286 | D20: 26.73 | E20: 10.62
B21: Blend | C21: 14.01 | D21: 14.01 | E21: 14.01
B22: Blend She | C22: 11.71 | D22: 19.3 | E22: 6.99
B23: Boss | C23: 15.667143 | D23: 20.77 | E23: 9.09
B24: Boss Orange | C24: 10.155 | D24: 11.32 | E24: 8.99
B25: Brixton | C25: 17.723333 | D25: 32.42 | E25: 8.99
B26: Bruuns Bazaar | C26: 20.288 | D26: 41.51 | E26: 12.12
B27: Burton Menswear London | C27: 18.641429 | D27: 34.62 | E27: 9.67
B28: Calvin Klein | C28: 16.9665 | D28: 37.38 | E28: 8.99
B29: Carhartt Wip | C29: 17.798 | D29: 33.57 | E29: 9.41
B30: Cars Jeans | C30: 20.936087 | D30: 53.93 | E30: 8.99
B31: Casual Friday | C31: 12.89 | D31: 15.19 | E31: 11.31
... B143: Grand Total | C143: 19.119528 | D143: 99.99 | E143: 6.99

Sheet Brand
B2: What is the total revenue potential per brand?
B3: How many products does each brand have listed? Which brand has the most SKUs?
C5: Number Of Product | D5: Percentage of Product | E5: Number of Sku | F5: Revenue
B6: Nike | C6: 100 | D6: 0.10162602 | E6: 100 | F6: 1750.43
B7: Adidas Performance | C7: 75 | D7: 0.076219512 | E7: 75 | F7: 1356.9
B8: Tommy Hilfiger | C8: 62 | D8: 0.06300813 | E8: 62 | F8: 1012.11 | M8: Brand | N8: Number of Products
B9: Only & Sons | C9: 27 | D9: 0.027439024 | E9: 27 | F9: 476.51 | M9: =B6 -> Nike | N9: =C6 -> 100
B10: Cars Jeans | C10: 23 | D10: 0.023373984 | E10: 23 | F10: 402.99 | M10: =B7 -> Adidas Performance | N10: =C7 -> 75
B11: Calvin Klein | C11: 20 | D11: 0.020325203 | E11: 20 | F11: 320.57 | M11: =B8 -> Tommy Hilfiger | N11: =C8 -> 62
B12: Produkt | C12: 20 | D12: 0.020325203 | E12: 20 | F12: 298.39 | M12: =B9 -> Only & Sons | N12: =C9 -> 27
B13: Anerkjendt | C13: 20 | D13: 0.020325203 | E13: 20 | F13: 372.72 | M13: =B10 -> Cars Jeans | N13: =C10 -> 23
B14: Salomon | C14: 18 | D14: 0.018292683 | E14: 18 | F14: 238.91 | M14: =B11 -> Calvin Klein | N14: =C11 -> 20
B15: Jack & Jones Junior | C15: 18 | D15: 0.018292683 | E15: 18 | F15: 309.6 | M15: =B12 -> Produkt | N15: =C12 -> 20
B16: Lacoste | C16: 17 | D16: 0.017276423 | E16: 17 | F16: 207.52 | M16: =B13 -> Anerkjendt | N16: =C13 -> 20
B17: Puma | C17: 16 | D17: 0.016260163 | E17: 16 | F17: 350.4 | M17: =B14 -> Salomon | N17: =C14 -> 18
B18: Guess | C18: 15 | D18: 0.015243902 | E18: 15 | F18: 201.09 | M18: =B15 -> Jack & Jones Junior | N18: =C15 -> 18
B19: Fila | C19: 14 | D19: 0.014227642 | E19: 14 | F19: 181.31
B20: Burton Menswear London | C20: 13 | D20: 0.013211382 | E20: 13 | F20: 213.4
B21: Mango Man | C21: 12 | D21: 0.012195122 | E21: 12 | F21: 139.34
B22: Element | C22: 12 | D22: 0.012195122 | E22: 12 | F22: 199.79
B23: Pier One | C23: 12 | D23: 0.012195122 | E23: 12 | F23: 203.83
B24: Shine Original | C24: 12 | D24: 0.012195122 | E24: 12 | F24: 216.01
B25: Anthracite | C25: 10 | D25: 0.010162602 | E25: 10 | F25: 157.14
B26: New Look | C26: 10 | D26: 0.010162602 | E26: 10 | F26: 121.51
B27: Levi's | C27: 10 | D27: 0.010162602 | E27: 10 | F27: 161.88
B28: J.Lindeberg | C28: 10 | D28: 0.010162602 | E28: 10 | F28: 129.16
B29: Craft | C29: 9 | D29: 0.0091463415 | E29: 9 | F29: 101.59
B30: Seidensticker | C30: 9 | D30: 0.0091463415 | E30: 9 | F30: 125.32
... B141: Grand Total | C141: 984 | D141: 1 | E141: 984 | F141: 16235.6

Sheet Real Sale
A1: Sku | B1: Product_url | C1: Brand | D1: Product_name | E1: Category | F1: Subcategory | G1: Subsubcategory | H1: Color | I1: Size_range | J1: Price_retail | K1: Price_current | L1: Price_label | M1: Currency | N1: Sort_by_ranking | O1: Rating | P1: Reviews_count | Q1: Promotion | R1: Sku_variant | S1: In_stock | T1: Scan_date | U1: Image_url | V1: Discount | W1: Discount Level | X1: Column1 | Y1: Basic Procut Name | Z1: Price range
A2: ZL100041 | B2: https://www.zalando.de/blend-she-essential-t-shirt---bordeaux-zl100041/ | C2: Blend She | D2: Essential T-SHIRT - BORDEAUX | E2: Men's T-Shirts & Polos | F2: T-Shirts | G2: Print T-Shirts | H2: Bordeaux | I2: XS | J2: 6.99 | K2: 6.99 | L2: NEW | M2: EUR | N2: 355 | O2: 3.2 | P2: 35.0 | S2: No | T2: 44955 | U2: https://img01.ztat.net/article/ZL100041.jpg | V2: =(Real_Sales[[#This Row],[Price_retail]]-Real_Sales[[#This Row],[Price_current]])/Real_Sales[[#This Row],[Price_retail]] -> 0 | W2: {=_xlfn.IFS(Real_Sales[[#This Row],[Discount]]=0%,"No Discount",Real_Sales[[#This Row],[Discount]]<=20%,"Light",Real_Sales[[#This Row],[Discount]]<=50%,"Moderate",Real_Sales[[#This Row],[Discount]]<=80%,"High", TRUE,"Very High")} -> No Discount | X2: =IF(Real_Sales[[#This Row],[Price_retail]]>$AC$3,"Premium","Average") -> Average | Y2: =IF(ISNUMBER(SEARCH("Basic",Real_Sales[[#This Row],[Product_name]])),"Yes","No") -> No | Z2: {=_xlfn.IFS(Real_Sales[[#This Row],[Price_retail]]<=15,1, Real_Sales[[#This Row],[Price_retail]]<=30,2, Real_Sales[[#This Row],[Price_retail]]<=50,3,Real_Sales[[#This Row],[Price_retail]]>50,4)} -> 1 | AC2: Average retail price
A3: ZL100359 | B3: https://www.zalando.de/columbia-print-t-shirt---white-zl100359/ | C3: Columbia | D3: Print T-SHIRT - WHITE | E3: Men's T-Shirts & Polos | F3: T-Shirts | G3: Slim Fit T-Shirts | H3: White | I3: S | J3: 8.99 | K3: 3.99 | L3: SALE | M3: EUR | N3: 892 | O3: 3.7 | P3: 42.0 | S3: Yes | T3: 44955 | U3: https://img01.ztat.net/article/ZL100359.jpg | V3: =(Real_Sales[[#This Row],[Price_retail]]-Real_Sales[[#This Row],[Price_current]])/Real_Sales[[#This Row],[Price_retail]] -> 0.55617353 | W3: {=_xlfn.IFS(Real_Sales[[#This Row],[Discount]]=0%,"No Discount",Real_Sales[[#This Row],[Discount]]<=20%,"Light",Real_Sales[[#This Row],[Discount]]<=50%,"Moderate",Real_Sales[[#This Row],[Discount]]<=80%,"High", TRUE,"Very High")} -> High | X3: =IF(Real_Sales[[#This Row],[Price_retail]]>$AC$3,"Premium","Average") -> Average | Y3: =IF(ISNUMBER(SEARCH("Basic",Real_Sales[[#This Row],[Product_name]])),"Yes","No") -> No | Z3: {=_xlfn.IFS(Real_Sales[[#This Row],[Price_retail]]<=15,1, Real_Sales[[#This Row],[Price_retail]]<=30,2, Real_Sales[[#This Row],[Price_retail]]<=50,3,Real_Sales[[#This Row],[Price_retail]]>50,4)} -> 1 | AC3: =AVERAGEA(Real_Sales[Price_retail]) -> 19.112348
A4: ZL100440 | B4: https://www.zalando.de/tommy-hilfiger-basic-polo---dark-blue-zl100440/ | C4: Tommy Hilfiger | D4: Basic POLO - DARK BLUE | E4: Men's T-Shirts & Polos | F4: Polo Shirts | G4: Slim Fit Polos | H4: Dark Blue | I4: XS | J4: 8.99 | K4: 3.99 | L4: SALE | M4: EUR | N4: 362 | O4: 3.6 | P4: 37.0 | S4: Yes | T4: 44955 | U4: https://img01.ztat.net/article/ZL100440.jpg | V4: =(Real_Sales[[#This Row],[Price_retail]]-Real_Sales[[#This Row],[Price_current]])/Real_Sales[[#This Row],[Price_retail]] -> 0.55617353 | W4: {=_xlfn.IFS(Real_Sales[[#This Row],[Discount]]=0%,"No Discount",Real_Sales[[#This Row],[Discount]]<=20%,"Light",Real_Sales[[#This Row],[Discount]]<=50%,"Moderate",Real_Sales[[#This Row],[Discount]]<=80%,"High", TRUE,"Very High")} -> High | X4: =IF(Real_Sales[[#This Row],[Price_retail]]>$AC$3,"Premium","Average") -> Average | Y4: =IF(ISNUMBER(SEARCH("Basic",Real_Sales[[#This Row],[Product_name]])),"Yes","No") -> Yes | Z4: {=_xlfn.IFS(Real_Sales[[#This Row],[Price_retail]]<=15,1, Real_Sales[[#This Row],[Price_retail]]<=30,2, Real_Sales[[#This Row],[Price_retail]]<=50,3,Real_Sales[[#This Row],[Price_retail]]>50,4)} -> 1
A5: ZL100672 | B5: https://www.zalando.de/bershka-slim-fit-t-shirt---royal-blue-zl100672/ | C5: Bershka | D5: Slim Fit T-SHIRT - ROYAL BLUE | E5: Men's T-Shirts & Polos | F5: T-Shirts | G5: Slim Fit T-Shirts | H5: Royal Blue | I5: XS | J5: 8.99 | K5: 3.99 | L5: SALE | M5: EUR | N5: 197 | O5: 3.2 | P5: 39.0 | S5: Yes | T5: 44955 | U5: https://img01.ztat.net/article/ZL100672.jpg | V5: =(Real_Sales[[#This Row],[Price_retail]]-Real_Sales[[#This Row],[Price_current]])/Real_Sales[[#This Row],[Price_retail]] -> 0.55617353 | W5: {=_xlfn.IFS(Real_Sales[[#This Row],[Discount]]=0%,"No Discount",Real_Sales[[#This Row],[Discount]]<=20%,"Light",Real_Sales[[#This Row],[Discount]]<=50%,"Moderate",Real_Sales[[#This Row],[Discount]]<=80%,"High", TRUE,"Very High")} -> High | X5: =IF(Real_Sales[[#This Row],[Price_retail]]>$AC$3,"Premium","Average") -> Average | Y5: =IF(ISNUMBER(SEARCH("Basic",Real_Sales[[#This Row],[Product_name]])),"Yes","No") -> No | Z5: {=_xlfn.IFS(Real_Sales[[#This Row],[Price_retail]]<=15,1, Real_Sales[[#This Row],[Price_retail]]<=30,2, Real_Sales[[#This Row],[Price_retail]]<=50,3,Real_Sales[[#This Row],[Price_retail]]>50,4)} -> 1
A6: ZL100726 | B6: https://www.zalando.de/calvin-klein-basic-polo---khaki-zl100726/ | C6: Calvin Klein | D6: Basic POLO - KHAKI | E6: Men's T-Shirts & Polos | F6: Polo Shirts | G6: Basic Polos | H6: Khaki | I6: S | J6: 8.99 | K6: 3.99 | L6: SALE | M6: EUR | N6: 339 | O6: 0 | P6: 27.0 | S6: Yes | T6: 44955 | U6: https://img01.ztat.net/article/ZL100726.jpg | V6: =(Real_Sales[[#This Row],[Price_retail]]-Real_Sales[[#This Row],[Price_current]])/Real_Sales[[#This Row],[Price_retail]] -> 0.55617353 | W6: {=_xlfn.IFS(Real_Sales[[#This Row],[Discount]]=0%,"No Discount",Real_Sales[[#This Row],[Discount]]<=20%,"Light",Real_Sales[[#This Row],[Discount]]<=50%,"Moderate",Real_Sales[[#This Row],[Discount]]<=80%,"High", TRUE,"Very High")} -> High | X6: =IF(Real_Sales[[#This Row],[Price_retail]]>$AC$3,"Premium","Average") -> Average | Y6: =IF(ISNUMBER(SEARCH("Basic",Real_Sales[[#This Row],[Product_name]])),"Yes","No") -> Yes | Z6: {=_xlfn.IFS(Real_Sales[[#This Row],[Price_retail]]<=15,1, Real_Sales[[#This Row],[Price_retail]]<=30,2, Real_Sales[[#This Row],[Price_retail]]<=50,3,Real_Sales[[#This Row],[Price_retail]]>50,4)} -> 1
A7: ZL100873 | B7: https://www.zalando.de/timberland-pro-print-polo---red-zl100873/ | C7: Timberland Pro | D7: Print POLO - RED | E7: Men's T-Shirts & Polos | F7: Polo Shirts | G7: Pique Polos | H7: Red | I7: S | J7: 8.99 | K7: 4.04 | L7: SALE | M7: EUR | N7: 280 | O7: 4.6 | P7: 0 | S7: Yes | T7: 44955 | U7: https://img01.ztat.net/article/ZL100873.jpg | V7: =(Real_Sales[[#This Row],[Price_retail]]-Real_Sales[[#This Row],[Price_current]])/Real_Sales[[#This Row],[Price_retail]] -> 0.55061179 | W7: {=_xlfn.IFS(Real_Sales[[#This Row],[Discount]]=0%,"No Discount",Real_Sales[[#This Row],[Discount]]<=20%,"Light",Real_Sales[[#This Row],[Discount]]<=50%,"Moderate",Real_Sales[[#This Row],[Discount]]<=80%,"High", TRUE,"Very High")} -> High | X7: =IF(Real_Sales[[#This Row],[Price_retail]]>$AC$3,"Premium","Average") -> Average | Y7: =IF(ISNUMBER(SEARCH("Basic",Real_Sales[[#This Row],[Product_name]])),"Yes","No") -> No | Z7: {=_xlfn.IFS(Real_Sales[[#This Row],[Price_retail]]<=15,1, Real_Sales[[#This Row],[Price_retail]]<=30,2, Real_Sales[[#This Row],[Price_retail]]<=50,3,Real_Sales[[#This Row],[Price_retail]]>50,4)} -> 1
A8: ZL100421 | B8: https://www.zalando.de/adidas-performance-slim-fit-polo---olive-zl100421/ | C8: Adidas Performance | D8: Slim Fit POLO - OLIVE | E8: Men's T-Shirts & Polos | F8: Polo Shirts | G8: Slim Fit Polos | H8: Olive | I8: S | J8: 8.99 | K8: 4.23 | L8: SALE | M8: EUR | N8: 590 | O8: 3.3 | P8: 42.0 | S8: Yes | T8: 44955 | U8: https://img01.ztat.net/article/ZL100421.jpg | V8: =(Real_Sales[[#This Row],[Price_retail]]-Real_Sales[[#This Row],[Price_current]])/Real_Sales[[#This Row],[Price_retail]] -> 0.5294772 | W8: {=_xlfn.IFS(Real_Sales[[#This Row],[Discount]]=0%,"No Discount",Real_Sales[[#This Row],[Discount]]<=20%,"Light",Real_Sales[[#This Row],[Discount]]<=50%,"Moderate",Real_Sales[[#This Row],[Discount]]<=80%,"High", TRUE,"Very High")} -> High | X8: =IF(Real_Sales[[#This Row],[Price_retail]]>$AC$3,"Premium","Average") -> Average | Y8: =IF(ISNUMBER(SEARCH("Basic",Real_Sales[[#This Row],[Product_name]])),"Yes","No") -> No | Z8: {=_xlfn.IFS(Real_Sales[[#This Row],[Price_retail]]<=15,1, Real_Sales[[#This Row],[Price_retail]]<=30,2, Real_Sales[[#This Row],[Price_retail]]<=50,3,Real_Sales[[#This Row],[Price_retail]]>50,4)} -> 1
A9: ZL100236 | B9: https://www.zalando.de/the-north-face-regular-fit-polo---navy-zl100236/ | C9: The North Face | D9: Regular Fit POLO - NAVY | E9: Men's T-Shirts & Polos | F9: Polo Shirts | G9: Slim Fit Polos | H9: Navy | I9: M | J9: 8.99 | K9: 4.34 | L9: SALE | M9: EUR | N9: 871 | O9: 4.1 | P9: 32.0 | S9: Yes | T9: 44955 | U9: https://img01.ztat.net/article/ZL100236.jpg | V9: =(Real_Sales[[#This Row],[Price_retail]]-Real_Sales[[#This Row],[Price_current]])/Real_Sales[[#This Row],[Price_retail]] -> 0.51724138 | W9: {=_xlfn.IFS(Real_Sales[[#This Row],[Discount]]=0%,"No Discount",Real_Sales[[#This Row],[Discount]]<=20%,"Light",Real_Sales[[#This Row],[Discount]]<=50%,"Moderate",Real_Sales[[#This Row],[Discount]]<=80%,"High", TRUE,"Very High")} -> High | X9: =IF(Real_Sales[[#This Row],[Price_retail]]>$AC$3,"Premium","Average") -> Average | Y9: =IF(ISNUMBER(SEARCH("Basic",Real_Sales[[#This Row],[Product_name]])),"Yes","No") -> No | Z9: {=_xlfn.IFS(Real_Sales[[#This Row],[Price_retail]]<=15,1, Real_Sales[[#This Row],[Price_retail]]<=30,2, Real_Sales[[#This Row],[Price_retail]]<=50,3,Real_Sales[[#This Row],[Price_retail]]>50,4)} -> 1
A10: ZL100524 | B10: https://www.zalando.de/nn07-basic-polo---royal-blue-zl100524/ | C10: Nike | D10: Basic POLO - ROYAL BLUE | E10: Men's T-Shirts & Polos | F10: Polo Shirts | G10: Slim Fit Polos | H10: Royal Blue | I10: XS | J10: 8.99 | K10: 4.48 | L10: SALE | M10: EUR | N10: 798 | O10: 4.1 | P10: 30.0 | T10: 44955 | U10: https://img01.ztat.net/article/ZL100524.jpg | V10: =(Real_Sales[[#This Row],[Price_retail]]-Real_Sales[[#This Row],[Price_current]])/Real_Sales[[#This Row],[Price_retail]] -> 0.50166852 | W10: {=_xlfn.IFS(Real_Sales[[#This Row],[Discount]]=0%,"No Discount",Real_Sales[[#This Row],[Discount]]<=20%,"Light",Real_Sales[[#This Row],[Discount]]<=50%,"Moderate",Real_Sales[[#This Row],[Discount]]<=80%,"High", TRUE,"Very High")} -> High | X10: =IF(Real_Sales[[#This Row],[Price_retail]]>$AC$3,"Premium","Average") -> Average | Y10: =IF(ISNUMBER(SEARCH("Basic",Real_Sales[[#This Row],[Product_name]])),"Yes","No") -> Yes | Z10: {=_xlfn.IFS(Real_Sales[[#This Row],[Price_retail]]<=15,1, Real_Sales[[#This Row],[Price_retail]]<=30,2, Real_Sales[[#This Row],[Price_retail]]<=50,3,Real_Sales[[#This Row],[Price_retail]]>50,4)} -> 1
A11: ZL100144 | B11: https://www.zalando.de/levi's-essential-polo---navy-zl100144/ | C11: Levi's | D11: Essential POLO - NAVY | E11: Men's T-Shirts & Polos | F11: Polo Shirts | G11: Pique Polos | H11: Navy | I11: S | J11: 8.99 | K11: 4.59 | L11: SALE | M11: EUR | N11: 267 | O11: 4.7 | P11: 46.0 | S11: Yes | T11: 44955 | U11: https://img01.ztat.net/article/ZL100144.jpg | V11: =(Real_Sales[[#This Row],[Price_retail]]-Real_Sales[[#This Row],[Price_current]])/Real_Sales[[#This Row],[Price_retail]] -> 0.4894327 | W11: {=_xlfn.IFS(Real_Sales[[#This Row],[Discount]]=0%,"No Discount",Real_Sales[[#This Row],[Discount]]<=20%,"Light",Real_Sales[[#This Row],[Discount]]<=50%,"Moderate",Real_Sales[[#This Row],[Discount]]<=80%,"High", TRUE,"Very High")} -> Moderate | X11: =IF(Real_Sales[[#This Row],[Price_retail]]>$AC$3,"Premium","Average") -> Average | Y11: =IF(ISNUMBER(SEARCH("Basic",Real_Sales[[#This Row],[Product_name]])),"Yes","No") -> No | Z11: {=_xlfn.IFS(Real_Sales[[#This Row],[Price_retail]]<=15,1, Real_Sales[[#This Row],[Price_retail]]<=30,2, Real_Sales[[#This Row],[Price_retail]]<=50,3,Real_Sales[[#This Row],[Price_retail]]>50,4)} -> 1
A12: ZL100216 | B12: https://www.zalando.de/lacoste-print-t-shirt---grey-melange-zl100216/ | C12: Lacoste | D12: Print T-SHIRT - GREY MELANGE | E12: Men's T-Shirts & Polos | F12: T-Shirts | G12: Basic T-Shirts | H12: Grey Melange | I12: XS | J12: 8.99 | K12: 4.59 | L12: SALE | M12: EUR | N12: 779 | O12: 0 | P12: 33.0 | S12: No | T12: 44955 | U12: https://img01.ztat.net/article/ZL100216.jpg | V12: =(Real_Sales[[#This Row],[Price_retail]]-Real_Sales[[#This Row],[Price_current]])/Real_Sales[[#This Row],[Price_retail]] -> 0.4894327 | W12: {=_xlfn.IFS(Real_Sales[[#This Row],[Discount]]=0%,"No Discount",Real_Sales[[#This Row],[Discount]]<=20%,"Light",Real_Sales[[#This Row],[Discount]]<=50%,"Moderate",Real_Sales[[#This Row],[Discount]]<=80%,"High", TRUE,"Very High")} -> Moderate | X12: =IF(Real_Sales[[#This Row],[Price_retail]]>$AC$3,"Premium","Average") -> Average | Y12: =IF(ISNUMBER(SEARCH("Basic",Real_Sales[[#This Row],[Product_name]])),"Yes","No") -> No | Z12: {=_xlfn.IFS(Real_Sales[[#This Row],[Price_retail]]<=15,1, Real_Sales[[#This Row],[Price_retail]]<=30,2, Real_Sales[[#This Row],[Price_retail]]<=50,3,Real_Sales[[#This Row],[Price_retail]]>50,4)} -> 1
A13: ZL100525 | B13: https://www.zalando.de/adidas-performance-basic-t-shirt---denim-blue-zl100525/ | C13: Adidas Performance | D13: Basic T-SHIRT - DENIM BLUE | E13: Men's T-Shirts & Polos | F13: T-Shirts | G13: Slim Fit T-Shirts | H13: Denim Blue | I13: S | J13: 8.99 | K13: 4.61 | L13: SALE | M13: EUR | N13: 780 | O13: 4.7 | P13: 36.0 | S13: Yes | T13: 44955 | U13: https://img01.ztat.net/article/ZL100525.jpg | V13: =(Real_Sales[[#This Row],[Price_retail]]-Real_Sales[[#This Row],[Price_current]])/Real_Sales[[#This Row],[Price_retail]] -> 0.48720801 | W13: {=_xlfn.IFS(Real_Sales[[#This Row],[Discount]]=0%,"No Discount",Real_Sales[[#This Row],[Discount]]<=20%,"Light",Real_Sales[[#This Row],[Discount]]<=50%,"Moderate",Real_Sales[[#This Row],[Discount]]<=80%,"High", TRUE,"Very High")} -> Moderate | X13: =IF(Real_Sales[[#This Row],[Price_retail]]>$AC$3,"Premium","Average") -> Average | Y13: =IF(ISNUMBER(SEARCH("Basic",Real_Sales[[#This Row],[Product_name]])),"Yes","No") -> Yes | Z13: {=_xlfn.IFS(Real_Sales[[#This Row],[Price_retail]]<=15,1, Real_Sales[[#This Row],[Price_retail]]<=30,2, Real_Sales[[#This Row],[Price_retail]]<=50,3,Real_Sales[[#This Row],[Price_retail]]>50,4)} -> 1
A14: ZL100393 | B14: https://www.zalando.de/urban-classics-slim-fit-t-shirt---bordeaux-zl100393/ | C14: Urban Classics | D14: Slim Fit T-SHIRT - BORDEAUX | E14: Men's T-Shirts & Polos | F14: T-Shirts | G14: Print T-Shirts | H14: Bordeaux | I14: M | J14: 8.99 | K14: 4.66 | L14: SALE | M14: EUR | N14: 235 | O14: 0 | P14: 30.0 | S14: Yes | T14: 44955 | U14: https://img01.ztat.net/article/ZL100393.jpg | V14: =(Real_Sales[[#This Row],[Price_retail]]-Real_Sales[[#This Row],[Price_current]])/Real_Sales[[#This Row],[Price_retail]] -> 0.48164627 | W14: {=_xlfn.IFS(Real_Sales[[#This Row],[Discount]]=0%,"No Discount",Real_Sales[[#This Row],[Discount]]<=20%,"Light",Real_Sales[[#This Row],[Discount]]<=50%,"Moderate",Real_Sales[[#This Row],[Discount]]<=80%,"High", TRUE,"Very High")} -> Moderate | X14: =IF(Real_Sales[[#This Row],[Price_retail]]>$AC$3,"Premium","Average") -> Average | Y14: =IF(ISNUMBER(SEARCH("Basic",Real_Sales[[#This Row],[Product_name]])),"Yes","No") -> No | Z14: {=_xlfn.IFS(Real_Sales[[#This Row],[Price_retail]]<=15,1, Real_Sales[[#This Row],[Price_retail]]<=30,2, Real_Sales[[#This Row],[Price_retail]]<=50,3,Real_Sales[[#This Row],[Price_retail]]>50,4)} -> 1
A15: ZL100303 | B15: https://www.zalando.de/blend-she-essential-polo---bordeaux-zl100303/ | C15: Blend She | D15: Essential POLO - BORDEAUX | E15: Men's T-Shirts & Polos | F15: Polo Shirts | G15: Basic Polos | H15: Bordeaux | I15: XS | J15: 8.99 | K15: 4.7 | L15: SALE | M15: EUR | N15: 957 | O15: 4.8 | P15: 24.0 | S15: Yes | T15: 44955 | U15: https://img01.ztat.net/article/ZL100303.jpg | V15: =(Real_Sales[[#This Row],[Price_retail]]-Real_Sales[[#This Row],[Price_current]])/Real_Sales[[#This Row],[Price_retail]] -> 0.47719689 | W15: {=_xlfn.IFS(Real_Sales[[#This Row],[Discount]]=0%,"No Discount",Real_Sales[[#This Row],[Discount]]<=20%,"Light",Real_Sales[[#This Row],[Discount]]<=50%,"Moderate",Real_Sales[[#This Row],[Discount]]<=80%,"High", TRUE,"Very High")} -> Moderate | X15: =IF(Real_Sales[[#This Row],[Price_retail]]>$AC$3,"Premium","Average") -> Average | Y15: =IF(ISNUMBER(SEARCH("Basic",Real_Sales[[#This Row],[Product_name]])),"Yes","No") -> No | Z15: {=_xlfn.IFS(Real_Sales[[#This Row],[Price_retail]]<=15,1, Real_Sales[[#This Row],[Price_retail]]<=30,2, Real_Sales[[#This Row],[Price_retail]]<=50,3,Real_Sales[[#This Row],[Price_retail]]>50,4)} -> 1
A16: ZL100738 | B16: https://www.zalando.de/seidensticker-slim-fit-t-shirt---olive-zl100738/ | C16: Seidensticker | D16: Slim Fit T-SHIRT - OLIVE | E16: Men's T-Shirts & Polos | F16: T-Shirts | G16: Basic T-Shirts | H16: Olive | I16: XS | J16: 8.99 | K16: 4.82 | L16: SALE | M16: EUR | N16: 452 | O16: 4.9 | P16: 47.0 | S16: Yes | T16: 44955 | U16: https://img01.ztat.net/article/ZL100738.jpg | V16: =(Real_Sales[[#This Row],[Price_retail]]-Real_Sales[[#This Row],[Price_current]])/Real_Sales[[#This Row],[Price_retail]] -> 0.46384872 | W16: {=_xlfn.IFS(Real_Sales[[#This Row],[Discount]]=0%,"No Discount",Real_Sales[[#This Row],[Discount]]<=20%,"Light",Real_Sales[[#This Row],[Discount]]<=50%,"Moderate",Real_Sales[[#This Row],[Discount]]<=80%,"High", TRUE,"Very High")} -> Moderate | X16: =IF(Real_Sales[[#This Row],[Price_retail]]>$AC$3,"Premium","Average") -> Average | Y16: =IF(ISNUMBER(SEARCH("Basic",Real_Sales[[#This Row],[Product_name]])),"Yes","No") -> No | Z16: {=_xlfn.IFS(Real_Sales[[#This Row],[Price_retail]]<=15,1, Real_Sales[[#This Row],[Price_retail]]<=30,2, Real_Sales[[#This Row],[Price_retail]]<=50,3,Real_Sales[[#This Row],[Price_retail]]>50,4)} -> 1
A17: ZL100247 | B17: https://www.zalando.de/fila-slim-fit-t-shirt---mint-zl100247/ | C17: Fila | D17: Slim Fit T-SHIRT - MINT | E17: Men's T-Shirts & Polos | F17: T-Shirts | G17: Basic T-Shirts | H17: Mint | I17: S | J17: 8.99 | K17: 4.89 | L17: SALE | M17: EUR | N17: 478 | O17: 3.8 | P17: 38.0 | S17: No | T17: 44955 | U17: https://img01.ztat.net/article/ZL100247.jpg | V17: =(Real_Sales[[#This Row],[Price_retail]]-Real_Sales[[#This Row],[Price_current]])/Real_Sales[[#This Row],[Price_retail]] -> 0.45606229 | W17: {=_xlfn.IFS(Real_Sales[[#This Row],[Discount]]=0%,"No Discount",Real_Sales[[#This Row],[Discount]]<=20%,"Light",Real_Sales[[#This Row],[Discount]]<=50%,"Moderate",Real_Sales[[#This Row],[Discount]]<=80%,"High", TRUE,"Very High")} -> Moderate | X17: =IF(Real_Sales[[#This Row],[Price_retail]]>$AC$3,"Premium","Average") -> Average | Y17: =IF(ISNUMBER(SEARCH("Basic",Real_Sales[[#This Row],[Product_name]])),"Yes","No") -> No | Z17: {=_xlfn.IFS(Real_Sales[[#This Row],[Price_retail]]<=15,1, Real_Sales[[#This Row],[Price_retail]]<=30,2, Real_Sales[[#This Row],[Price_retail]]<=50,3,Real_Sales[[#This Row],[Price_retail]]>50,4)} -> 1
A18: ZL100823 | B18: https://www.zalando.de/puma-print-t-shirt---grey-melange-zl100823/ | C18: Puma | D18: Print T-SHIRT - GREY MELANGE | E18: Men's T-Shirts & Polos | F18: T-Shirts | G18: Slim Fit T-Shirts | H18: Grey Melange | I18: M | J18: 8.99 | K18: 5.04 | L18: SALE | M18: EUR | N18: 702 | O18: 0 | P18: 31.0 | S18: Yes | T18: 44955 | U18: https://img01.ztat.net/article/ZL100823.jpg | V18: =(Real_Sales[[#This Row],[Price_retail]]-Real_Sales[[#This Row],[Price_current]])/Real_Sales[[#This Row],[Price_retail]] -> 0.43937709 | W18: {=_xlfn.IFS(Real_Sales[[#This Row],[Discount]]=0%,"No Discount",Real_Sales[[#This Row],[Discount]]<=20%,"Light",Real_Sales[[#This Row],[Discount]]<=50%,"Moderate",Real_Sales[[#This Row],[Discount]]<=80%,"High", TRUE,"Very High")} -> Moderate | X18: =IF(Real_Sales[[#This Row],[Price_retail]]>$AC$3,"Premium","Average") -> Average | Y18: =IF(ISNUMBER(SEARCH("Basic",Real_Sales[[#This Row],[Product_name]])),"Yes","No") -> No | Z18: {=_xlfn.IFS(Real_Sales[[#This Row],[Price_retail]]<=15,1, Real_Sales[[#This Row],[Price_retail]]<=30,2, Real_Sales[[#This Row],[Price_retail]]<=50,3,Real_Sales[[#This Row],[Price_retail]]>50,4)} -> 1
A19: ZL100407 | B19: https://www.zalando.de/adidas-performance-print-t-shirt---off-white-zl100407/ | C19: Adidas Performance | D19: Print T-SHIRT - OFF WHITE | E19: Men's T-Shirts & Polos | F19: T-Shirts | G19: Print T-Shirts | I19: S | J19: 8.99 | K19: 5.1 | L19: SALE | M19: EUR | N19: 45 | O19: 4.6 | P19: 40.0 | S19: Yes | T19: 44955 | U19: https://img01.ztat.net/article/ZL100407.jpg | V19: =(Real_Sales[[#This Row],[Price_retail]]-Real_Sales[[#This Row],[Price_current]])/Real_Sales[[#This Row],[Price_retail]] -> 0.432703 | W19: {=_xlfn.IFS(Real_Sales[[#This Row],[Discount]]=0%,"No Discount",Real_Sales[[#This Row],[Discount]]<=20%,"Light",Real_Sales[[#This Row],[Discount]]<=50%,"Moderate",Real_Sales[[#This Row],[Discount]]<=80%,"High", TRUE,"Very High")} -> Moderate | X19: =IF(Real_Sales[[#This Row],[Price_retail]]>$AC$3,"Premium","Average") -> Average | Y19: =IF(ISNUMBER(SEARCH("Basic",Real_Sales[[#This Row],[Product_name]])),"Yes","No") -> No | Z19: {=_xlfn.IFS(Real_Sales[[#This Row],[Price_retail]]<=15,1, Real_Sales[[#This Row],[Price_retail]]<=30,2, Real_Sales[[#This Row],[Price_retail]]<=50,3,Real_Sales[[#This Row],[Price_retail]]>50,4)} -> 1
A20: ZL100924 | B20: https://www.zalando.de/element-essential-t-shirt---light-grey-zl100924/ | C20: Element | D20: Essential T-SHIRT - LIGHT GREY | E20: Men's T-Shirts & Polos | F20: T-Shirts | G20: Long Sleeve T-Shirts | H20: Light Grey | I20: M | J20: 8.99 | K20: 5.12 | L20: SALE | M20: EUR | N20: 890 | O20: 0 | P20: 30.0 | S20: No | T20: 44955 | U20: https://img01.ztat.net/article/ZL100924.jpg | V20: =(Real_Sales[[#This Row],[Price_retail]]-Real_Sales[[#This Row],[Price_current]])/Real_Sales[[#This Row],[Price_retail]] -> 0.43047831 | W20: {=_xlfn.IFS(Real_Sales[[#This Row],[Discount]]=0%,"No Discount",Real_Sales[[#This Row],[Discount]]<=20%,"Light",Real_Sales[[#This Row],[Discount]]<=50%,"Moderate",Real_Sales[[#This Row],[Discount]]<=80%,"High", TRUE,"Very High")} -> Moderate | X20: =IF(Real_Sales[[#This Row],[Price_retail]]>$AC$3,"Premium","Average") -> Average | Y20: =IF(ISNUMBER(SEARCH("Basic",Real_Sales[[#This Row],[Product_name]])),"Yes","No") -> No | Z20: {=_xlfn.IFS(Real_Sales[[#This Row],[Price_retail]]<=15,1, Real_Sales[[#This Row],[Price_retail]]<=30,2, Real_Sales[[#This Row],[Price_retail]]<=50,3,Real_Sales[[#This Row],[Price_retail]]>50,4)} -> 1
A21: ZL100037 | B21: https://www.zalando.de/umbro-print-polo---light-grey-zl100037/ | C21: Umbro | D21: Print POLO - LIGHT GREY | E21: Men's T-Shirts & Polos | F21: Polo Shirts | G21: Slim Fit Polos | H21: Light Grey | I21: M | J21: 8.99 | K21: 5.17 | L21: SALE | M21: EUR | N21: 143 | O21: 3.4 | P21: 30.0 | S21: Yes | T21: 44955 | U21: https://img01.ztat.net/article/ZL100037.jpg | V21: =(Real_Sales[[#This Row],[Price_retail]]-Real_Sales[[#This Row],[Price_current]])/Real_Sales[[#This Row],[Price_retail]] -> 0.42491657 | W21: {=_xlfn.IFS(Real_Sales[[#This Row],[Discount]]=0%,"No Discount",Real_Sales[[#This Row],[Discount]]<=20%,"Light",Real_Sales[[#This Row],[Discount]]<=50%,"Moderate",Real_Sales[[#This Row],[Discount]]<=80%,"High", TRUE,"Very High")} -> Moderate | X21: =IF(Real_Sales[[#This Row],[Price_retail]]>$AC$3,"Premium","Average") -> Average | Y21: =IF(ISNUMBER(SEARCH("Basic",Real_Sales[[#This Row],[Product_name]])),"Yes","No") -> No | Z21: {=_xlfn.IFS(Real_Sales[[#This Row],[Price_retail]]<=15,1, Real_Sales[[#This Row],[Price_retail]]<=30,2, Real_Sales[[#This Row],[Price_retail]]<=50,3,Real_Sales[[#This Row],[Price_retail]]>50,4)} -> 1
A22: ZL100045 | B22: https://www.zalando.de/dickies-print-t-shirt---navy-zl100045/ | C22: Dickies | D22: Print T-SHIRT - NAVY | E22: Men's T-Shirts & Polos | F22: T-Shirts | G22: Long Sleeve T-Shirts | H22: Navy | I22: XS | J22: 8.99 | K22: 5.17 | L22: SALE | M22: EUR | N22: 548 | O22: 4.5 | P22: 28.0 | S22: Yes | T22: 44955 | U22: https://img01.ztat.net/article/ZL100045.jpg | V22: =(Real_Sales[[#This Row],[Price_retail]]-Real_Sales[[#This Row],[Price_current]])/Real_Sales[[#This Row],[Price_retail]] -> 0.42491657 | W22: {=_xlfn.IFS(Real_Sales[[#This Row],[Discount]]=0%,"No Discount",Real_Sales[[#This Row],[Discount]]<=20%,"Light",Real_Sales[[#This Row],[Discount]]<=50%,"Moderate",Real_Sales[[#This Row],[Discount]]<=80%,"High", TRUE,"Very High")} -> Moderate | X22: =IF(Real_Sales[[#This Row],[Price_retail]]>$AC$3,"Premium","Average") -> Average | Y22: =IF(ISNUMBER(SEARCH("Basic",Real_Sales[[#This Row],[Product_name]])),"Yes","No") -> No | Z22: {=_xlfn.IFS(Real_Sales[[#This Row],[Price_retail]]<=15,1, Real_Sales[[#This Row],[Price_retail]]<=30,2, Real_Sales[[#This Row],[Price_retail]]<=50,3,Real_Sales[[#This Row],[Price_retail]]>50,4)} -> 1
A23: ZL100404 | B23: https://www.zalando.de/columbia-essential-polo---mint-zl100404/ | C23: Columbia | D23: Essential POLO - MINT | E23: Men's T-Shirts & Polos | F23: Polo Shirts | G23: Slim Fit Polos | H23: Mint | I23: S | J23: 8.99 | K23: 5.26 | L23: SALE | M23: EUR | N23: 775 | O23: 3.4 | P23: 41.0 | S23: No | T23: 44955 | U23: https://img01.ztat.net/article/ZL100404.jpg | V23: =(Real_Sales[[#This Row],[Price_retail]]-Real_Sales[[#This Row],[Price_current]])/Real_Sales[[#This Row],[Price_retail]] -> 0.41490545 | W23: {=_xlfn.IFS(Real_Sales[[#This Row],[Discount]]=0%,"No Discount",Real_Sales[[#This Row],[Discount]]<=20%,"Light",Real_Sales[[#This Row],[Discount]]<=50%,"Moderate",Real_Sales[[#This Row],[Discount]]<=80%,"High", TRUE,"Very High")} -> Moderate | X23: =IF(Real_Sales[[#This Row],[Price_retail]]>$AC$3,"Premium","Average") -> Average | Y23: =IF(ISNUMBER(SEARCH("Basic",Real_Sales[[#This Row],[Product_name]])),"Yes","No") -> No | Z23: {=_xlfn.IFS(Real_Sales[[#This Row],[Price_retail]]<=15,1, Real_Sales[[#This Row],[Price_retail]]<=30,2, Real_Sales[[#This Row],[Price_retail]]<=50,3,Real_Sales[[#This Row],[Price_retail]]>50,4)} -> 1
A24: ZL100550 | B24: https://www.zalando.de/adidas-performance-print-polo---navy-zl100550/ | C24: Adidas Performance | D24: Print POLO - NAVY | E24: Men's T-Shirts & Polos | F24: Polo Shirts | G24: Basic Polos | H24: Navy | I24: XS | J24: 8.99 | K24: 5.3 | L24: SALE | M24: EUR | N24: 794 | O24: 3.9 | P24: 39.0 | S24: Yes | T24: 44955 | U24: https://img01.ztat.net/article/ZL100550.jpg | V24: =(Real_Sales[[#This Row],[Price_retail]]-Real_Sales[[#This Row],[Price_current]])/Real_Sales[[#This Row],[Price_retail]] -> 0.41045606 | W24: {=_xlfn.IFS(Real_Sales[[#This Row],[Discount]]=0%,"No Discount",Real_Sales[[#This Row],[Discount]]<=20%,"Light",Real_Sales[[#This Row],[Discount]]<=50%,"Moderate",Real_Sales[[#This Row],[Discount]]<=80%,"High", TRUE,"Very High")} -> Moderate | X24: =IF(Real_Sales[[#This Row],[Price_retail]]>$AC$3,"Premium","Average") -> Average | Y24: =IF(ISNUMBER(SEARCH("Basic",Real_Sales[[#This Row],[Product_name]])),"Yes","No") -> No | Z24: {=_xlfn.IFS(Real_Sales[[#This Row],[Price_retail]]<=15,1, Real_Sales[[#This Row],[Price_retail]]<=30,2, Real_Sales[[#This Row],[Price_retail]]<=50,3,Real_Sales[[#This Row],[Price_retail]]>50,4)} -> 1
A25: ZL100909 | B25: https://www.zalando.de/salomon-slim-fit-t-shirt---white-zl100909/ | C25: Salomon | D25: Slim Fit T-SHIRT - WHITE | E25: Men's T-Shirts & Polos | F25: T-Shirts | G25: Print T-Shirts | H25: White | I25: S | J25: 8.99 | K25: 5.34 | L25: SALE | M25: EUR | N25: 282 | O25: 4.1 | P25: 43.0 | S25: No | T25: 44955 | U25: https://img01.ztat.net/article/ZL100909.jpg | V25: =(Real_Sales[[#This Row],[Price_retail]]-Real_Sales[[#This Row],[Price_current]])/Real_Sales[[#This Row],[Price_retail]] -> 0.40600667 | W25: {=_xlfn.IFS(Real_Sales[[#This Row],[Discount]]=0%,"No Discount",Real_Sales[[#This Row],[Discount]]<=20%,"Light",Real_Sales[[#This Row],[Discount]]<=50%,"Moderate",Real_Sales[[#This Row],[Discount]]<=80%,"High", TRUE,"Very High")} -> Moderate | X25: =IF(Real_Sales[[#This Row],[Price_retail]]>$AC$3,"Premium","Average") -> Average | Y25: =IF(ISNUMBER(SEARCH("Basic",Real_Sales[[#This Row],[Product_name]])),"Yes","No") -> No | Z25: {=_xlfn.IFS(Real_Sales[[#This Row],[Price_retail]]<=15,1, Real_Sales[[#This Row],[Price_retail]]<=30,2, Real_Sales[[#This Row],[Price_retail]]<=50,3,Real_Sales[[#This Row],[Price_retail]]>50,4)} -> 1
A26: ZL100977 | B26: https://www.zalando.de/tommy-hilfiger-slim-fit-t-shirt---off-white-zl100977/ | C26: Tommy Hilfiger | D26: Slim Fit T-SHIRT - OFF WHITE | E26: Men's T-Shirts & Polos | F26: T-Shirts | G26: Print T-Shirts | H26: Off White | I26: S | J26: 8.99 | K26: 5.54 | L26: SALE | M26: EUR | N26: 451 | O26: 4.8 | P26: 42.0 | S26: Yes | T26: 44955 | U26: https://img01.ztat.net/article/ZL100977.jpg | V26: =(Real_Sales[[#This Row],[Price_retail]]-Real_Sales[[#This Row],[Price_current]])/Real_Sales[[#This Row],[Price_retail]] -> 0.38375973 | W26: {=_xlfn.IFS(Real_Sales[[#This Row],[Discount]]=0%,"No Discount",Real_Sales[[#This Row],[Discount]]<=20%,"Light",Real_Sales[[#This Row],[Discount]]<=50%,"Moderate",Real_Sales[[#This Row],[Discount]]<=80%,"High", TRUE,"Very High")} -> Moderate | X26: =IF(Real_Sales[[#This Row],[Price_retail]]>$AC$3,"Premium","Average") -> Average | Y26: =IF(ISNUMBER(SEARCH("Basic",Real_Sales[[#This Row],[Product_name]])),"Yes","No") -> No | Z26: {=_xlfn.IFS(Real_Sales[[#This Row],[Price_retail]]<=15,1, Real_Sales[[#This Row],[Price_retail]]<=30,2, Real_Sales[[#This Row],[Price_retail]]<=50,3,Real_Sales[[#This Row],[Price_retail]]>50,4)} -> 1
A27: ZL100085 | B27: https://www.zalando.de/new-look-print-t-shirt---royal-blue-zl100085/ | C27: New Look | D27: Print T-SHIRT - ROYAL BLUE | E27: Men's T-Shirts & Polos | F27: T-Shirts | G27: Slim Fit T-Shirts | H27: Royal Blue | I27: XS | J27: 8.99 | K27: 5.64 | L27: SALE | M27: EUR | N27: 244 | O27: 4.0 | P27: 31.0 | S27: No | T27: 44955 | U27: https://img01.ztat.net/article/ZL100085.jpg | V27: =(Real_Sales[[#This Row],[Price_retail]]-Real_Sales[[#This Row],[Price_current]])/Real_Sales[[#This Row],[Price_retail]] -> 0.37263626 | W27: {=_xlfn.IFS(Real_Sales[[#This Row],[Discount]]=0%,"No Discount",Real_Sales[[#This Row],[Discount]]<=20%,"Light",Real_Sales[[#This Row],[Discount]]<=50%,"Moderate",Real_Sales[[#This Row],[Discount]]<=80%,"High", TRUE,"Very High")} -> Moderate | X27: =IF(Real_Sales[[#This Row],[Price_retail]]>$AC$3,"Premium","Average") -> Average | Y27: =IF(ISNUMBER(SEARCH("Basic",Real_Sales[[#This Row],[Product_name]])),"Yes","No") -> No | Z27: {=_xlfn.IFS(Real_Sales[[#This Row],[Price_retail]]<=15,1, Real_Sales[[#This Row],[Price_retail]]<=30,2, Real_Sales[[#This Row],[Price_retail]]<=50,3,Real_Sales[[#This Row],[Price_retail]]>50,4)} -> 1
A28: ZL100549 | B28: https://www.zalando.de/craft-sportswear-slim-fit-polo---anthracite-zl100549/ | C28: Craft | D28: Slim Fit POLO - ANTHRACITE | E28: Men's T-Shirts & Polos | F28: Polo Shirts | G28: Pique Polos | H28: Anthracite | J28: 8.99 | K28: 5.65 | L28: SALE | M28: EUR | N28: 788 | O28: 4.5 | P28: 33.0 | S28: No | T28: 44955 | U28: https://img01.ztat.net/article/ZL100549.jpg | V28: =(Real_Sales[[#This Row],[Price_retail]]-Real_Sales[[#This Row],[Price_current]])/Real_Sales[[#This Row],[Price_retail]] -> 0.37152392 | W28: {=_xlfn.IFS(Real_Sales[[#This Row],[Discount]]=0%,"No Discount",Real_Sales[[#This Row],[Discount]]<=20%,"Light",Real_Sales[[#This Row],[Discount]]<=50%,"Moderate",Real_Sales[[#This Row],[Discount]]<=80%,"High", TRUE,"Very High")} -> Moderate | X28: =IF(Real_Sales[[#This Row],[Price_retail]]>$AC$3,"Premium","Average") -> Average | Y28: =IF(ISNUMBER(SEARCH("Basic",Real_Sales[[#This Row],[Product_name]])),"Yes","No") -> No | Z28: {=_xlfn.IFS(Real_Sales[[#This Row],[Price_retail]]<=15,1, Real_Sales[[#This Row],[Price_retail]]<=30,2, Real_Sales[[#This Row],[Price_retail]]<=50,3,Real_Sales[[#This Row],[Price_retail]]>50,4)} -> 1
A29: ZL100964 | B29: https://www.zalando.de/nudie-jeans-slim-fit-polo---off-white-zl100964/ | C29: Nudie Jeans | D29: Slim Fit POLO - OFF WHITE | E29: Men's T-Shirts & Polos | F29: Polo Shirts | G29: Basic Polos | H29: Off White | I29: S | J29: 8.99 | K29: 5.7 | L29: SALE | M29: EUR | N29: 129 | O29: 0 | P29: 46.0 | S29: Yes | T29: 44955 | U29: https://img01.ztat.net/article/ZL100964.jpg | V29: =(Real_Sales[[#This Row],[Price_retail]]-Real_Sales[[#This Row],[Price_current]])/Real_Sales[[#This Row],[Price_retail]] -> 0.36596218 | W29: {=_xlfn.IFS(Real_Sales[[#This Row],[Discount]]=0%,"No Discount",Real_Sales[[#This Row],[Discount]]<=20%,"Light",Real_Sales[[#This Row],[Discount]]<=50%,"Moderate",Real_Sales[[#This Row],[Discount]]<=80%,"High", TRUE,"Very High")} -> Moderate | X29: =IF(Real_Sales[[#This Row],[Price_retail]]>$AC$3,"Premium","Average") -> Average | Y29: =IF(ISNUMBER(SEARCH("Basic",Real_Sales[[#This Row],[Product_name]])),"Yes","No") -> No | Z29: {=_xlfn.IFS(Real_Sales[[#This Row],[Price_retail]]<=15,1, Real_Sales[[#This Row],[Price_retail]]<=30,2, Real_Sales[[#This Row],[Price_retail]]<=50,3,Real_Sales[[#This Row],[Price_retail]]>50,4)} -> 1
A30: ZL100202 | B30: https://www.zalando.de/olymp-slim-fit-polo---rust-zl100202/ | C30: Olymp | D30: Slim Fit POLO - RUST | E30: Men's T-Shirts & Polos | F30: Polo Shirts | G30: Basic Polos | H30: Rust | I30: S | J30: 8.99 | K30: 5.81 | L30: SALE | M30: EUR | N30: 795 | O30: 4.5 | P30: 32.0 | S30: No | T30: 44955 | U30: https://img01.ztat.net/article/ZL100202.jpg | V30: =(Real_Sales[[#This Row],[Price_retail]]-Real_Sales[[#This Row],[Price_current]])/Real_Sales[[#This Row],[Price_retail]] -> 0.35372636 | W30: {=_xlfn.IFS(Real_Sales[[#This Row],[Discount]]=0%,"No Discount",Real_Sales[[#This Row],[Discount]]<=20%,"Light",Real_Sales[[#This Row],[Discount]]<=50%,"Moderate",Real_Sales[[#This Row],[Discount]]<=80%,"High", TRUE,"Very High")} -> Moderate | X30: =IF(Real_Sales[[#This Row],[Price_retail]]>$AC$3,"Premium","Average") -> Average | Y30: =IF(ISNUMBER(SEARCH("Basic",Real_Sales[[#This Row],[Product_name]])),"Yes","No") -> No | Z30: {=_xlfn.IFS(Real_Sales[[#This Row],[Price_retail]]<=15,1, Real_Sales[[#This Row],[Price_retail]]<=30,2, Real_Sales[[#This Row],[Price_retail]]<=50,3,Real_Sales[[#This Row],[Price_retail]]>50,4)} -> 1
A31: ZL100066 | B31: https://www.zalando.de/nike-essential-polo---anthracite-zl100066/ | C31: Nike | D31: Essential POLO - ANTHRACITE | E31: Men's T-Shirts & Polos | F31: Polo Shirts | G31: Pique Polos | H31: Anthracite | I31: M | J31: 8.99 | K31: 5.83 | L31: SALE | M31: EUR | N31: 533 | O31: 3.6 | P31: 39.0 | S31: Yes | T31: 44955 | U31: https://img01.ztat.net/article/ZL100066.jpg | V31: =(Real_Sales[[#This Row],[Price_retail]]-Real_Sales[[#This Row],[Price_current]])/Real_Sales[[#This Row],[Price_retail]] -> 0.35150167 | W31: {=_xlfn.IFS(Real_Sales[[#This Row],[Discount]]=0%,"No Discount",Real_Sales[[#This Row],[Discount]]<=20%,"Light",Real_Sales[[#This Row],[Discount]]<=50%,"Moderate",Real_Sales[[#This Row],[Discount]]<=80%,"High", TRUE,"Very High")} -> Moderate | X31: =IF(Real_Sales[[#This Row],[Price_retail]]>$AC$3,"Premium","Average") -> Average | Y31: =IF(ISNUMBER(SEARCH("Basic",Real_Sales[[#This Row],[Product_name]])),"Yes","No") -> No | Z31: {=_xlfn.IFS(Real_Sales[[#This Row],[Price_retail]]<=15,1, Real_Sales[[#This Row],[Price_retail]]<=30,2, Real_Sales[[#This Row],[Price_retail]]<=50,3,Real_Sales[[#This Row],[Price_retail]]>50,4)} -> 1
A32: ZL100890 | B32: https://www.zalando.de/nike-regular-fit-t-shirt---off-white-zl100890/ | C32: Nike | D32: Regular Fit T-SHIRT - OFF WHITE | E32: Men's T-Shirts & Polos | F32: T-Shirts | G32: Slim Fit T-Shirts | H32: Off White | I32: S | J32: 8.99 | K32: 5.83 | L32: SALE | M32: EUR | N32: 933 | O32: 4.8 | P32: 0 | S32: No | T32: 44955 | U32: https://img01.ztat.net/article/ZL100890.jpg | V32: =(Real_Sales[[#This Row],[Price_retail]]-Real_Sales[[#This Row],[Price_current]])/Real_Sales[[#This Row],[Price_retail]] -> 0.35150167 | W32: {=_xlfn.IFS(Real_Sales[[#This Row],[Discount]]=0%,"No Discount",Real_Sales[[#This Row],[Discount]]<=20%,"Light",Real_Sales[[#This Row],[Discount]]<=50%,"Moderate",Real_Sales[[#This Row],[Discount]]<=80%,"High", TRUE,"Very High")} -> Moderate | X32: =IF(Real_Sales[[#This Row],[Price_retail]]>$AC$3,"Premium","Average") -> Average | Y32: =IF(ISNUMBER(SEARCH("Basic",Real_Sales[[#This Row],[Product_name]])),"Yes","No") -> No | Z32: {=_xlfn.IFS(Real_Sales[[#This Row],[Price_retail]]<=15,1, Real_Sales[[#This Row],[Price_retail]]<=30,2, Real_Sales[[#This Row],[Price_retail]]<=50,3,Real_Sales[[#This Row],[Price_retail]]>50,4)} -> 1
A33: ZL100688 | B33: https://www.zalando.de/jack-jones-junior-print-t-shirt---white-zl100688/ | C33: Jack & Jones Junior | D33: Print T-SHIRT - WHITE | E33: Men's T-Shirts & Polos | F33: T-Shirts | G33: Long Sleeve T-Shirts | H33: White | I33: XS | J33: 8.99 | K33: 5.86 | L33: SALE | M33: EUR | N33: 565 | O33: 3.2 | P33: 38.0 | S33: Yes | T33: 44955 | U33: https://img01.ztat.net/article/ZL100688.jpg | V33: =(Real_Sales[[#This Row],[Price_retail]]-Real_Sales[[#This Row],[Price_current]])/Real_Sales[[#This Row],[Price_retail]] -> 0.34816463 | W33: {=_xlfn.IFS(Real_Sales[[#This Row],[Discount]]=0%,"No Discount",Real_Sales[[#This Row],[Discount]]<=20%,"Light",Real_Sales[[#This Row],[Discount]]<=50%,"Moderate",Real_Sales[[#This Row],[Discount]]<=80%,"High", TRUE,"Very High")} -> Moderate | X33: =IF(Real_Sales[[#This Row],[Price_retail]]>$AC$3,"Premium","Average") -> Average | Y33: =IF(ISNUMBER(SEARCH("Basic",Real_Sales[[#This Row],[Product_name]])),"Yes","No") -> No | Z33: {=_xlfn.IFS(Real_Sales[[#This Row],[Price_retail]]<=15,1, Real_Sales[[#This Row],[Price_retail]]<=30,2, Real_Sales[[#This Row],[Price_retail]]<=50,3,Real_Sales[[#This Row],[Price_retail]]>50,4)} -> 1
A34: ZL100908 | B34: https://www.zalando.de/digel-print-t-shirt---olive-zl100908/ | C34: Digel | D34: Print T-SHIRT - OLIVE | E34: Men's T-Shirts & Polos | F34: T-Shirts | G34: Print T-Shirts | H34: Olive | I34: S | J34: 8.99 | K34: 5.86 | L34: SALE | M34: EUR | N34: 883 | O34: 4.5 | P34: 39.0 | S34: Yes | T34: 44955 | U34: https://img01.ztat.net/article/ZL100908.jpg | V34: =(Real_Sales[[#This Row],[Price_retail]]-Real_Sales[[#This Row],[Price_current]])/Real_Sales[[#This Row],[Price_retail]] -> 0.34816463 | W34: {=_xlfn.IFS(Real_Sales[[#This Row],[Discount]]=0%,"No Discount",Real_Sales[[#This Row],[Discount]]<=20%,"Light",Real_Sales[[#This Row],[Discount]]<=50%,"Moderate",Real_Sales[[#This Row],[Discount]]<=80%,"High", TRUE,"Very High")} -> Moderate | X34: =IF(Real_Sales[[#This Row],[Price_retail]]>$AC$3,"Premium","Average") -> Average | Y34: =IF(ISNUMBER(SEARCH("Basic",Real_Sales[[#This Row],[Product_name]])),"Yes","No") -> No | Z34: {=_xlfn.IFS(Real_Sales[[#This Row],[Price_retail]]<=15,1, Real_Sales[[#This Row],[Price_retail]]<=30,2, Real_Sales[[#This Row],[Price_retail]]<=50,3,Real_Sales[[#This Row],[Price_retail]]>50,4)} -> 1
A35: ZL100350 | B35: https://www.zalando.de/hollister-co.-essential-t-shirt---mint-zl100350/ | C35: Hollister Co. | D35: Essential T-SHIRT - MINT | E35: Men's T-Shirts & Polos | F35: T-Shirts | G35: Print T-Shirts | H35: Mint | I35: M | J35: 8.99 | K35: 5.89 | L35: SALE | M35: EUR | N35: 269 | O35: N/A | P35: 31.0 | S35: Yes | T35: 44955 | U35: https://img01.ztat.net/article/ZL100350.jpg | V35: =(Real_Sales[[#This Row],[Price_retail]]-Real_Sales[[#This Row],[Price_current]])/Real_Sales[[#This Row],[Price_retail]] -> 0.34482759 | W35: {=_xlfn.IFS(Real_Sales[[#This Row],[Discount]]=0%,"No Discount",Real_Sales[[#This Row],[Discount]]<=20%,"Light",Real_Sales[[#This Row],[Discount]]<=50%,"Moderate",Real_Sales[[#This Row],[Discount]]<=80%,"High", TRUE,"Very High")} -> Moderate | X35: =IF(Real_Sales[[#This Row],[Price_retail]]>$AC$3,"Premium","Average") -> Average | Y35: =IF(ISNUMBER(SEARCH("Basic",Real_Sales[[#This Row],[Product_name]])),"Yes","No") -> No | Z35: {=_xlfn.IFS(Real_Sales[[#This Row],[Price_retail]]<=15,1, Real_Sales[[#This Row],[Price_retail]]<=30,2, Real_Sales[[#This Row],[Price_retail]]<=50,3,Real_Sales[[#This Row],[Price_retail]]>50,4)} -> 1
A36: ZL100017 | B36: https://www.zalando.de/cleptomanicx-regular-fit-t-shirt---black-zl100017/ | C36: Cleptomanicx | D36: Regular Fit T-SHIRT - BLACK | E36: Men's T-Shirts & Polos | F36: T-Shirts | G36: Slim Fit T-Shirts | H36: Black | I36: M | J36: 8.99 | K36: 5.93 | L36: SALE | M36: EUR | N36: 435 | O36: 0 | P36: 38.0 | S36: Yes | T36: 44955 | U36: https://img01.ztat.net/article/ZL100017.jpg | V36: =(Real_Sales[[#This Row],[Price_retail]]-Real_Sales[[#This Row],[Price_current]])/Real_Sales[[#This Row],[Price_retail]] -> 0.3403782 | W36: {=_xlfn.IFS(Real_Sales[[#This Row],[Discount]]=0%,"No Discount",Real_Sales[[#This Row],[Discount]]<=20%,"Light",Real_Sales[[#This Row],[Discount]]<=50%,"Moderate",Real_Sales[[#This Row],[Discount]]<=80%,"High", TRUE,"Very High")} -> Moderate | X36: =IF(Real_Sales[[#This Row],[Price_retail]]>$AC$3,"Premium","Average") -> Average | Y36: =IF(ISNUMBER(SEARCH("Basic",Real_Sales[[#This Row],[Product_name]])),"Yes","No") -> No | Z36: {=_xlfn.IFS(Real_Sales[[#This Row],[Price_retail]]<=15,1, Real_Sales[[#This Row],[Price_retail]]<=30,2, Real_Sales[[#This Row],[Price_retail]]<=50,3,Real_Sales[[#This Row],[Price_retail]]>50,4)} -> 1
A37: ZL100950 | B37: https://www.zalando.de/napapijri-basic-t-shirt---dark-green-zl100950/ | C37: Napapijri | D37: Basic T-SHIRT - DARK GREEN | E37: Men's T-Shirts & Polos | F37: T-Shirts | G37: Slim Fit T-Shirts | H37: Dark Green | I37: S | J37: 8.99 | K37: 6 | L37: SALE | M37: EUR | N37: 984 | O37: 3.1 | P37: 32.0 | S37: Yes | T37: 44955 | U37: https://img01.ztat.net/article/ZL100950.jpg | V37: =(Real_Sales[[#This Row],[Price_retail]]-Real_Sales[[#This Row],[Price_current]])/Real_Sales[[#This Row],[Price_retail]] -> 0.33259177 | W37: {=_xlfn.IFS(Real_Sales[[#This Row],[Discount]]=0%,"No Discount",Real_Sales[[#This Row],[Discount]]<=20%,"Light",Real_Sales[[#This Row],[Discount]]<=50%,"Moderate",Real_Sales[[#This Row],[Discount]]<=80%,"High", TRUE,"Very High")} -> Moderate | X37: =IF(Real_Sales[[#This Row],[Price_retail]]>$AC$3,"Premium","Average") -> Average | Y37: =IF(ISNUMBER(SEARCH("Basic",Real_Sales[[#This Row],[Product_name]])),"Yes","No") -> Yes | Z37: {=_xlfn.IFS(Real_Sales[[#This Row],[Price_retail]]<=15,1, Real_Sales[[#This Row],[Price_retail]]<=30,2, Real_Sales[[#This Row],[Price_retail]]<=50,3,Real_Sales[[#This Row],[Price_retail]]>50,4)} -> 1
A38: ZL100224 | B38: https://www.zalando.de/produkt-slim-fit-t-shirt---grey-melange-zl100224/ | C38: Produkt | D38: Slim Fit T-SHIRT - GREY MELANGE | E38: Men's T-Shirts & Polos | F38: T-Shirts | G38: Basic T-Shirts | H38: Grey Melange | I38: XS | J38: 8.99 | K38: 6.02 | L38: SALE | M38: EUR | N38: 400 | O38: 4.7 | P38: 29.0 | S38: No | T38: 44955 | U38: https://img01.ztat.net/article/ZL100224.jpg | V38: =(Real_Sales[[#This Row],[Price_retail]]-Real_Sales[[#This Row],[Price_current]])/Real_Sales[[#This Row],[Price_retail]] -> 0.33036707 | W38: {=_xlfn.IFS(Real_Sales[[#This Row],[Discount]]=0%,"No Discount",Real_Sales[[#This Row],[Discount]]<=20%,"Light",Real_Sales[[#This Row],[Discount]]<=50%,"Moderate",Real_Sales[[#This Row],[Discount]]<=80%,"High", TRUE,"Very High")} -> Moderate | X38: =IF(Real_Sales[[#This Row],[Price_retail]]>$AC$3,"Premium","Average") -> Average | Y38: =IF(ISNUMBER(SEARCH("Basic",Real_Sales[[#This Row],[Product_name]])),"Yes","No") -> No | Z38: {=_xlfn.IFS(Real_Sales[[#This Row],[Price_retail]]<=15,1, Real_Sales[[#This Row],[Price_retail]]<=30,2, Real_Sales[[#This Row],[Price_retail]]<=50,3,Real_Sales[[#This Row],[Price_retail]]>50,4)} -> 1
A39: ZL100035 | B39: https://www.zalando.de/kappa-print-t-shirt---royal-blue-zl100035/ | C39: Kappa | D39: Print T-SHIRT - ROYAL BLUE | E39: Men's T-Shirts & Polos | F39: T-Shirts | G39: Slim Fit T-Shirts | H39: Royal Blue | I39: XS | J39: 8.99 | K39: 6.41 | L39: SALE | M39: EUR | N39: 922 | O39: 4.6 | P39: 33.0 | S39: Yes | T39: 44955 | U39: https://img01.ztat.net/article/ZL100035.jpg | V39: =(Real_Sales[[#This Row],[Price_retail]]-Real_Sales[[#This Row],[Price_current]])/Real_Sales[[#This Row],[Price_retail]] -> 0.28698554 | W39: {=_xlfn.IFS(Real_Sales[[#This Row],[Discount]]=0%,"No Discount",Real_Sales[[#This Row],[Discount]]<=20%,"Light",Real_Sales[[#This Row],[Discount]]<=50%,"Moderate",Real_Sales[[#This Row],[Discount]]<=80%,"High", TRUE,"Very High")} -> Moderate | X39: =IF(Real_Sales[[#This Row],[Price_retail]]>$AC$3,"Premium","Average") -> Average | Y39: =IF(ISNUMBER(SEARCH("Basic",Real_Sales[[#This Row],[Product_name]])),"Yes","No") -> No | Z39: {=_xlfn.IFS(Real_Sales[[#This Row],[Price_retail]]<=15,1, Real_Sales[[#This Row],[Price_retail]]<=30,2, Real_Sales[[#This Row],[Price_retail]]<=50,3,Real_Sales[[#This Row],[Price_retail]]>50,4)} -> 1
A40: ZL100079 | B40: https://www.zalando.de/produkt-slim-fit-t-shirt---rust-zl100079/ | C40: Produkt | D40: Slim Fit T-SHIRT - RUST | E40: Men's T-Shirts & Polos | F40: T-Shirts | G40: Slim Fit T-Shirts | H40: Rust | I40: S | J40: 8.99 | K40: 6.41 | L40: SALE | M40: EUR | N40: 671 | O40: 0 | P40: 33.0 | S40: No | T40: 44955 | U40: https://img01.ztat.net/article/ZL100079.jpg | V40: =(Real_Sales[[#This Row],[Price_retail]]-Real_Sales[[#This Row],[Price_current]])/Real_Sales[[#This Row],[Price_retail]] -> 0.28698554 | W40: {=_xlfn.IFS(Real_Sales[[#This Row],[Discount]]=0%,"No Discount",Real_Sales[[#This Row],[Discount]]<=20%,"Light",Real_Sales[[#This Row],[Discount]]<=50%,"Moderate",Real_Sales[[#This Row],[Discount]]<=80%,"High", TRUE,"Very High")} -> Moderate | X40: =IF(Real_Sales[[#This Row],[Price_retail]]>$AC$3,"Premium","Average") -> Average | Y40: =IF(ISNUMBER(SEARCH("Basic",Real_Sales[[#This Row],[Product_name]])),"Yes","No") -> No | Z40: {=_xlfn.IFS(Real_Sales[[#This Row],[Price_retail]]<=15,1, Real_Sales[[#This Row],[Price_retail]]<=30,2, Real_Sales[[#This Row],[Price_retail]]<=50,3,Real_Sales[[#This Row],[Price_retail]]>50,4)} -> 1
... A58: ZL100229 | B58: https://www.zalando.de/produkt-essential-polo---black-zl100229/ | C58: Produkt | D58: Essential POLO - BLACK | E58: Men's T-Shirts & Polos | F58: Polo Shirts | G58: Basic Polos | H58: Black | I58: XS | J58: 8.99 | K58: 7.18 | L58: SALE | M58: EUR | N58: 530 | O58: 0 | P58: 37.0 | S58: Yes | T58: 44955 | U58: https://img01.ztat.net/article/ZL100229.jpg | V58: =(Real_Sales[[#This Row],[Price_retail]]-Real_Sales[[#This Row],[Price_current]])/Real_Sales[[#This Row],[Price_retail]] -> 0.20133482 | W58: {=_xlfn.IFS(Real_Sales[[#This Row],[Discount]]=0%,"No Discount",Real_Sales[[#This Row],[Discount]]<=20%,"Light",Real_Sales[[#This Row],[Discount]]<=50%,"Moderate",Real_Sales[[#This Row],[Discount]]<=80%,"High", TRUE,"Very High")} -> Moderate | X58: =IF(Real_Sales[[#This Row],[Price_retail]]>$AC$3,"Premium","Average") -> Average | Y58: =IF(ISNUMBER(SEARCH("Basic",Real_Sales[[#This Row],[Product_name]])),"Yes","No") -> No | Z58: {=_xlfn.IFS(Real_Sales[[#This Row],[Price_retail]]<=15,1, Real_Sales[[#This Row],[Price_retail]]<=30,2, Real_Sales[[#This Row],[Price_retail]]<=50,3,Real_Sales[[#This Row],[Price_retail]]>50,4)} -> 1
A59: ZL100355 | B59: https://www.zalando.de/craft-sportswear-print-t-shirt---royal-blue-zl100355/ | C59: Craft | D59: Print T-SHIRT - ROYAL BLUE | E59: Men's T-Shirts & Polos | F59: T-Shirts | G59: Basic T-Shirts | H59: Royal Blue | J59: 8.99 | K59: 7.18 | L59: SALE | M59: EUR | N59: 712 | O59: 3.6 | P59: 34.0 | S59: Yes | T59: 44955 | U59: https://img01.ztat.net/article/ZL100355.jpg | V59: =(Real_Sales[[#This Row],[Price_retail]]-Real_Sales[[#This Row],[Price_current]])/Real_Sales[[#This Row],[Price_retail]] -> 0.20133482 | W59: {=_xlfn.IFS(Real_Sales[[#This Row],[Discount]]=0%,"No Discount",Real_Sales[[#This Row],[Discount]]<=20%,"Light",Real_Sales[[#This Row],[Discount]]<=50%,"Moderate",Real_Sales[[#This Row],[Discount]]<=80%,"High", TRUE,"Very High")} -> Moderate | X59: =IF(Real_Sales[[#This Row],[Price_retail]]>$AC$3,"Premium","Average") -> Average | Y59: =IF(ISNUMBER(SEARCH("Basic",Real_Sales[[#This Row],[Product_name]])),"Yes","No") -> No | Z59: {=_xlfn.IFS(Real_Sales[[#This Row],[Price_retail]]<=15,1, Real_Sales[[#This Row],[Price_retail]]<=30,2, Real_Sales[[#This Row],[Price_retail]]<=50,3,Real_Sales[[#This Row],[Price_retail]]>50,4)} -> 1
A60: ZL100807 | B60: https://www.zalando.de/calvin-klein-regular-fit-polo---red-zl100807/ | C60: Calvin Klein | D60: Regular Fit POLO - RED | E60: Men's T-Shirts & Polos | F60: Polo Shirts | G60: Slim Fit Polos | H60: Red | I60: XS | J60: 8.99 | K60: 7.19 | L60: SALE | M60: EUR | N60: 310 | O60: 4.0 | P60: 41.0 | S60: Yes | T60: 44955 | U60: https://img01.ztat.net/article/ZL100807.jpg | V60: =(Real_Sales[[#This Row],[Price_retail]]-Real_Sales[[#This Row],[Price_current]])/Real_Sales[[#This Row],[Price_retail]] -> 0.20022247 | W60: {=_xlfn.IFS(Real_Sales[[#This Row],[Discount]]=0%,"No Discount",Real_Sales[[#This Row],[Discount]]<=20%,"Light",Real_Sales[[#This Row],[Discount]]<=50%,"Moderate",Real_Sales[[#This Row],[Discount]]<=80%,"High", TRUE,"Very High")} -> Moderate | X60: =IF(Real_Sales[[#This Row],[Price_retail]]>$AC$3,"Premium","Average") -> Average | Y60: =IF(ISNUMBER(SEARCH("Basic",Real_Sales[[#This Row],[Product_name]])),"Yes","No") -> No | Z60: {=_xlfn.IFS(Real_Sales[[#This Row],[Price_retail]]<=15,1, Real_Sales[[#This Row],[Price_retail]]<=30,2, Real_Sales[[#This Row],[Price_retail]]<=50,3,Real_Sales[[#This Row],[Price_retail]]>50,4)} -> 1
A61: ZL100487 | B61: https://www.zalando.de/jack-wolfskin-basic-polo---navy-zl100487/ | C61: Jack Wolfskin | D61: Basic POLO - NAVY | E61: Men's T-Shirts & Polos | F61: Polo Shirts | G61: Slim Fit Polos | H61: Navy | I61: XS | J61: 8.99 | K61: 7.28 | L61: SALE | M61: EUR | N61: 242 | O61: 4.3 | P61: 29.0 | S61: Yes | T61: 44955 | U61: https://img01.ztat.net/article/ZL100487.jpg | V61: =(Real_Sales[[#This Row],[Price_retail]]-Real_Sales[[#This Row],[Price_current]])/Real_Sales[[#This Row],[Price_retail]] -> 0.19021135 | W61: {=_xlfn.IFS(Real_Sales[[#This Row],[Discount]]=0%,"No Discount",Real_Sales[[#This Row],[Discount]]<=20%,"Light",Real_Sales[[#This Row],[Discount]]<=50%,"Moderate",Real_Sales[[#This Row],[Discount]]<=80%,"High", TRUE,"Very High")} -> Light | X61: =IF(Real_Sales[[#This Row],[Price_retail]]>$AC$3,"Premium","Average") -> Average | Y61: =IF(ISNUMBER(SEARCH("Basic",Real_Sales[[#This Row],[Product_name]])),"Yes","No") -> Yes | Z61: {=_xlfn.IFS(Real_Sales[[#This Row],[Price_retail]]<=15,1, Real_Sales[[#This Row],[Price_retail]]<=30,2, Real_Sales[[#This Row],[Price_retail]]<=50,3,Real_Sales[[#This Row],[Price_retail]]>50,4)} -> 1
A62: ZL100610 | B62: https://www.zalando.de/weekday-basic-polo---dark-green-zl100610/ | C62: Weekday | D62: Basic POLO - DARK GREEN | E62: Men's T-Shirts & Polos | F62: Polo Shirts | G62: Pique Polos | H62: Dark Green | I62: XS | J62: 8.99 | K62: 7.52 | L62: SALE | M62: EUR | N62: 687 | O62: 4.0 | P62: 31.0 | S62: Yes | T62: 44955 | U62: https://img01.ztat.net/article/ZL100610.jpg | V62: =(Real_Sales[[#This Row],[Price_retail]]-Real_Sales[[#This Row],[Price_current]])/Real_Sales[[#This Row],[Price_retail]] -> 0.16351502 | W62: {=_xlfn.IFS(Real_Sales[[#This Row],[Discount]]=0%,"No Discount",Real_Sales[[#This Row],[Discount]]<=20%,"Light",Real_Sales[[#This Row],[Discount]]<=50%,"Moderate",Real_Sales[[#This Row],[Discount]]<=80%,"High", TRUE,"Very High")} -> Light | X62: =IF(Real_Sales[[#This Row],[Price_retail]]>$AC$3,"Premium","Average") -> Average | Y62: =IF(ISNUMBER(SEARCH("Basic",Real_Sales[[#This Row],[Product_name]])),"Yes","No") -> Yes | Z62: {=_xlfn.IFS(Real_Sales[[#This Row],[Price_retail]]<=15,1, Real_Sales[[#This Row],[Price_retail]]<=30,2, Real_Sales[[#This Row],[Price_retail]]<=50,3,Real_Sales[[#This Row],[Price_retail]]>50,4)} -> 1
A63: ZL100090 | B63: https://www.zalando.de/yourturn-essential-t-shirt---rust-zl100090/ | C63: Yourturn | D63: Essential T-SHIRT - RUST | E63: Men's T-Shirts & Polos | F63: T-Shirts | G63: Print T-Shirts | H63: Rust | I63: XS | J63: 8.99 | K63: 7.69 | L63: SALE | M63: EUR | N63: 410 | O63: 4.3 | P63: 44.0 | S63: Yes | T63: 44955 | U63: https://img01.ztat.net/article/ZL100090.jpg | V63: =(Real_Sales[[#This Row],[Price_retail]]-Real_Sales[[#This Row],[Price_current]])/Real_Sales[[#This Row],[Price_retail]] -> 0.14460512 | W63: {=_xlfn.IFS(Real_Sales[[#This Row],[Discount]]=0%,"No Discount",Real_Sales[[#This Row],[Discount]]<=20%,"Light",Real_Sales[[#This Row],[Discount]]<=50%,"Moderate",Real_Sales[[#This Row],[Discount]]<=80%,"High", TRUE,"Very High")} -> Light | X63: =IF(Real_Sales[[#This Row],[Price_retail]]>$AC$3,"Premium","Average") -> Average | Y63: =IF(ISNUMBER(SEARCH("Basic",Real_Sales[[#This Row],[Product_name]])),"Yes","No") -> No | Z63: {=_xlfn.IFS(Real_Sales[[#This Row],[Price_retail]]<=15,1, Real_Sales[[#This Row],[Price_retail]]<=30,2, Real_Sales[[#This Row],[Price_retail]]<=50,3,Real_Sales[[#This Row],[Price_retail]]>50,4)} -> 1
A64: ZL100591 | B64: https://www.zalando.de/superdry-print-t-shirt---anthracite-zl100591/ | C64: Superdry | D64: Print T-SHIRT - ANTHRACITE | E64: Men's T-Shirts & Polos | F64: T-Shirts | G64: Basic T-Shirts | H64: Anthracite | I64: XS | J64: 8.99 | K64: 7.74 | L64: SALE | M64: EUR | N64: 607 | O64: 3.9 | P64: 35.0 | S64: Yes | T64: 44955 | U64: https://img01.ztat.net/article/ZL100591.jpg | V64: =(Real_Sales[[#This Row],[Price_retail]]-Real_Sales[[#This Row],[Price_current]])/Real_Sales[[#This Row],[Price_retail]] -> 0.13904338 | W64: {=_xlfn.IFS(Real_Sales[[#This Row],[Discount]]=0%,"No Discount",Real_Sales[[#This Row],[Discount]]<=20%,"Light",Real_Sales[[#This Row],[Discount]]<=50%,"Moderate",Real_Sales[[#This Row],[Discount]]<=80%,"High", TRUE,"Very High")} -> Light | X64: =IF(Real_Sales[[#This Row],[Price_retail]]>$AC$3,"Premium","Average") -> Average | Y64: =IF(ISNUMBER(SEARCH("Basic",Real_Sales[[#This Row],[Product_name]])),"Yes","No") -> No | Z64: {=_xlfn.IFS(Real_Sales[[#This Row],[Price_retail]]<=15,1, Real_Sales[[#This Row],[Price_retail]]<=30,2, Real_Sales[[#This Row],[Price_retail]]<=50,3,Real_Sales[[#This Row],[Price_retail]]>50,4)} -> 1
A65: ZL100207 | B65: https://www.zalando.de/pier-1-regular-fit-polo---dark-green-zl100207/ | C65: Pier One | D65: Regular Fit POLO - DARK GREEN | E65: Men's T-Shirts & Polos | F65: Polo Shirts | G65: Basic Polos | H65: Dark Green | I65: S | J65: 8.99 | K65: 7.83 | L65: SALE | M65: EUR | N65: 692 | O65: 3.2 | P65: 0 | S65: Yes | T65: 44955 | U65: https://img01.ztat.net/article/ZL100207.jpg | V65: =(Real_Sales[[#This Row],[Price_retail]]-Real_Sales[[#This Row],[Price_current]])/Real_Sales[[#This Row],[Price_retail]] -> 0.12903226 | W65: {=_xlfn.IFS(Real_Sales[[#This Row],[Discount]]=0%,"No Discount",Real_Sales[[#This Row],[Discount]]<=20%,"Light",Real_Sales[[#This Row],[Discount]]<=50%,"Moderate",Real_Sales[[#This Row],[Discount]]<=80%,"High", TRUE,"Very High")} -> Light | X65: =IF(Real_Sales[[#This Row],[Price_retail]]>$AC$3,"Premium","Average") -> Average | Y65: =IF(ISNUMBER(SEARCH("Basic",Real_Sales[[#This Row],[Product_name]])),"Yes","No") -> No | Z65: {=_xlfn.IFS(Real_Sales[[#This Row],[Price_retail]]<=15,1, Real_Sales[[#This Row],[Price_retail]]<=30,2, Real_Sales[[#This Row],[Price_retail]]<=50,3,Real_Sales[[#This Row],[Price_retail]]>50,4)} -> 1
A66: ZL100361 | B66: https://www.zalando.de/adidas-performance-regular-fit-polo---denim-blue-zl100361/ | C66: Adidas Performance | D66: Regular Fit POLO - DENIM BLUE | E66: Men's T-Shirts & Polos | F66: Polo Shirts | G66: Slim Fit Polos | H66: Denim Blue | I66: XS | J66: 8.99 | K66: 7.97 | L66: SALE | M66: EUR | N66: 896 | O66: 3.1 | P66: 35.0 | S66: Yes | T66: 44955 | U66: https://img01.ztat.net/article/ZL100361.jpg | V66: =(Real_Sales[[#This Row],[Price_retail]]-Real_Sales[[#This Row],[Price_current]])/Real_Sales[[#This Row],[Price_retail]] -> 0.1134594 | W66: {=_xlfn.IFS(Real_Sales[[#This Row],[Discount]]=0%,"No Discount",Real_Sales[[#This Row],[Discount]]<=20%,"Light",Real_Sales[[#This Row],[Discount]]<=50%,"Moderate",Real_Sales[[#This Row],[Discount]]<=80%,"High", TRUE,"Very High")} -> Light | X66: =IF(Real_Sales[[#This Row],[Price_retail]]>$AC$3,"Premium","Average") -> Average | Y66: =IF(ISNUMBER(SEARCH("Basic",Real_Sales[[#This Row],[Product_name]])),"Yes","No") -> No | Z66: {=_xlfn.IFS(Real_Sales[[#This Row],[Price_retail]]<=15,1, Real_Sales[[#This Row],[Price_retail]]<=30,2, Real_Sales[[#This Row],[Price_retail]]<=50,3,Real_Sales[[#This Row],[Price_retail]]>50,4)} -> 1
A67: ZL100452 | B67: https://www.zalando.de/adidas-performance-basic-t-shirt---dark-blue-zl100452/ | C67: Adidas Performance | D67: Basic T-SHIRT - DARK BLUE | E67: Men's T-Shirts & Polos | F67: T-Shirts | G67: Basic T-Shirts | H67: Dark Blue | I67: XS | J67: 8.99 | K67: 7.98 | L67: SALE | M67: EUR | N67: 344 | O67: 4.9 | P67: 29.0 | S67: No | T67: 44955 | U67: https://img01.ztat.net/article/ZL100452.jpg | V67: =(Real_Sales[[#This Row],[Price_retail]]-Real_Sales[[#This Row],[Price_current]])/Real_Sales[[#This Row],[Price_retail]] -> 0.11234705 | W67: {=_xlfn.IFS(Real_Sales[[#This Row],[Discount]]=0%,"No Discount",Real_Sales[[#This Row],[Discount]]<=20%,"Light",Real_Sales[[#This Row],[Discount]]<=50%,"Moderate",Real_Sales[[#This Row],[Discount]]<=80%,"High", TRUE,"Very High")} -> Light | X67: =IF(Real_Sales[[#This Row],[Price_retail]]>$AC$3,"Premium","Average") -> Average | Y67: =IF(ISNUMBER(SEARCH("Basic",Real_Sales[[#This Row],[Product_name]])),"Yes","No") -> Yes | Z67: {=_xlfn.IFS(Real_Sales[[#This Row],[Price_retail]]<=15,1, Real_Sales[[#This Row],[Price_retail]]<=30,2, Real_Sales[[#This Row],[Price_retail]]<=50,3,Real_Sales[[#This Row],[Price_retail]]>50,4)} -> 1
A68: ZL100235 | B68: https://www.zalando.de/mango-man-regular-fit-t-shirt---dark-blue-zl100235/ | C68: Mango Man | D68: Regular Fit T-SHIRT - DARK BLUE | E68: Men's T-Shirts & Polos | F68: T-Shirts | G68: Long Sleeve T-Shirts | H68: Dark Blue | I68: XS | J68: 8.99 | K68: 8.54 | L68: SALE | M68: EUR | N68: 13 | O68: 4.4 | P68: 0 | S68: No | T68: 44955 | U68: https://img01.ztat.net/article/ZL100235.jpg | V68: =(Real_Sales[[#This Row],[Price_retail]]-Real_Sales[[#This Row],[Price_current]])/Real_Sales[[#This Row],[Price_retail]] -> 0.050055617 | W68: {=_xlfn.IFS(Real_Sales[[#This Row],[Discount]]=0%,"No Discount",Real_Sales[[#This Row],[Discount]]<=20%,"Light",Real_Sales[[#This Row],[Discount]]<=50%,"Moderate",Real_Sales[[#This Row],[Discount]]<=80%,"High", TRUE,"Very High")} -> Light | X68: =IF(Real_Sales[[#This Row],[Price_retail]]>$AC$3,"Premium","Average") -> Average | Y68: =IF(ISNUMBER(SEARCH("Basic",Real_Sales[[#This Row],[Product_name]])),"Yes","No") -> No | Z68: {=_xlfn.IFS(Real_Sales[[#This Row],[Price_retail]]<=15,1, Real_Sales[[#This Row],[Price_retail]]<=30,2, Real_Sales[[#This Row],[Price_retail]]<=50,3,Real_Sales[[#This Row],[Price_retail]]>50,4)} -> 1
A69: ZL100635 | B69: https://www.zalando.de/the-north-face-print-t-shirt---beige-zl100635/ | C69: The North Face | D69: Print T-SHIRT - BEIGE | E69: Men's T-Shirts & Polos | F69: T-Shirts | G69: Long Sleeve T-Shirts | H69: Beige | I69: S | J69: 8.99 | K69: 8.54 | L69: SALE | M69: EUR | N69: 387 | O69: 3.4 | P69: 33.0 | S69: Yes | T69: 44955 | U69: https://img01.ztat.net/article/ZL100635.jpg | V69: =(Real_Sales[[#This Row],[Price_retail]]-Real_Sales[[#This Row],[Price_current]])/Real_Sales[[#This Row],[Price_retail]] -> 0.050055617 | W69: {=_xlfn.IFS(Real_Sales[[#This Row],[Discount]]=0%,"No Discount",Real_Sales[[#This Row],[Discount]]<=20%,"Light",Real_Sales[[#This Row],[Discount]]<=50%,"Moderate",Real_Sales[[#This Row],[Discount]]<=80%,"High", TRUE,"Very High")} -> Light | X69: =IF(Real_Sales[[#This Row],[Price_retail]]>$AC$3,"Premium","Average") -> Average | Y69: =IF(ISNUMBER(SEARCH("Basic",Real_Sales[[#This Row],[Product_name]])),"Yes","No") -> No | Z69: {=_xlfn.IFS(Real_Sales[[#This Row],[Price_retail]]<=15,1, Real_Sales[[#This Row],[Price_retail]]<=30,2, Real_Sales[[#This Row],[Price_retail]]<=50,3,Real_Sales[[#This Row],[Price_retail]]>50,4)} -> 1
A70: ZL100009 | B70: https://www.zalando.de/jack-and-jones-slim-fit-polo---denim-blue-zl100009/ | C70: Jack & Jones | D70: Slim Fit POLO - DENIM BLUE | E70: Men's T-Shirts & Polos | F70: Polo Shirts | G70: Slim Fit Polos | H70: Denim Blue | I70: S | J70: 8.99 | K70: 8.99 | L70: Regular Price | M70: EUR | N70: 741 | O70: 3.7 | P70: 43.0 | S70: No | T70: 44955 | U70: https://img01.ztat.net/article/ZL100009.jpg | V70: =(Real_Sales[[#This Row],[Price_retail]]-Real_Sales[[#This Row],[Price_current]])/Real_Sales[[#This Row],[Price_retail]] -> 0 | W70: {=_xlfn.IFS(Real_Sales[[#This Row],[Discount]]=0%,"No Discount",Real_Sales[[#This Row],[Discount]]<=20%,"Light",Real_Sales[[#This Row],[Discount]]<=50%,"Moderate",Real_Sales[[#This Row],[Discount]]<=80%,"High", TRUE,"Very High")} -> No Discount | X70: =IF(Real_Sales[[#This Row],[Price_retail]]>$AC$3,"Premium","Average") -> Average | Y70: =IF(ISNUMBER(SEARCH("Basic",Real_Sales[[#This Row],[Product_name]])),"Yes","No") -> No | Z70: {=_xlfn.IFS(Real_Sales[[#This Row],[Price_retail]]<=15,1, Real_Sales[[#This Row],[Price_retail]]<=30,2, Real_Sales[[#This Row],[Price_retail]]<=50,3,Real_Sales[[#This Row],[Price_retail]]>50,4)} -> 1
A71: ZL100044 | B71: https://www.zalando.de/only-and-sons-denim-regular-fit-t-shirt---beige-zl100044/ | C71: Only & Sons | D71: Regular Fit T-SHIRT - BEIGE | E71: Men's T-Shirts & Polos | F71: T-Shirts | G71: Long Sleeve T-Shirts | H71: Beige | I71: XS | J71: 8.99 | K71: 8.99 | L71: Regular Price | M71: EUR | N71: 67 | O71: 4.8 | P71: 34.0 | S71: No | T71: 44955 | U71: https://img01.ztat.net/article/ZL100044.jpg | V71: =(Real_Sales[[#This Row],[Price_retail]]-Real_Sales[[#This Row],[Price_current]])/Real_Sales[[#This Row],[Price_retail]] -> 0 | W71: {=_xlfn.IFS(Real_Sales[[#This Row],[Discount]]=0%,"No Discount",Real_Sales[[#This Row],[Discount]]<=20%,"Light",Real_Sales[[#This Row],[Discount]]<=50%,"Moderate",Real_Sales[[#This Row],[Discount]]<=80%,"High", TRUE,"Very High")} -> No Discount | X71: =IF(Real_Sales[[#This Row],[Price_retail]]>$AC$3,"Premium","Average") -> Average | Y71: =IF(ISNUMBER(SEARCH("Basic",Real_Sales[[#This Row],[Product_name]])),"Yes","No") -> No | Z71: {=_xlfn.IFS(Real_Sales[[#This Row],[Price_retail]]<=15,1, Real_Sales[[#This Row],[Price_retail]]<=30,2, Real_Sales[[#This Row],[Price_retail]]<=50,3,Real_Sales[[#This Row],[Price_retail]]>50,4)} -> 1
... A74: ZL100105 | B74: https://www.zalando.de/bershka-regular-fit-polo---bordeaux-zl100105/ | C74: Bershka | D74: Regular Fit POLO - BORDEAUX | E74: Men's T-Shirts & Polos | F74: Polo Shirts | G74: Basic Polos | H74: Bordeaux | I74: S | J74: 8.99 | K74: 8.99 | L74: Regular Price | M74: EUR | N74: 887 | O74: 4.7 | P74: 30.0 | S74: No | T74: 44955 | U74: https://img01.ztat.net/article/ZL100105.jpg | V74: =(Real_Sales[[#This Row],[Price_retail]]-Real_Sales[[#This Row],[Price_current]])/Real_Sales[[#This Row],[Price_retail]] -> 0 | W74: {=_xlfn.IFS(Real_Sales[[#This Row],[Discount]]=0%,"No Discount",Real_Sales[[#This Row],[Discount]]<=20%,"Light",Real_Sales[[#This Row],[Discount]]<=50%,"Moderate",Real_Sales[[#This Row],[Discount]]<=80%,"High", TRUE,"Very High")} -> No Discount | X74: =IF(Real_Sales[[#This Row],[Price_retail]]>$AC$3,"Premium","Average") -> Average | Y74: =IF(ISNUMBER(SEARCH("Basic",Real_Sales[[#This Row],[Product_name]])),"Yes","No") -> No | Z74: {=_xlfn.IFS(Real_Sales[[#This Row],[Price_retail]]<=15,1, Real_Sales[[#This Row],[Price_retail]]<=30,2, Real_Sales[[#This Row],[Price_retail]]<=50,3,Real_Sales[[#This Row],[Price_retail]]>50,4)} -> 1
A75: ZL100106 | B75: https://www.zalando.de/nike-basic-polo---rust-zl100106/ | C75: Nike | D75: Basic POLO - RUST | E75: Men's T-Shirts & Polos | F75: Polo Shirts | G75: Pique Polos | I75: XS | J75: 8.99 | K75: 8.99 | L75: Regular Price | M75: EUR | N75: 640 | O75: 4.6 | P75: 41.0 | S75: Yes | T75: 44955 | U75: https://img01.ztat.net/article/ZL100106.jpg | V75: =(Real_Sales[[#This Row],[Price_retail]]-Real_Sales[[#This Row],[Price_current]])/Real_Sales[[#This Row],[Price_retail]] -> 0 | W75: {=_xlfn.IFS(Real_Sales[[#This Row],[Discount]]=0%,"No Discount",Real_Sales[[#This Row],[Discount]]<=20%,"Light",Real_Sales[[#This Row],[Discount]]<=50%,"Moderate",Real_Sales[[#This Row],[Discount]]<=80%,"High", TRUE,"Very High")} -> No Discount | X75: =IF(Real_Sales[[#This Row],[Price_retail]]>$AC$3,"Premium","Average") -> Average | Y75: =IF(ISNUMBER(SEARCH("Basic",Real_Sales[[#This Row],[Product_name]])),"Yes","No") -> Yes | Z75: {=_xlfn.IFS(Real_Sales[[#This Row],[Price_retail]]<=15,1, Real_Sales[[#This Row],[Price_retail]]<=30,2, Real_Sales[[#This Row],[Price_retail]]<=50,3,Real_Sales[[#This Row],[Price_retail]]>50,4)} -> 1
A76: ZL100131 | B76: https://www.zalando.de/cars-print-t-shirt---bordeaux-zl100131/ | C76: Cars Jeans | D76: Print T-SHIRT - BORDEAUX | E76: Men's T-Shirts & Polos | F76: T-Shirts | G76: Long Sleeve T-Shirts | H76: Bordeaux | I76: S | J76: 8.99 | K76: 8.99 | L76: Regular Price | M76: EUR | N76: 287 | O76: 0 | P76: 33.0 | S76: Yes | T76: 44955 | U76: https://img01.ztat.net/article/ZL100131.jpg | V76: =(Real_Sales[[#This Row],[Price_retail]]-Real_Sales[[#This Row],[Price_current]])/Real_Sales[[#This Row],[Price_retail]] -> 0 | W76: {=_xlfn.IFS(Real_Sales[[#This Row],[Discount]]=0%,"No Discount",Real_Sales[[#This Row],[Discount]]<=20%,"Light",Real_Sales[[#This Row],[Discount]]<=50%,"Moderate",Real_Sales[[#This Row],[Discount]]<=80%,"High", TRUE,"Very High")} -> No Discount | X76: =IF(Real_Sales[[#This Row],[Price_retail]]>$AC$3,"Premium","Average") -> Average | Y76: =IF(ISNUMBER(SEARCH("Basic",Real_Sales[[#This Row],[Product_name]])),"Yes","No") -> No | Z76: {=_xlfn.IFS(Real_Sales[[#This Row],[Price_retail]]<=15,1, Real_Sales[[#This Row],[Price_retail]]<=30,2, Real_Sales[[#This Row],[Price_retail]]<=50,3,Real_Sales[[#This Row],[Price_retail]]>50,4)} -> 1
A77: ZL100190 | B77: https://www.zalando.de/fila-print-t-shirt---royal-blue-zl100190/ | C77: Fila | D77: Print T-SHIRT - ROYAL BLUE | E77: Men's T-Shirts & Polos | F77: T-Shirts | G77: Slim Fit T-Shirts | H77: Royal Blue | I77: M | J77: 8.99 | K77: 8.99 | L77: Regular Price | M77: EUR | N77: 501 | O77: 4.3 | P77: 34.0 | S77: Yes | T77: 44955 | U77: https://img01.ztat.net/article/ZL100190.jpg | V77: =(Real_Sales[[#This Row],[Price_retail]]-Real_Sales[[#This Row],[Price_current]])/Real_Sales[[#This Row],[Price_retail]] -> 0 | W77: {=_xlfn.IFS(Real_Sales[[#This Row],[Discount]]=0%,"No Discount",Real_Sales[[#This Row],[Discount]]<=20%,"Light",Real_Sales[[#This Row],[Discount]]<=50%,"Moderate",Real_Sales[[#This Row],[Discount]]<=80%,"High", TRUE,"Very High")} -> No Discount | X77: =IF(Real_Sales[[#This Row],[Price_retail]]>$AC$3,"Premium","Average") -> Average | Y77: =IF(ISNUMBER(SEARCH("Basic",Real_Sales[[#This Row],[Product_name]])),"Yes","No") -> No | Z77: {=_xlfn.IFS(Real_Sales[[#This Row],[Price_retail]]<=15,1, Real_Sales[[#This Row],[Price_retail]]<=30,2, Real_Sales[[#This Row],[Price_retail]]<=50,3,Real_Sales[[#This Row],[Price_retail]]>50,4)} -> 1
A78: ZL100226 | B78: https://www.zalando.de/guess-essential-t-shirt---olive-zl100226/ | C78: Guess | D78: Essential T-SHIRT - OLIVE | E78: Men's T-Shirts & Polos | F78: T-Shirts | G78: Long Sleeve T-Shirts | H78: Olive | I78: S | J78: 8.99 | K78: 8.99 | L78: Regular Price | M78: EUR | N78: 796 | O78: 4.2 | P78: 36.0 | S78: Yes | T78: 44955 | U78: https://img01.ztat.net/article/ZL100226.jpg | V78: =(Real_Sales[[#This Row],[Price_retail]]-Real_Sales[[#This Row],[Price_current]])/Real_Sales[[#This Row],[Price_retail]] -> 0 | W78: {=_xlfn.IFS(Real_Sales[[#This Row],[Discount]]=0%,"No Discount",Real_Sales[[#This Row],[Discount]]<=20%,"Light",Real_Sales[[#This Row],[Discount]]<=50%,"Moderate",Real_Sales[[#This Row],[Discount]]<=80%,"High", TRUE,"Very High")} -> No Discount | X78: =IF(Real_Sales[[#This Row],[Price_retail]]>$AC$3,"Premium","Average") -> Average | Y78: =IF(ISNUMBER(SEARCH("Basic",Real_Sales[[#This Row],[Product_name]])),"Yes","No") -> No | Z78: {=_xlfn.IFS(Real_Sales[[#This Row],[Price_retail]]<=15,1, Real_Sales[[#This Row],[Price_retail]]<=30,2, Real_Sales[[#This Row],[Price_retail]]<=50,3,Real_Sales[[#This Row],[Price_retail]]>50,4)} -> 1
A79: ZL100238 | B79: https://www.zalando.de/produkt-basic-t-shirt---white-zl100238/ | C79: Produkt | D79: Basic T-SHIRT - WHITE | E79: Men's T-Shirts & Polos | F79: T-Shirts | G79: Basic T-Shirts | H79: White | I79: XS | J79: 8.99 | K79: 8.99 | L79: Regular Price | M79: EUR | N79: 773 | O79: 4.5 | P79: 39.0 | S79: Yes | T79: 44955 | U79: https://img01.ztat.net/article/ZL100238.jpg | V79: =(Real_Sales[[#This Row],[Price_retail]]-Real_Sales[[#This Row],[Price_current]])/Real_Sales[[#This Row],[Price_retail]] -> 0 | W79: {=_xlfn.IFS(Real_Sales[[#This Row],[Discount]]=0%,"No Discount",Real_Sales[[#This Row],[Discount]]<=20%,"Light",Real_Sales[[#This Row],[Discount]]<=50%,"Moderate",Real_Sales[[#This Row],[Discount]]<=80%,"High", TRUE,"Very High")} -> No Discount | X79: =IF(Real_Sales[[#This Row],[Price_retail]]>$AC$3,"Premium","Average") -> Average | Y79: =IF(ISNUMBER(SEARCH("Basic",Real_Sales[[#This Row],[Product_name]])),"Yes","No") -> Yes | Z79: {=_xlfn.IFS(Real_Sales[[#This Row],[Price_retail]]<=15,1, Real_Sales[[#This Row],[Price_retail]]<=30,2, Real_Sales[[#This Row],[Price_retail]]<=50,3,Real_Sales[[#This Row],[Price_retail]]>50,4)} -> 1
A80: ZL100243 | B80: https://www.zalando.de/armani-exchange-basic-t-shirt---mint-zl100243/ | C80: Armani Exchange | D80: Basic T-SHIRT - MINT | E80: Men's T-Shirts & Polos | F80: T-Shirts | G80: Basic T-Shirts | H80: Mint | I80: S | J80: 8.99 | K80: 8.99 | L80: Regular Price | M80: EUR | N80: 821 | O80: 4.2 | P80: 23.0 | S80: Yes | T80: 44955 | U80: https://img01.ztat.net/article/ZL100243.jpg | V80: =(Real_Sales[[#This Row],[Price_retail]]-Real_Sales[[#This Row],[Price_current]])/Real_Sales[[#This Row],[Price_retail]] -> 0 | W80: {=_xlfn.IFS(Real_Sales[[#This Row],[Discount]]=0%,"No Discount",Real_Sales[[#This Row],[Discount]]<=20%,"Light",Real_Sales[[#This Row],[Discount]]<=50%,"Moderate",Real_Sales[[#This Row],[Discount]]<=80%,"High", TRUE,"Very High")} -> No Discount | X80: =IF(Real_Sales[[#This Row],[Price_retail]]>$AC$3,"Premium","Average") -> Average | Y80: =IF(ISNUMBER(SEARCH("Basic",Real_Sales[[#This Row],[Product_name]])),"Yes","No") -> Yes | Z80: {=_xlfn.IFS(Real_Sales[[#This Row],[Price_retail]]<=15,1, Real_Sales[[#This Row],[Price_retail]]<=30,2, Real_Sales[[#This Row],[Price_retail]]<=50,3,Real_Sales[[#This Row],[Price_retail]]>50,4)} -> 1
A81: ZL100256 | B81: https://www.zalando.de/anthracite-basic-t-shirt---dark-green-zl100256/ | C81: Anthracite | D81: Basic T-SHIRT - DARK GREEN | E81: Men's T-Shirts & Polos | F81: T-Shirts | G81: Basic T-Shirts | H81: Dark Green | I81: M | J81: 8.99 | K81: 8.99 | L81: Regular Price | M81: EUR | N81: 298 | O81: 4.1 | P81: 25.0 | S81: No | T81: 44955 | U81: https://img01.ztat.net/article/ZL100256.jpg | V81: =(Real_Sales[[#This Row],[Price_retail]]-Real_Sales[[#This Row],[Price_current]])/Real_Sales[[#This Row],[Price_retail]] -> 0 | W81: {=_xlfn.IFS(Real_Sales[[#This Row],[Discount]]=0%,"No Discount",Real_Sales[[#This Row],[Discount]]<=20%,"Light",Real_Sales[[#This Row],[Discount]]<=50%,"Moderate",Real_Sales[[#This Row],[Discount]]<=80%,"High", TRUE,"Very High")} -> No Discount | X81: =IF(Real_Sales[[#This Row],[Price_retail]]>$AC$3,"Premium","Average") -> Average | Y81: =IF(ISNUMBER(SEARCH("Basic",Real_Sales[[#This Row],[Product_name]])),"Yes","No") -> Yes | Z81: {=_xlfn.IFS(Real_Sales[[#This Row],[Price_retail]]<=15,1, Real_Sales[[#This Row],[Price_retail]]<=30,2, Real_Sales[[#This Row],[Price_retail]]<=50,3,Real_Sales[[#This Row],[Price_retail]]>50,4)} -> 1
A82: ZL100262 | B82: https://www.zalando.de/craft-sportswear-regular-fit-t-shirt---off-white-zl100262/ | C82: Craft | D82: Regular Fit T-SHIRT - OFF WHITE | E82: Men's T-Shirts & Polos | F82: T-Shirts | G82: Slim Fit T-Shirts | H82: Off White | I82: S | J82: 8.99 | K82: 8.99 | L82: Regular Price | M82: EUR | N82: 745 | O82: 4.6 | P82: 27.0 | S82: Yes | T82: 44955 | U82: https://img01.ztat.net/article/ZL100262.jpg | V82: =(Real_Sales[[#This Row],[Price_retail]]-Real_Sales[[#This Row],[Price_current]])/Real_Sales[[#This Row],[Price_retail]] -> 0 | W82: {=_xlfn.IFS(Real_Sales[[#This Row],[Discount]]=0%,"No Discount",Real_Sales[[#This Row],[Discount]]<=20%,"Light",Real_Sales[[#This Row],[Discount]]<=50%,"Moderate",Real_Sales[[#This Row],[Discount]]<=80%,"High", TRUE,"Very High")} -> No Discount | X82: =IF(Real_Sales[[#This Row],[Price_retail]]>$AC$3,"Premium","Average") -> Average | Y82: =IF(ISNUMBER(SEARCH("Basic",Real_Sales[[#This Row],[Product_name]])),"Yes","No") -> No | Z82: {=_xlfn.IFS(Real_Sales[[#This Row],[Price_retail]]<=15,1, Real_Sales[[#This Row],[Price_retail]]<=30,2, Real_Sales[[#This Row],[Price_retail]]<=50,3,Real_Sales[[#This Row],[Price_retail]]>50,4)} -> 1
A83: ZL100263 | B83: https://www.zalando.de/billabong-slim-fit-polo---white-zl100263/ | C83: Billabong | D83: Slim Fit POLO - WHITE | E83: Men's T-Shirts & Polos | F83: Polo Shirts | G83: Slim Fit Polos | H83: White | I83: XS | J83: 8.99 | K83: 8.99 | L83: Regular Price | M83: EUR | N83: 211 | O83: 4.9 | P83: 29.0 | S83: Yes | T83: 44955 | U83: https://img01.ztat.net/article/ZL100263.jpg | V83: =(Real_Sales[[#This Row],[Price_retail]]-Real_Sales[[#This Row],[Price_current]])/Real_Sales[[#This Row],[Price_retail]] -> 0 | W83: {=_xlfn.IFS(Real_Sales[[#This Row],[Discount]]=0%,"No Discount",Real_Sales[[#This Row],[Discount]]<=20%,"Light",Real_Sales[[#This Row],[Discount]]<=50%,"Moderate",Real_Sales[[#This Row],[Discount]]<=80%,"High", TRUE,"Very High")} -> No Discount | X83: =IF(Real_Sales[[#This Row],[Price_retail]]>$AC$3,"Premium","Average") -> Average | Y83: =IF(ISNUMBER(SEARCH("Basic",Real_Sales[[#This Row],[Product_name]])),"Yes","No") -> No | Z83: {=_xlfn.IFS(Real_Sales[[#This Row],[Price_retail]]<=15,1, Real_Sales[[#This Row],[Price_retail]]<=30,2, Real_Sales[[#This Row],[Price_retail]]<=50,3,Real_Sales[[#This Row],[Price_retail]]>50,4)} -> 1
A84: ZL100291 | B84: https://www.zalando.de/alpha-industries-slim-fit-polo---mint-zl100291/ | C84: Alpha Industries | D84: Slim Fit POLO - MINT | E84: Men's T-Shirts & Polos | F84: Polo Shirts | G84: Basic Polos | H84: Mint | I84: M | J84: 8.99 | K84: 8.99 | L84: Regular Price | M84: EUR | N84: 622 | O84: 3.7 | P84: 48.0 | S84: Yes | T84: 44955 | U84: https://img01.ztat.net/article/ZL100291.jpg | V84: =(Real_Sales[[#This Row],[Price_retail]]-Real_Sales[[#This Row],[Price_current]])/Real_Sales[[#This Row],[Price_retail]] -> 0 | W84: {=_xlfn.IFS(Real_Sales[[#This Row],[Discount]]=0%,"No Discount",Real_Sales[[#This Row],[Discount]]<=20%,"Light",Real_Sales[[#This Row],[Discount]]<=50%,"Moderate",Real_Sales[[#This Row],[Discount]]<=80%,"High", TRUE,"Very High")} -> No Discount | X84: =IF(Real_Sales[[#This Row],[Price_retail]]>$AC$3,"Premium","Average") -> Average | Y84: =IF(ISNUMBER(SEARCH("Basic",Real_Sales[[#This Row],[Product_name]])),"Yes","No") -> No | Z84: {=_xlfn.IFS(Real_Sales[[#This Row],[Price_retail]]<=15,1, Real_Sales[[#This Row],[Price_retail]]<=30,2, Real_Sales[[#This Row],[Price_retail]]<=50,3,Real_Sales[[#This Row],[Price_retail]]>50,4)} -> 1
A85: ZL100296 | B85: https://www.zalando.de/colours-and-sons-essential-polo---mint-zl100296/ | C85: Colours & Sons | D85: Essential POLO - MINT | E85: Men's T-Shirts & Polos | F85: Polo Shirts | G85: Pique Polos | H85: Mint | I85: S | J85: 8.99 | K85: 8.99 | L85: Regular Price | M85: EUR | N85: 945 | O85: 3.0 | P85: 32.0 | S85: No | T85: 44955 | U85: https://img01.ztat.net/article/ZL100296.jpg | V85: =(Real_Sales[[#This Row],[Price_retail]]-Real_Sales[[#This Row],[Price_current]])/Real_Sales[[#This Row],[Price_retail]] -> 0 | W85: {=_xlfn.IFS(Real_Sales[[#This Row],[Discount]]=0%,"No Discount",Real_Sales[[#This Row],[Discount]]<=20%,"Light",Real_Sales[[#This Row],[Discount]]<=50%,"Moderate",Real_Sales[[#This Row],[Discount]]<=80%,"High", TRUE,"Very High")} -> No Discount | X85: =IF(Real_Sales[[#This Row],[Price_retail]]>$AC$3,"Premium","Average") -> Average | Y85: =IF(ISNUMBER(SEARCH("Basic",Real_Sales[[#This Row],[Product_name]])),"Yes","No") -> No | Z85: {=_xlfn.IFS(Real_Sales[[#This Row],[Price_retail]]<=15,1, Real_Sales[[#This Row],[Price_retail]]<=30,2, Real_Sales[[#This Row],[Price_retail]]<=50,3,Real_Sales[[#This Row],[Price_retail]]>50,4)} -> 1
A86: ZL100317 | B86: https://www.zalando.de/nike-print-t-shirt---mint-zl100317/ | C86: Nike | D86: Print T-SHIRT - MINT | E86: Men's T-Shirts & Polos | F86: T-Shirts | G86: Slim Fit T-Shirts | H86: Mint | I86: XS | J86: 8.99 | K86: 8.99 | L86: Regular Price | M86: EUR | N86: 905 | O86: 3.4 | P86: 0 | S86: Yes | T86: 44955 | U86: https://img01.ztat.net/article/ZL100317.jpg | V86: =(Real_Sales[[#This Row],[Price_retail]]-Real_Sales[[#This Row],[Price_current]])/Real_Sales[[#This Row],[Price_retail]] -> 0 | W86: {=_xlfn.IFS(Real_Sales[[#This Row],[Discount]]=0%,"No Discount",Real_Sales[[#This Row],[Discount]]<=20%,"Light",Real_Sales[[#This Row],[Discount]]<=50%,"Moderate",Real_Sales[[#This Row],[Discount]]<=80%,"High", TRUE,"Very High")} -> No Discount | X86: =IF(Real_Sales[[#This Row],[Price_retail]]>$AC$3,"Premium","Average") -> Average | Y86: =IF(ISNUMBER(SEARCH("Basic",Real_Sales[[#This Row],[Product_name]])),"Yes","No") -> No | Z86: {=_xlfn.IFS(Real_Sales[[#This Row],[Price_retail]]<=15,1, Real_Sales[[#This Row],[Price_retail]]<=30,2, Real_Sales[[#This Row],[Price_retail]]<=50,3,Real_Sales[[#This Row],[Price_retail]]>50,4)} -> 1
A87: ZL100321 | B87: https://www.zalando.de/under-armour-slim-fit-polo---royal-blue-zl100321/ | C87: Under Armour | D87: Slim Fit POLO - ROYAL BLUE | E87: Men's T-Shirts & Polos | F87: Polo Shirts | G87: Pique Polos | H87: Royal Blue | I87: XS | J87: 8.99 | K87: 8.99 | L87: Regular Price | M87: EUR | N87: 364 | O87: 0 | P87: 35.0 | S87: Yes | T87: 44955 | U87: https://img01.ztat.net/article/ZL100321.jpg | V87: =(Real_Sales[[#This Row],[Price_retail]]-Real_Sales[[#This Row],[Price_current]])/Real_Sales[[#This Row],[Price_retail]] -> 0 | W87: {=_xlfn.IFS(Real_Sales[[#This Row],[Discount]]=0%,"No Discount",Real_Sales[[#This Row],[Discount]]<=20%,"Light",Real_Sales[[#This Row],[Discount]]<=50%,"Moderate",Real_Sales[[#This Row],[Discount]]<=80%,"High", TRUE,"Very High")} -> No Discount | X87: =IF(Real_Sales[[#This Row],[Price_retail]]>$AC$3,"Premium","Average") -> Average | Y87: =IF(ISNUMBER(SEARCH("Basic",Real_Sales[[#This Row],[Product_name]])),"Yes","No") -> No | Z87: {=_xlfn.IFS(Real_Sales[[#This Row],[Price_retail]]<=15,1, Real_Sales[[#This Row],[Price_retail]]<=30,2, Real_Sales[[#This Row],[Price_retail]]<=50,3,Real_Sales[[#This Row],[Price_retail]]>50,4)} -> 1
... A139: ZL100802 | B139: https://www.zalando.de/seidensticker-print-polo---mint-zl100802/ | C139: Seidensticker | D139: Print POLO - MINT | E139: Men's T-Shirts & Polos | F139: Polo Shirts | G139: Slim Fit Polos | H139: Mint | I139: M | J139: 8.99 | K139: 8.99 | L139: Regular Price | M139: EUR | N139: 799 | O139: 3.3 | P139: 40.0 | S139: Yes | T139: 44955 | U139: https://img01.ztat.net/article/ZL100802.jpg | V139: =(Real_Sales[[#This Row],[Price_retail]]-Real_Sales[[#This Row],[Price_current]])/Real_Sales[[#This Row],[Price_retail]] -> 0 | W139: {=_xlfn.IFS(Real_Sales[[#This Row],[Discount]]=0%,"No Discount",Real_Sales[[#This Row],[Discount]]<=20%,"Light",Real_Sales[[#This Row],[Discount]]<=50%,"Moderate",Real_Sales[[#This Row],[Discount]]<=80%,"High", TRUE,"Very High")} -> No Discount | X139: =IF(Real_Sales[[#This Row],[Price_retail]]>$AC$3,"Premium","Average") -> Average | Y139: =IF(ISNUMBER(SEARCH("Basic",Real_Sales[[#This Row],[Product_name]])),"Yes","No") -> No | Z139: {=_xlfn.IFS(Real_Sales[[#This Row],[Price_retail]]<=15,1, Real_Sales[[#This Row],[Price_retail]]<=30,2, Real_Sales[[#This Row],[Price_retail]]<=50,3,Real_Sales[[#This Row],[Price_retail]]>50,4)} -> 1
A140: ZL100817 | B140: https://www.zalando.de/anerkjendt-regular-fit-polo---white-zl100817/ | C140: Anerkjendt | D140: Regular Fit POLO - WHITE | E140: Men's T-Shirts & Polos | F140: Polo Shirts | G140: Slim Fit Polos | I140: XS | J140: 8.99 | K140: 8.99 | L140: Regular Price | M140: EUR | N140: 382 | O140: 4.3 | P140: 37.0 | S140: No | T140: 44955 | U140: https://img01.ztat.net/article/ZL100817.jpg | V140: =(Real_Sales[[#This Row],[Price_retail]]-Real_Sales[[#This Row],[Price_current]])/Real_Sales[[#This Row],[Price_retail]] -> 0 | W140: {=_xlfn.IFS(Real_Sales[[#This Row],[Discount]]=0%,"No Discount",Real_Sales[[#This Row],[Discount]]<=20%,"Light",Real_Sales[[#This Row],[Discount]]<=50%,"Moderate",Real_Sales[[#This Row],[Discount]]<=80%,"High", TRUE,"Very High")} -> No Discount | X140: =IF(Real_Sales[[#This Row],[Price_retail]]>$AC$3,"Premium","Average") -> Average | Y140: =IF(ISNUMBER(SEARCH("Basic",Real_Sales[[#This Row],[Product_name]])),"Yes","No") -> No | Z140: {=_xlfn.IFS(Real_Sales[[#This Row],[Price_retail]]<=15,1, Real_Sales[[#This Row],[Price_retail]]<=30,2, Real_Sales[[#This Row],[Price_retail]]<=50,3,Real_Sales[[#This Row],[Price_retail]]>50,4)} -> 1
A141: ZL100825 | B141: https://www.zalando.de/adidas-performance-basic-polo---grey-melange-zl100825/ | C141: Adidas Performance | D141: Basic POLO - GREY MELANGE | E141: Men's T-Shirts & Polos | F141: Polo Shirts | G141: Basic Polos | H141: Grey Melange | I141: S | J141: 8.99 | K141: 8.99 | L141: Regular Price | M141: EUR | N141: 306 | O141: 4.2 | P141: 32.0 | S141: No | T141: 44955 | U141: https://img01.ztat.net/article/ZL100825.jpg | V141: =(Real_Sales[[#This Row],[Price_retail]]-Real_Sales[[#This Row],[Price_current]])/Real_Sales[[#This Row],[Price_retail]] -> 0 | W141: {=_xlfn.IFS(Real_Sales[[#This Row],[Discount]]=0%,"No Discount",Real_Sales[[#This Row],[Discount]]<=20%,"Light",Real_Sales[[#This Row],[Discount]]<=50%,"Moderate",Real_Sales[[#This Row],[Discount]]<=80%,"High", TRUE,"Very High")} -> No Discount | X141: =IF(Real_Sales[[#This Row],[Price_retail]]>$AC$3,"Premium","Average") -> Average | Y141: =IF(ISNUMBER(SEARCH("Basic",Real_Sales[[#This Row],[Product_name]])),"Yes","No") -> Yes | Z141: {=_xlfn.IFS(Real_Sales[[#This Row],[Price_retail]]<=15,1, Real_Sales[[#This Row],[Price_retail]]<=30,2, Real_Sales[[#This Row],[Price_retail]]<=50,3,Real_Sales[[#This Row],[Price_retail]]>50,4)} -> 1
A142: ZL100848 | B142: https://www.zalando.de/only-and-sons-slim-fit-polo---navy-zl100848/ | C142: Only & Sons | D142: Slim Fit POLO - NAVY | E142: Men's T-Shirts & Polos | F142: Polo Shirts | G142: Slim Fit Polos | H142: Navy | I142: S | J142: 8.99 | K142: 8.99 | L142: Regular Price | M142: EUR | N142: 566 | O142: 4.7 | P142: N/A | S142: Yes | T142: 44955 | U142: https://img01.ztat.net/article/ZL100848.jpg | V142: =(Real_Sales[[#This Row],[Price_retail]]-Real_Sales[[#This Row],[Price_current]])/Real_Sales[[#This Row],[Price_retail]] -> 0 | W142: {=_xlfn.IFS(Real_Sales[[#This Row],[Discount]]=0%,"No Discount",Real_Sales[[#This Row],[Discount]]<=20%,"Light",Real_Sales[[#This Row],[Discount]]<=50%,"Moderate",Real_Sales[[#This Row],[Discount]]<=80%,"High", TRUE,"Very High")} -> No Discount | X142: =IF(Real_Sales[[#This Row],[Price_retail]]>$AC$3,"Premium","Average") -> Average | Y142: =IF(ISNUMBER(SEARCH("Basic",Real_Sales[[#This Row],[Product_name]])),"Yes","No") -> No | Z142: {=_xlfn.IFS(Real_Sales[[#This Row],[Price_retail]]<=15,1, Real_Sales[[#This Row],[Price_retail]]<=30,2, Real_Sales[[#This Row],[Price_retail]]<=50,3,Real_Sales[[#This Row],[Price_retail]]>50,4)} -> 1
A143: ZL100849 | B143: https://www.zalando.de/solid-homme-print-polo---red-zl100849/ | C143: Solid Homme | D143: Print POLO - RED | E143: Men's T-Shirts & Polos | F143: Polo Shirts | G143: Slim Fit Polos | H143: Red | I143: XS | J143: 8.99 | K143: 8.99 | L143: Regular Price | M143: EUR | N143: 906 | O143: 3.6 | P143: 44.0 | S143: Yes | T143: 44955 | U143: https://img01.ztat.net/article/ZL100849.jpg | V143: =(Real_Sales[[#This Row],[Price_retail]]-Real_Sales[[#This Row],[Price_current]])/Real_Sales[[#This Row],[Price_retail]] -> 0 | W143: {=_xlfn.IFS(Real_Sales[[#This Row],[Discount]]=0%,"No Discount",Real_Sales[[#This Row],[Discount]]<=20%,"Light",Real_Sales[[#This Row],[Discount]]<=50%,"Moderate",Real_Sales[[#This Row],[Discount]]<=80%,"High", TRUE,"Very High")} -> No Discount | X143: =IF(Real_Sales[[#This Row],[Price_retail]]>$AC$3,"Premium","Average") -> Average | Y143: =IF(ISNUMBER(SEARCH("Basic",Real_Sales[[#This Row],[Product_name]])),"Yes","No") -> No | Z143: {=_xlfn.IFS(Real_Sales[[#This Row],[Price_retail]]<=15,1, Real_Sales[[#This Row],[Price_retail]]<=30,2, Real_Sales[[#This Row],[Price_retail]]<=50,3,Real_Sales[[#This Row],[Price_retail]]>50,4)} -> 1
A144: ZL100854 | B144: https://www.zalando.de/odlo-regular-fit-t-shirt---beige-zl100854/ | C144: Odlo | D144: Regular Fit T-SHIRT - BEIGE | E144: Men's T-Shirts & Polos | F144: T-Shirts | G144: Long Sleeve T-Shirts | H144: Beige | I144: XS | J144: 8.99 | K144: 8.99 | L144: Regular Price | M144: EUR | N144: 830 | O144: 3.2 | P144: 35.0 | S144: Yes | T144: 44955 | U144: https://img01.ztat.net/article/ZL100854.jpg | V144: =(Real_Sales[[#This Row],[Price_retail]]-Real_Sales[[#This Row],[Price_current]])/Real_Sales[[#This Row],[Price_retail]] -> 0 | W144: {=_xlfn.IFS(Real_Sales[[#This Row],[Discount]]=0%,"No Discount",Real_Sales[[#This Row],[Discount]]<=20%,"Light",Real_Sales[[#This Row],[Discount]]<=50%,"Moderate",Real_Sales[[#This Row],[Discount]]<=80%,"High", TRUE,"Very High")} -> No Discount | X144: =IF(Real_Sales[[#This Row],[Price_retail]]>$AC$3,"Premium","Average") -> Average | Y144: =IF(ISNUMBER(SEARCH("Basic",Real_Sales[[#This Row],[Product_name]])),"Yes","No") -> No | Z144: {=_xlfn.IFS(Real_Sales[[#This Row],[Price_retail]]<=15,1, Real_Sales[[#This Row],[Price_retail]]<=30,2, Real_Sales[[#This Row],[Price_retail]]<=50,3,Real_Sales[[#This Row],[Price_retail]]>50,4)} -> 1
A145: ZL100864 | B145: https://www.zalando.de/adidas-performance-print-t-shirt---denim-blue-zl100864/ | C145: Adidas Performance | D145: Print T-SHIRT - DENIM BLUE | E145: Men's T-Shirts & Polos | F145: T-Shirts | G145: Print T-Shirts | H145: Denim Blue | I145: XS | J145: 8.99 | K145: 8.99 | L145: Regular Price | M145: EUR | N145: 290 | O145: 3.4 | P145: 39.0 | S145: Yes | T145: 44955 | U145: https://img01.ztat.net/article/ZL100864.jpg | V145: =(Real_Sales[[#This Row],[Price_retail]]-Real_Sales[[#This Row],[Price_current]])/Real_Sales[[#This Row],[Price_retail]] -> 0 | W145: {=_xlfn.IFS(Real_Sales[[#This Row],[Discount]]=0%,"No Discount",Real_Sales[[#This Row],[Discount]]<=20%,"Light",Real_Sales[[#This Row],[Discount]]<=50%,"Moderate",Real_Sales[[#This Row],[Discount]]<=80%,"High", TRUE,"Very High")} -> No Discount | X145: =IF(Real_Sales[[#This Row],[Price_retail]]>$AC$3,"Premium","Average") -> Average | Y145: =IF(ISNUMBER(SEARCH("Basic",Real_Sales[[#This Row],[Product_name]])),"Yes","No") -> No | Z145: {=_xlfn.IFS(Real_Sales[[#This Row],[Price_retail]]<=15,1, Real_Sales[[#This Row],[Price_retail]]<=30,2, Real_Sales[[#This Row],[Price_retail]]<=50,3,Real_Sales[[#This Row],[Price_retail]]>50,4)} -> 1
A146: ZL100880 | B146: https://www.zalando.de/windsor.-essential-t-shirt---mint-zl100880/ | C146: Windsor. | D146: Essential T-SHIRT - MINT | E146: Men's T-Shirts & Polos | F146: T-Shirts | G146: Basic T-Shirts | H146: Mint | I146: S | J146: 8.99 | K146: 8.99 | L146: Regular Price | M146: EUR | N146: 505 | O146: 3.2 | P146: 48.0 | S146: Yes | T146: 44955 | U146: https://img01.ztat.net/article/ZL100880.jpg | V146: =(Real_Sales[[#This Row],[Price_retail]]-Real_Sales[[#This Row],[Price_current]])/Real_Sales[[#This Row],[Price_retail]] -> 0 | W146: {=_xlfn.IFS(Real_Sales[[#This Row],[Discount]]=0%,"No Discount",Real_Sales[[#This Row],[Discount]]<=20%,"Light",Real_Sales[[#This Row],[Discount]]<=50%,"Moderate",Real_Sales[[#This Row],[Discount]]<=80%,"High", TRUE,"Very High")} -> No Discount | X146: =IF(Real_Sales[[#This Row],[Price_retail]]>$AC$3,"Premium","Average") -> Average | Y146: =IF(ISNUMBER(SEARCH("Basic",Real_Sales[[#This Row],[Product_name]])),"Yes","No") -> No | Z146: {=_xlfn.IFS(Real_Sales[[#This Row],[Price_retail]]<=15,1, Real_Sales[[#This Row],[Price_retail]]<=30,2, Real_Sales[[#This Row],[Price_retail]]<=50,3,Real_Sales[[#This Row],[Price_retail]]>50,4)} -> 1
A147: ZL100882 | B147: https://www.zalando.de/puma-basic-polo---red-zl100882/ | C147: Puma | D147: Basic POLO - RED | E147: Men's T-Shirts & Polos | F147: Polo Shirts | G147: Slim Fit Polos | H147: Red | I147: XS | J147: 8.99 | K147: 8.99 | L147: Regular Price | M147: EUR | N147: 558 | O147: 3.1 | P147: 35.0 | S147: Yes | T147: 44955 | U147: https://img01.ztat.net/article/ZL100882.jpg | V147: =(Real_Sales[[#This Row],[Price_retail]]-Real_Sales[[#This Row],[Price_current]])/Real_Sales[[#This Row],[Price_retail]] -> 0 | W147: {=_xlfn.IFS(Real_Sales[[#This Row],[Discount]]=0%,"No Discount",Real_Sales[[#This Row],[Discount]]<=20%,"Light",Real_Sales[[#This Row],[Discount]]<=50%,"Moderate",Real_Sales[[#This Row],[Discount]]<=80%,"High", TRUE,"Very High")} -> No Discount | X147: =IF(Real_Sales[[#This Row],[Price_retail]]>$AC$3,"Premium","Average") -> Average | Y147: =IF(ISNUMBER(SEARCH("Basic",Real_Sales[[#This Row],[Product_name]])),"Yes","No") -> Yes | Z147: {=_xlfn.IFS(Real_Sales[[#This Row],[Price_retail]]<=15,1, Real_Sales[[#This Row],[Price_retail]]<=30,2, Real_Sales[[#This Row],[Price_retail]]<=50,3,Real_Sales[[#This Row],[Price_retail]]>50,4)} -> 1
A148: ZL100905 | B148: https://www.zalando.de/adidas-performance-basic-polo---mint-zl100905/ | C148: Adidas Performance | D148: Basic POLO - MINT | E148: Men's T-Shirts & Polos | F148: Polo Shirts | G148: Slim Fit Polos | H148: Mint | I148: M | J148: 8.99 | K148: 8.99 | L148: Regular Price | M148: EUR | N148: 700 | O148: 4.1 | P148: 37.0 | S148: Yes | T148: 44955 | U148: https://img01.ztat.net/article/ZL100905.jpg | V148: =(Real_Sales[[#This Row],[Price_retail]]-Real_Sales[[#This Row],[Price_current]])/Real_Sales[[#This Row],[Price_retail]] -> 0 | W148: {=_xlfn.IFS(Real_Sales[[#This Row],[Discount]]=0%,"No Discount",Real_Sales[[#This Row],[Discount]]<=20%,"Light",Real_Sales[[#This Row],[Discount]]<=50%,"Moderate",Real_Sales[[#This Row],[Discount]]<=80%,"High", TRUE,"Very High")} -> No Discount | X148: =IF(Real_Sales[[#This Row],[Price_retail]]>$AC$3,"Premium","Average") -> Average | Y148: =IF(ISNUMBER(SEARCH("Basic",Real_Sales[[#This Row],[Product_name]])),"Yes","No") -> Yes | Z148: {=_xlfn.IFS(Real_Sales[[#This Row],[Price_retail]]<=15,1, Real_Sales[[#This Row],[Price_retail]]<=30,2, Real_Sales[[#This Row],[Price_retail]]<=50,3,Real_Sales[[#This Row],[Price_retail]]>50,4)} -> 1
A149: ZL100919 | B149: https://www.zalando.de/salomon-essential-t-shirt---beige-zl100919/ | C149: Salomon | D149: Essential T-SHIRT - BEIGE | E149: Men's T-Shirts & Polos | F149: T-Shirts | G149: Slim Fit T-Shirts | H149: Beige | I149: S | J149: 8.99 | K149: 8.99 | L149: Regular Price | M149: EUR | N149: 749 | O149: 4.9 | P149: 39.0 | S149: Yes | T149: 44955 | U149: https://img01.ztat.net/article/ZL100919.jpg | V149: =(Real_Sales[[#This Row],[Price_retail]]-Real_Sales[[#This Row],[Price_current]])/Real_Sales[[#This Row],[Price_retail]] -> 0 | W149: {=_xlfn.IFS(Real_Sales[[#This Row],[Discount]]=0%,"No Discount",Real_Sales[[#This Row],[Discount]]<=20%,"Light",Real_Sales[[#This Row],[Discount]]<=50%,"Moderate",Real_Sales[[#This Row],[Discount]]<=80%,"High", TRUE,"Very High")} -> No Discount | X149: =IF(Real_Sales[[#This Row],[Price_retail]]>$AC$3,"Premium","Average") -> Average | Y149: =IF(ISNUMBER(SEARCH("Basic",Real_Sales[[#This Row],[Product_name]])),"Yes","No") -> No | Z149: {=_xlfn.IFS(Real_Sales[[#This Row],[Price_retail]]<=15,1, Real_Sales[[#This Row],[Price_retail]]<=30,2, Real_Sales[[#This Row],[Price_retail]]<=50,3,Real_Sales[[#This Row],[Price_retail]]>50,4)} -> 1
A150: ZL100920 | B150: https://www.zalando.de/tommy-hilfiger-regular-fit-t-shirt---navy-zl100920/ | C150: Tommy Hilfiger | D150: Regular Fit T-SHIRT - NAVY | E150: Men's T-Shirts & Polos | F150: T-Shirts | G150: Slim Fit T-Shirts | H150: Navy | I150: M | J150: 8.99 | K150: 8.99 | L150: Regular Price | M150: EUR | N150: 354 | O150: 4.3 | P150: 35.0 | S150: No | T150: 44955 | U150: https://img01.ztat.net/article/ZL100920.jpg | V150: =(Real_Sales[[#This Row],[Price_retail]]-Real_Sales[[#This Row],[Price_current]])/Real_Sales[[#This Row],[Price_retail]] -> 0 | W150: {=_xlfn.IFS(Real_Sales[[#This Row],[Discount]]=0%,"No Discount",Real_Sales[[#This Row],[Discount]]<=20%,"Light",Real_Sales[[#This Row],[Discount]]<=50%,"Moderate",Real_Sales[[#This Row],[Discount]]<=80%,"High", TRUE,"Very High")} -> No Discount | X150: =IF(Real_Sales[[#This Row],[Price_retail]]>$AC$3,"Premium","Average") -> Average | Y150: =IF(ISNUMBER(SEARCH("Basic",Real_Sales[[#This Row],[Product_name]])),"Yes","No") -> No | Z150: {=_xlfn.IFS(Real_Sales[[#This Row],[Price_retail]]<=15,1, Real_Sales[[#This Row],[Price_retail]]<=30,2, Real_Sales[[#This Row],[Price_retail]]<=50,3,Real_Sales[[#This Row],[Price_retail]]>50,4)} -> 1
A151: ZL100922 | B151: https://www.zalando.de/under-armour-slim-fit-t-shirt---black-zl100922/ | C151: Under Armour | D151: Slim Fit T-SHIRT - BLACK | E151: Men's T-Shirts & Polos | F151: T-Shirts | G151: Slim Fit T-Shirts | H151: Black | I151: S | J151: 8.99 | K151: 8.99 | L151: Regular Price | M151: EUR | N151: 401 | O151: 4.9 | P151: 33.0 | S151: Yes | T151: 44955 | U151: https://img01.ztat.net/article/ZL100922.jpg | V151: =(Real_Sales[[#This Row],[Price_retail]]-Real_Sales[[#This Row],[Price_current]])/Real_Sales[[#This Row],[Price_retail]] -> 0 | W151: {=_xlfn.IFS(Real_Sales[[#This Row],[Discount]]=0%,"No Discount",Real_Sales[[#This Row],[Discount]]<=20%,"Light",Real_Sales[[#This Row],[Discount]]<=50%,"Moderate",Real_Sales[[#This Row],[Discount]]<=80%,"High", TRUE,"Very High")} -> No Discount | X151: =IF(Real_Sales[[#This Row],[Price_retail]]>$AC$3,"Premium","Average") -> Average | Y151: =IF(ISNUMBER(SEARCH("Basic",Real_Sales[[#This Row],[Product_name]])),"Yes","No") -> No | Z151: {=_xlfn.IFS(Real_Sales[[#This Row],[Price_retail]]<=15,1, Real_Sales[[#This Row],[Price_retail]]<=30,2, Real_Sales[[#This Row],[Price_retail]]<=50,3,Real_Sales[[#This Row],[Price_retail]]>50,4)} -> 1
A152: ZL100936 | B152: https://www.zalando.de/new-look-basic-t-shirt---olive-zl100936/ | C152: New Look | D152: Basic T-SHIRT - OLIVE | E152: Men's T-Shirts & Polos | F152: T-Shirts | G152: Print T-Shirts | H152: Olive | I152: M | J152: 8.99 | K152: 8.99 | L152: Regular Price | M152: EUR | N152: 58 | O152: 0 | P152: N/A | S152: Yes | T152: 44955 | U152: https://img01.ztat.net/article/ZL100936.jpg | V152: =(Real_Sales[[#This Row],[Price_retail]]-Real_Sales[[#This Row],[Price_current]])/Real_Sales[[#This Row],[Price_retail]] -> 0 | W152: {=_xlfn.IFS(Real_Sales[[#This Row],[Discount]]=0%,"No Discount",Real_Sales[[#This Row],[Discount]]<=20%,"Light",Real_Sales[[#This Row],[Discount]]<=50%,"Moderate",Real_Sales[[#This Row],[Discount]]<=80%,"High", TRUE,"Very High")} -> No Discount | X152: =IF(Real_Sales[[#This Row],[Price_retail]]>$AC$3,"Premium","Average") -> Average | Y152: =IF(ISNUMBER(SEARCH("Basic",Real_Sales[[#This Row],[Product_name]])),"Yes","No") -> Yes | Z152: {=_xlfn.IFS(Real_Sales[[#This Row],[Price_retail]]<=15,1, Real_Sales[[#This Row],[Price_retail]]<=30,2, Real_Sales[[#This Row],[Price_retail]]<=50,3,Real_Sales[[#This Row],[Price_retail]]>50,4)} -> 1
... A216: ZL100201 | B216: https://www.zalando.de/tommy-hilfiger-slim-fit-t-shirt---beige-zl100201/ | C216: Tommy Hilfiger | D216: Slim Fit T-SHIRT - BEIGE | E216: Men's T-Shirts & Polos | F216: T-Shirts | G216: Slim Fit T-Shirts | H216: Beige | I216: S | J216: 10.41 | K216: 5.62 | L216: SALE | M216: EUR | N216: 597 | O216: 4.3 | P216: 37.0 | S216: Yes | T216: 44955 | U216: https://img01.ztat.net/article/ZL100201.jpg | V216: =(Real_Sales[[#This Row],[Price_retail]]-Real_Sales[[#This Row],[Price_current]])/Real_Sales[[#This Row],[Price_retail]] -> 0.46013449 | W216: {=_xlfn.IFS(Real_Sales[[#This Row],[Discount]]=0%,"No Discount",Real_Sales[[#This Row],[Discount]]<=20%,"Light",Real_Sales[[#This Row],[Discount]]<=50%,"Moderate",Real_Sales[[#This Row],[Discount]]<=80%,"High", TRUE,"Very High")} -> Moderate | X216: =IF(Real_Sales[[#This Row],[Price_retail]]>$AC$3,"Premium","Average") -> Average | Y216: =IF(ISNUMBER(SEARCH("Basic",Real_Sales[[#This Row],[Product_name]])),"Yes","No") -> No | Z216: {=_xlfn.IFS(Real_Sales[[#This Row],[Price_retail]]<=15,1, Real_Sales[[#This Row],[Price_retail]]<=30,2, Real_Sales[[#This Row],[Price_retail]]<=50,3,Real_Sales[[#This Row],[Price_retail]]>50,4)} -> 1
A217: ZL100624 | B217: https://www.zalando.de/the-north-face-essential-polo---khaki-zl100624/ | C217: The North Face | D217: Essential POLO - KHAKI | E217: Men's T-Shirts & Polos | F217: Polo Shirts | G217: Pique Polos | I217: S | J217: 10.45 | K217: 10.45 | L217: Regular Price | M217: EUR | N217: 219 | O217: 4.9 | P217: 0 | S217: Yes | T217: 44955 | U217: https://img01.ztat.net/article/ZL100624.jpg | V217: =(Real_Sales[[#This Row],[Price_retail]]-Real_Sales[[#This Row],[Price_current]])/Real_Sales[[#This Row],[Price_retail]] -> 0 | W217: {=_xlfn.IFS(Real_Sales[[#This Row],[Discount]]=0%,"No Discount",Real_Sales[[#This Row],[Discount]]<=20%,"Light",Real_Sales[[#This Row],[Discount]]<=50%,"Moderate",Real_Sales[[#This Row],[Discount]]<=80%,"High", TRUE,"Very High")} -> No Discount | X217: =IF(Real_Sales[[#This Row],[Price_retail]]>$AC$3,"Premium","Average") -> Average | Y217: =IF(ISNUMBER(SEARCH("Basic",Real_Sales[[#This Row],[Product_name]])),"Yes","No") -> No | Z217: {=_xlfn.IFS(Real_Sales[[#This Row],[Price_retail]]<=15,1, Real_Sales[[#This Row],[Price_retail]]<=30,2, Real_Sales[[#This Row],[Price_retail]]<=50,3,Real_Sales[[#This Row],[Price_retail]]>50,4)} -> 1
A218: ZL100665 | B218: https://www.zalando.de/reebok-slim-fit-t-shirt---olive-zl100665/ | C218: Reebok | D218: Slim Fit T-SHIRT - OLIVE | E218: Men's T-Shirts & Polos | F218: T-Shirts | G218: Print T-Shirts | H218: Olive | I218: S | J218: 10.47 | K218: 6.75 | L218: SALE | M218: EUR | N218: 843 | O218: 0 | P218: 43.0 | S218: Yes | T218: 44955 | U218: https://img01.ztat.net/article/ZL100665.jpg | V218: =(Real_Sales[[#This Row],[Price_retail]]-Real_Sales[[#This Row],[Price_current]])/Real_Sales[[#This Row],[Price_retail]] -> 0.35530086 | W218: {=_xlfn.IFS(Real_Sales[[#This Row],[Discount]]=0%,"No Discount",Real_Sales[[#This Row],[Discount]]<=20%,"Light",Real_Sales[[#This Row],[Discount]]<=50%,"Moderate",Real_Sales[[#This Row],[Discount]]<=80%,"High", TRUE,"Very High")} -> Moderate | X218: =IF(Real_Sales[[#This Row],[Price_retail]]>$AC$3,"Premium","Average") -> Average | Y218: =IF(ISNUMBER(SEARCH("Basic",Real_Sales[[#This Row],[Product_name]])),"Yes","No") -> No | Z218: {=_xlfn.IFS(Real_Sales[[#This Row],[Price_retail]]<=15,1, Real_Sales[[#This Row],[Price_retail]]<=30,2, Real_Sales[[#This Row],[Price_retail]]<=50,3,Real_Sales[[#This Row],[Price_retail]]>50,4)} -> 1
A219: ZL100915 | B219: https://www.zalando.de/tommy-hilfiger-print-t-shirt---dark-green-zl100915/ | C219: Tommy Hilfiger | D219: Print T-Shirt - Dark Green | E219: Men's T-Shirts & Polos | F219: T-Shirts | G219: Basic T-Shirts | H219: Dark Green | I219: S | J219: 10.47 | K219: 10.47 | L219: Regular Price | M219: EUR | N219: 256 | O219: 0 | P219: 33.0 | S219: Yes | T219: 44955 | U219: https://img01.ztat.net/article/ZL100915.jpg | V219: =(Real_Sales[[#This Row],[Price_retail]]-Real_Sales[[#This Row],[Price_current]])/Real_Sales[[#This Row],[Price_retail]] -> 0 | W219: {=_xlfn.IFS(Real_Sales[[#This Row],[Discount]]=0%,"No Discount",Real_Sales[[#This Row],[Discount]]<=20%,"Light",Real_Sales[[#This Row],[Discount]]<=50%,"Moderate",Real_Sales[[#This Row],[Discount]]<=80%,"High", TRUE,"Very High")} -> No Discount | X219: =IF(Real_Sales[[#This Row],[Price_retail]]>$AC$3,"Premium","Average") -> Average | Y219: =IF(ISNUMBER(SEARCH("Basic",Real_Sales[[#This Row],[Product_name]])),"Yes","No") -> No | Z219: {=_xlfn.IFS(Real_Sales[[#This Row],[Price_retail]]<=15,1, Real_Sales[[#This Row],[Price_retail]]<=30,2, Real_Sales[[#This Row],[Price_retail]]<=50,3,Real_Sales[[#This Row],[Price_retail]]>50,4)} -> 1
A220: ZL100588 | B220: https://www.zalando.de/diesel-basic-polo---khaki-zl100588/ | C220: Diesel | D220: Basic POLO - KHAKI | E220: Men's T-Shirts & Polos | F220: Polo Shirts | G220: Slim Fit Polos | H220: Khaki | I220: XS | J220: 10.51 | K220: 7.47 | L220: SALE | M220: EUR | N220: 25 | O220: 0 | P220: 28.0 | S220: Yes | T220: 44955 | U220: https://img01.ztat.net/article/ZL100588.jpg | V220: =(Real_Sales[[#This Row],[Price_retail]]-Real_Sales[[#This Row],[Price_current]])/Real_Sales[[#This Row],[Price_retail]] -> 0.28924833 | W220: {=_xlfn.IFS(Real_Sales[[#This Row],[Discount]]=0%,"No Discount",Real_Sales[[#This Row],[Discount]]<=20%,"Light",Real_Sales[[#This Row],[Discount]]<=50%,"Moderate",Real_Sales[[#This Row],[Discount]]<=80%,"High", TRUE,"Very High")} -> Moderate | X220: =IF(Real_Sales[[#This Row],[Price_retail]]>$AC$3,"Premium","Average") -> Average | Y220: =IF(ISNUMBER(SEARCH("Basic",Real_Sales[[#This Row],[Product_name]])),"Yes","No") -> Yes | Z220: {=_xlfn.IFS(Real_Sales[[#This Row],[Price_retail]]<=15,1, Real_Sales[[#This Row],[Price_retail]]<=30,2, Real_Sales[[#This Row],[Price_retail]]<=50,3,Real_Sales[[#This Row],[Price_retail]]>50,4)} -> 1
A221: ZL100390 | B221: https://www.zalando.de/burton-london-slim-fit-t-shirt---bordeaux-zl100390/ | C221: Burton Menswear London | D221: Slim Fit T-SHIRT - BORDEAUX | E221: Men's T-Shirts & Polos | F221: T-Shirts | G221: Slim Fit T-Shirts | H221: Bordeaux | I221: XS | J221: 10.52 | K221: 6.11 | L221: SALE | M221: EUR | N221: 115 | O221: 4.2 | P221: 33.0 | S221: Yes | T221: 44955 | U221: https://img01.ztat.net/article/ZL100390.jpg | V221: =(Real_Sales[[#This Row],[Price_retail]]-Real_Sales[[#This Row],[Price_current]])/Real_Sales[[#This Row],[Price_retail]] -> 0.41920152 | W221: {=_xlfn.IFS(Real_Sales[[#This Row],[Discount]]=0%,"No Discount",Real_Sales[[#This Row],[Discount]]<=20%,"Light",Real_Sales[[#This Row],[Discount]]<=50%,"Moderate",Real_Sales[[#This Row],[Discount]]<=80%,"High", TRUE,"Very High")} -> Moderate | X221: =IF(Real_Sales[[#This Row],[Price_retail]]>$AC$3,"Premium","Average") -> Average | Y221: =IF(ISNUMBER(SEARCH("Basic",Real_Sales[[#This Row],[Product_name]])),"Yes","No") -> No | Z221: {=_xlfn.IFS(Real_Sales[[#This Row],[Price_retail]]<=15,1, Real_Sales[[#This Row],[Price_retail]]<=30,2, Real_Sales[[#This Row],[Price_retail]]<=50,3,Real_Sales[[#This Row],[Price_retail]]>50,4)} -> 1
A222: ZL100844 | B222: https://www.zalando.de/tommy-hilfiger-essential-t-shirt---rust-zl100844/ | C222: Tommy Hilfiger | D222: Essential T-SHIRT - RUST | E222: Men's T-Shirts & Polos | F222: T-Shirts | G222: Basic T-Shirts | H222: Rust | I222: XS | J222: 10.54 | K222: 7.94 | L222: SALE | M222: EUR | N222: 650 | O222: 3.9 | P222: 40.0 | S222: Yes | T222: 44955 | U222: https://img01.ztat.net/article/ZL100844.jpg | V222: =(Real_Sales[[#This Row],[Price_retail]]-Real_Sales[[#This Row],[Price_current]])/Real_Sales[[#This Row],[Price_retail]] -> 0.24667932 | W222: {=_xlfn.IFS(Real_Sales[[#This Row],[Discount]]=0%,"No Discount",Real_Sales[[#This Row],[Discount]]<=20%,"Light",Real_Sales[[#This Row],[Discount]]<=50%,"Moderate",Real_Sales[[#This Row],[Discount]]<=80%,"High", TRUE,"Very High")} -> Moderate | X222: =IF(Real_Sales[[#This Row],[Price_retail]]>$AC$3,"Premium","Average") -> Average | Y222: =IF(ISNUMBER(SEARCH("Basic",Real_Sales[[#This Row],[Product_name]])),"Yes","No") -> No | Z222: {=_xlfn.IFS(Real_Sales[[#This Row],[Price_retail]]<=15,1, Real_Sales[[#This Row],[Price_retail]]<=30,2, Real_Sales[[#This Row],[Price_retail]]<=50,3,Real_Sales[[#This Row],[Price_retail]]>50,4)} -> 1
A223: ZL100693 | B223: https://www.zalando.de/adidas-performance-basic-polo---royal-blue-zl100693/ | C223: Adidas Performance | D223: Basic POLO - ROYAL BLUE | E223: Men's T-Shirts & Polos | F223: Polo Shirts | G223: Basic Polos | H223: Royal Blue | I223: S | J223: 10.54 | K223: 10.54 | L223: Regular Price | M223: EUR | N223: 464 | O223: 4.7 | P223: 34.0 | S223: Yes | T223: 44955 | U223: https://img01.ztat.net/article/ZL100693.jpg | V223: =(Real_Sales[[#This Row],[Price_retail]]-Real_Sales[[#This Row],[Price_current]])/Real_Sales[[#This Row],[Price_retail]] -> 0 | W223: {=_xlfn.IFS(Real_Sales[[#This Row],[Discount]]=0%,"No Discount",Real_Sales[[#This Row],[Discount]]<=20%,"Light",Real_Sales[[#This Row],[Discount]]<=50%,"Moderate",Real_Sales[[#This Row],[Discount]]<=80%,"High", TRUE,"Very High")} -> No Discount | X223: =IF(Real_Sales[[#This Row],[Price_retail]]>$AC$3,"Premium","Average") -> Average | Y223: =IF(ISNUMBER(SEARCH("Basic",Real_Sales[[#This Row],[Product_name]])),"Yes","No") -> Yes | Z223: {=_xlfn.IFS(Real_Sales[[#This Row],[Price_retail]]<=15,1, Real_Sales[[#This Row],[Price_retail]]<=30,2, Real_Sales[[#This Row],[Price_retail]]<=50,3,Real_Sales[[#This Row],[Price_retail]]>50,4)} -> 1
A224: ZL100145 | B224: https://www.zalando.de/carhartt-wip-slim-fit-polo---dark-blue-zl100145/ | C224: Carhartt Wip | D224: Slim Fit POLO - DARK BLUE | E224: Men's T-Shirts & Polos | F224: Polo Shirts | G224: Slim Fit Polos | H224: Dark Blue | I224: XS | J224: 10.55 | K224: 6.82 | L224: SALE | M224: EUR | N224: 942 | O224: 3.1 | P224: 33.0 | S224: No | T224: 44955 | U224: https://img01.ztat.net/article/ZL100145.jpg | V224: =(Real_Sales[[#This Row],[Price_retail]]-Real_Sales[[#This Row],[Price_current]])/Real_Sales[[#This Row],[Price_retail]] -> 0.3535545 | W224: {=_xlfn.IFS(Real_Sales[[#This Row],[Discount]]=0%,"No Discount",Real_Sales[[#This Row],[Discount]]<=20%,"Light",Real_Sales[[#This Row],[Discount]]<=50%,"Moderate",Real_Sales[[#This Row],[Discount]]<=80%,"High", TRUE,"Very High")} -> Moderate | X224: =IF(Real_Sales[[#This Row],[Price_retail]]>$AC$3,"Premium","Average") -> Average | Y224: =IF(ISNUMBER(SEARCH("Basic",Real_Sales[[#This Row],[Product_name]])),"Yes","No") -> No | Z224: {=_xlfn.IFS(Real_Sales[[#This Row],[Price_retail]]<=15,1, Real_Sales[[#This Row],[Price_retail]]<=30,2, Real_Sales[[#This Row],[Price_retail]]<=50,3,Real_Sales[[#This Row],[Price_retail]]>50,4)} -> 1
A225: ZL100462 | B225: https://www.zalando.de/mango-man-essential-polo---dark-green-zl100462/ | C225: Mango Man | D225: Essential POLO - DARK GREEN | E225: Men's T-Shirts & Polos | F225: Polo Shirts | G225: Slim Fit Polos | H225: Dark Green | I225: XS | J225: 10.55 | K225: 10.55 | L225: Regular Price | M225: EUR | N225: 954 | O225: 3.7 | P225: 44.0 | S225: Yes | T225: 44955 | U225: https://img01.ztat.net/article/ZL100462.jpg | V225: =(Real_Sales[[#This Row],[Price_retail]]-Real_Sales[[#This Row],[Price_current]])/Real_Sales[[#This Row],[Price_retail]] -> 0 | W225: {=_xlfn.IFS(Real_Sales[[#This Row],[Discount]]=0%,"No Discount",Real_Sales[[#This Row],[Discount]]<=20%,"Light",Real_Sales[[#This Row],[Discount]]<=50%,"Moderate",Real_Sales[[#This Row],[Discount]]<=80%,"High", TRUE,"Very High")} -> No Discount | X225: =IF(Real_Sales[[#This Row],[Price_retail]]>$AC$3,"Premium","Average") -> Average | Y225: =IF(ISNUMBER(SEARCH("Basic",Real_Sales[[#This Row],[Product_name]])),"Yes","No") -> No | Z225: {=_xlfn.IFS(Real_Sales[[#This Row],[Price_retail]]<=15,1, Real_Sales[[#This Row],[Price_retail]]<=30,2, Real_Sales[[#This Row],[Price_retail]]<=50,3,Real_Sales[[#This Row],[Price_retail]]>50,4)} -> 1
A226: ZL100341 | B226: https://www.zalando.de/peter-werth-essential-polo---denim-blue-zl100341/ | C226: Peter Werth | D226: Essential POLO - DENIM BLUE | E226: Men's T-Shirts & Polos | F226: Polo Shirts | G226: Basic Polos | H226: Denim Blue | I226: XS | J226: 10.56 | K226: 7.6 | L226: SALE | M226: EUR | N226: 792 | O226: 4.6 | P226: 38.0 | S226: Yes | T226: 44955 | U226: https://img01.ztat.net/article/ZL100341.jpg | V226: =(Real_Sales[[#This Row],[Price_retail]]-Real_Sales[[#This Row],[Price_current]])/Real_Sales[[#This Row],[Price_retail]] -> 0.28030303 | W226: {=_xlfn.IFS(Real_Sales[[#This Row],[Discount]]=0%,"No Discount",Real_Sales[[#This Row],[Discount]]<=20%,"Light",Real_Sales[[#This Row],[Discount]]<=50%,"Moderate",Real_Sales[[#This Row],[Discount]]<=80%,"High", TRUE,"Very High")} -> Moderate | X226: =IF(Real_Sales[[#This Row],[Price_retail]]>$AC$3,"Premium","Average") -> Average | Y226: =IF(ISNUMBER(SEARCH("Basic",Real_Sales[[#This Row],[Product_name]])),"Yes","No") -> No | Z226: {=_xlfn.IFS(Real_Sales[[#This Row],[Price_retail]]<=15,1, Real_Sales[[#This Row],[Price_retail]]<=30,2, Real_Sales[[#This Row],[Price_retail]]<=50,3,Real_Sales[[#This Row],[Price_retail]]>50,4)} -> 1
A227: ZL100618 | B227: https://www.zalando.de/levi's-slim-fit-t-shirt---light-grey-zl100618/ | C227: Levi's | D227: Slim Fit T-SHIRT - LIGHT GREY | E227: Men's T-Shirts & Polos | F227: T-Shirts | G227: Slim Fit T-Shirts | H227: Light Grey | I227: M | J227: 10.59 | K227: 10.59 | L227: Regular Price | M227: EUR | N227: 108 | O227: 3.7 | P227: 34.0 | S227: Yes | T227: 44955 | U227: https://img01.ztat.net/article/ZL100618.jpg | V227: =(Real_Sales[[#This Row],[Price_retail]]-Real_Sales[[#This Row],[Price_current]])/Real_Sales[[#This Row],[Price_retail]] -> 0 | W227: {=_xlfn.IFS(Real_Sales[[#This Row],[Discount]]=0%,"No Discount",Real_Sales[[#This Row],[Discount]]<=20%,"Light",Real_Sales[[#This Row],[Discount]]<=50%,"Moderate",Real_Sales[[#This Row],[Discount]]<=80%,"High", TRUE,"Very High")} -> No Discount | X227: =IF(Real_Sales[[#This Row],[Price_retail]]>$AC$3,"Premium","Average") -> Average | Y227: =IF(ISNUMBER(SEARCH("Basic",Real_Sales[[#This Row],[Product_name]])),"Yes","No") -> No | Z227: {=_xlfn.IFS(Real_Sales[[#This Row],[Price_retail]]<=15,1, Real_Sales[[#This Row],[Price_retail]]<=30,2, Real_Sales[[#This Row],[Price_retail]]<=50,3,Real_Sales[[#This Row],[Price_retail]]>50,4)} -> 1
A228: ZL100332 | B228: https://www.zalando.de/björn-borg-basic-polo---bordeaux-zl100332/ | C228: Björn Borg | D228: Basic POLO - BORDEAUX | E228: Men's T-Shirts & Polos | F228: Polo Shirts | G228: Pique Polos | H228: Bordeaux | I228: XS | J228: 10.62 | K228: 10.62 | L228: Regular Price | M228: EUR | N228: 657 | O228: 4.2 | P228: 41.0 | S228: No | T228: 44955 | U228: https://img01.ztat.net/article/ZL100332.jpg | V228: =(Real_Sales[[#This Row],[Price_retail]]-Real_Sales[[#This Row],[Price_current]])/Real_Sales[[#This Row],[Price_retail]] -> 0 | W228: {=_xlfn.IFS(Real_Sales[[#This Row],[Discount]]=0%,"No Discount",Real_Sales[[#This Row],[Discount]]<=20%,"Light",Real_Sales[[#This Row],[Discount]]<=50%,"Moderate",Real_Sales[[#This Row],[Discount]]<=80%,"High", TRUE,"Very High")} -> No Discount | X228: =IF(Real_Sales[[#This Row],[Price_retail]]>$AC$3,"Premium","Average") -> Average | Y228: =IF(ISNUMBER(SEARCH("Basic",Real_Sales[[#This Row],[Product_name]])),"Yes","No") -> Yes | Z228: {=_xlfn.IFS(Real_Sales[[#This Row],[Price_retail]]<=15,1, Real_Sales[[#This Row],[Price_retail]]<=30,2, Real_Sales[[#This Row],[Price_retail]]<=50,3,Real_Sales[[#This Row],[Price_retail]]>50,4)} -> 1
A229: ZL100502 | B229: https://www.zalando.de/pier-one-slim-fit-t-shirt---off-white-zl100502/ | C229: Pier One | D229: Slim Fit T-SHIRT - OFF WHITE | E229: Men's T-Shirts & Polos | F229: T-Shirts | G229: Long Sleeve T-Shirts | H229: Off White | I229: S | J229: 10.64 | K229: 10.64 | L229: Regular Price | M229: EUR | N229: 214 | O229: 3.7 | P229: 35.0 | S229: Yes | T229: 44955 | U229: https://img01.ztat.net/article/ZL100502.jpg | V229: =(Real_Sales[[#This Row],[Price_retail]]-Real_Sales[[#This Row],[Price_current]])/Real_Sales[[#This Row],[Price_retail]] -> 0 | W229: {=_xlfn.IFS(Real_Sales[[#This Row],[Discount]]=0%,"No Discount",Real_Sales[[#This Row],[Discount]]<=20%,"Light",Real_Sales[[#This Row],[Discount]]<=50%,"Moderate",Real_Sales[[#This Row],[Discount]]<=80%,"High", TRUE,"Very High")} -> No Discount | X229: =IF(Real_Sales[[#This Row],[Price_retail]]>$AC$3,"Premium","Average") -> Average | Y229: =IF(ISNUMBER(SEARCH("Basic",Real_Sales[[#This Row],[Product_name]])),"Yes","No") -> No | Z229: {=_xlfn.IFS(Real_Sales[[#This Row],[Price_retail]]<=15,1, Real_Sales[[#This Row],[Price_retail]]<=30,2, Real_Sales[[#This Row],[Price_retail]]<=50,3,Real_Sales[[#This Row],[Price_retail]]>50,4)} -> 1
... A239: ZL100778 | B239: https://www.zalando.de/nike-essential-t-shirt---khaki-zl100778/ | C239: Nike | D239: Essential T-Shirt - Khaki | E239: Men's T-Shirts & Polos | F239: T-Shirts | G239: Long Sleeve T-Shirts | H239: Khaki | I239: XS | J239: 10.78 | K239: 10.78 | L239: Regular Price | M239: EUR | N239: 81 | O239: 4.7 | P239: 38.0 | S239: No | T239: 44955 | U239: https://img01.ztat.net/article/ZL100778.jpg | V239: =(Real_Sales[[#This Row],[Price_retail]]-Real_Sales[[#This Row],[Price_current]])/Real_Sales[[#This Row],[Price_retail]] -> 0 | W239: {=_xlfn.IFS(Real_Sales[[#This Row],[Discount]]=0%,"No Discount",Real_Sales[[#This Row],[Discount]]<=20%,"Light",Real_Sales[[#This Row],[Discount]]<=50%,"Moderate",Real_Sales[[#This Row],[Discount]]<=80%,"High", TRUE,"Very High")} -> No Discount | X239: =IF(Real_Sales[[#This Row],[Price_retail]]>$AC$3,"Premium","Average") -> Average | Y239: =IF(ISNUMBER(SEARCH("Basic",Real_Sales[[#This Row],[Product_name]])),"Yes","No") -> No | Z239: {=_xlfn.IFS(Real_Sales[[#This Row],[Price_retail]]<=15,1, Real_Sales[[#This Row],[Price_retail]]<=30,2, Real_Sales[[#This Row],[Price_retail]]<=50,3,Real_Sales[[#This Row],[Price_retail]]>50,4)} -> 1
A240: ZL100546 | B240: https://www.zalando.de/guess-basic-polo---white-zl100546/ | C240: Guess | D240: Basic POLO - WHITE | E240: Men's T-Shirts & Polos | F240: Polo Shirts | G240: Slim Fit Polos | H240: White | I240: XS | J240: 10.79 | K240: 10.79 | L240: Regular Price | M240: EUR | N240: 762 | O240: 3.6 | P240: 37.0 | T240: 44955 | U240: https://img01.ztat.net/article/ZL100546.jpg | V240: =(Real_Sales[[#This Row],[Price_retail]]-Real_Sales[[#This Row],[Price_current]])/Real_Sales[[#This Row],[Price_retail]] -> 0 | W240: {=_xlfn.IFS(Real_Sales[[#This Row],[Discount]]=0%,"No Discount",Real_Sales[[#This Row],[Discount]]<=20%,"Light",Real_Sales[[#This Row],[Discount]]<=50%,"Moderate",Real_Sales[[#This Row],[Discount]]<=80%,"High", TRUE,"Very High")} -> No Discount | X240: =IF(Real_Sales[[#This Row],[Price_retail]]>$AC$3,"Premium","Average") -> Average | Y240: =IF(ISNUMBER(SEARCH("Basic",Real_Sales[[#This Row],[Product_name]])),"Yes","No") -> Yes | Z240: {=_xlfn.IFS(Real_Sales[[#This Row],[Price_retail]]<=15,1, Real_Sales[[#This Row],[Price_retail]]<=30,2, Real_Sales[[#This Row],[Price_retail]]<=50,3,Real_Sales[[#This Row],[Price_retail]]>50,4)} -> 1
A241: ZL100322 | B241: https://www.zalando.de/barbour-slim-fit-t-shirt---off-white-zl100322/ | C241: Barbour | D241: Slim Fit T-SHIRT - OFF WHITE | E241: Men's T-Shirts & Polos | F241: T-Shirts | G241: Basic T-Shirts | H241: Off White | I241: XS | J241: 10.81 | K241: 10.81 | L241: Regular Price | M241: EUR | N241: 321 | O241: 3.5 | P241: 34.0 | S241: Yes | T241: 44955 | U241: https://img01.ztat.net/article/ZL100322.jpg | V241: =(Real_Sales[[#This Row],[Price_retail]]-Real_Sales[[#This Row],[Price_current]])/Real_Sales[[#This Row],[Price_retail]] -> 0 | W241: {=_xlfn.IFS(Real_Sales[[#This Row],[Discount]]=0%,"No Discount",Real_Sales[[#This Row],[Discount]]<=20%,"Light",Real_Sales[[#This Row],[Discount]]<=50%,"Moderate",Real_Sales[[#This Row],[Discount]]<=80%,"High", TRUE,"Very High")} -> No Discount | X241: =IF(Real_Sales[[#This Row],[Price_retail]]>$AC$3,"Premium","Average") -> Average | Y241: =IF(ISNUMBER(SEARCH("Basic",Real_Sales[[#This Row],[Product_name]])),"Yes","No") -> No | Z241: {=_xlfn.IFS(Real_Sales[[#This Row],[Price_retail]]<=15,1, Real_Sales[[#This Row],[Price_retail]]<=30,2, Real_Sales[[#This Row],[Price_retail]]<=50,3,Real_Sales[[#This Row],[Price_retail]]>50,4)} -> 1
A242: ZL100259 | B242: https://www.zalando.de/jack-wolfskin-print-t-shirt---khaki-zl100259/ | C242: Jack Wolfskin | D242: Print T-SHIRT - KHAKI | E242: Men's T-Shirts & Polos | F242: T-Shirts | G242: Basic T-Shirts | H242: Khaki | I242: S | J242: 10.88 | K242: 8.5 | L242: SALE | M242: EUR | N242: 463 | O242: 4.2 | P242: 40.0 | S242: Yes | T242: 44955 | U242: https://img01.ztat.net/article/ZL100259.jpg | V242: =(Real_Sales[[#This Row],[Price_retail]]-Real_Sales[[#This Row],[Price_current]])/Real_Sales[[#This Row],[Price_retail]] -> 0.21875 | W242: {=_xlfn.IFS(Real_Sales[[#This Row],[Discount]]=0%,"No Discount",Real_Sales[[#This Row],[Discount]]<=20%,"Light",Real_Sales[[#This Row],[Discount]]<=50%,"Moderate",Real_Sales[[#This Row],[Discount]]<=80%,"High", TRUE,"Very High")} -> Moderate | X242: =IF(Real_Sales[[#This Row],[Price_retail]]>$AC$3,"Premium","Average") -> Average | Y242: =IF(ISNUMBER(SEARCH("Basic",Real_Sales[[#This Row],[Product_name]])),"Yes","No") -> No | Z242: {=_xlfn.IFS(Real_Sales[[#This Row],[Price_retail]]<=15,1, Real_Sales[[#This Row],[Price_retail]]<=30,2, Real_Sales[[#This Row],[Price_retail]]<=50,3,Real_Sales[[#This Row],[Price_retail]]>50,4)} -> 1
...

Sheet Row
A1: Sku | B1: Product_url | C1: Brand | D1: Product_name | E1: Category | F1: Subcategory | G1: Subsubcategory | H1: Color | I1: Size_range | J1: Price_retail | K1: Price_current | L1: Price_label | M1: Currency | N1: Sort_by_ranking | O1: Rating | P1: Reviews_count | Q1: Promotion | R1: Sku_variant | S1: In_stock | T1: Scan_date | U1: Image_url | V1: Discount | W1: Discount Level
A2: ZL100000 | B2: https://www.zalando.de/petrol-industries-slim-fit-polo---red-zl100000/ | C2: Petrol Industries | D2: Slim Fit POLO - RED | E2: Men's T-Shirts & Polos | F2: Polo Shirts | G2: Pique Polos | H2: Red | J2: 99.99 | K2: 42.31 | L2: SALE | M2: EUR | N2: 652 | O2: 5.0 | P2: 47.0 | S2: No | T2: 44955 | U2: https://img01.ztat.net/article/ZL100000.jpg | V2: =(Sales[[#This Row],[Price_retail]]-Sales[[#This Row],[Price_current]])/Sales[[#This Row],[Price_retail]] -> 0.57685769 | W2: {=_xlfn.IFS(Sales[[#This Row],[Discount]]=0%,"No Discount",Sales[[#This Row],[Discount]]<=20%,"Light",Sales[[#This Row],[Discount]]<=50%,"Moderate",Sales[[#This Row],[Discount]]<=80%,"High", TRUE,"Very High")} -> High
A3: ZL100001 | B3: https://www.zalando.de/only-and-sons-denim-print-t-shirt---rust-zl100001/ | C3: Only & Sons | D3: Print T-SHIRT - RUST | E3: Men's T-Shirts & Polos | F3: T-Shirts | G3: Long Sleeve T-Shirts | H3: Rust | I3: S | J3: 22.03 | K3: 22.03 | L3: Regular Price | M3: EUR | N3: 316 | O3: 3.8 | P3: 0 | S3: Yes | T3: 44955 | U3: https://img01.ztat.net/article/ZL100001.jpg | V3: =(Sales[[#This Row],[Price_retail]]-Sales[[#This Row],[Price_current]])/Sales[[#This Row],[Price_retail]] -> 0 | W3: {=_xlfn.IFS(Sales[[#This Row],[Discount]]=0%,"No Discount",Sales[[#This Row],[Discount]]<=20%,"Light",Sales[[#This Row],[Discount]]<=50%,"Moderate",Sales[[#This Row],[Discount]]<=80%,"High", TRUE,"Very High")} -> No Discount
A4: ZL100002 | B4: https://www.zalando.de/anerkjendt-essential-t-shirt---grey-melange-zl100002/ | C4: Anerkjendt | D4: Essential T-SHIRT - GREY MELANGE | E4: Men's T-Shirts & Polos | F4: T-Shirts | G4: Slim Fit T-Shirts | H4: Grey Melange | I4: XS | J4: 26.38 | K4: 26.38 | L4: Regular Price | M4: EUR | N4: 990 | O4: 3.1 | P4: 29.0 | S4: Yes | T4: 44955 | U4: https://img01.ztat.net/article/ZL100002.jpg | V4: =(Sales[[#This Row],[Price_retail]]-Sales[[#This Row],[Price_current]])/Sales[[#This Row],[Price_retail]] -> 0 | W4: {=_xlfn.IFS(Sales[[#This Row],[Discount]]=0%,"No Discount",Sales[[#This Row],[Discount]]<=20%,"Light",Sales[[#This Row],[Discount]]<=50%,"Moderate",Sales[[#This Row],[Discount]]<=80%,"High", TRUE,"Very High")} -> No Discount
A5: ZL100003 | B5: https://www.zalando.de/adidas-performance-regular-fit-t-shirt---khaki-zl100003/ | C5: Adidas Performance | D5: Regular Fit T-SHIRT - KHAKI | E5: Men's T-Shirts & Polos | F5: T-Shirts | G5: Slim Fit T-Shirts | H5: Khaki | I5: M | J5: 21.05 | K5: 12.67 | L5: SALE | M5: EUR | N5: 473 | O5: 3.9 | P5: 31.0 | S5: Yes | T5: 44955 | U5: https://img01.ztat.net/article/ZL100003.jpg | V5: =(Sales[[#This Row],[Price_retail]]-Sales[[#This Row],[Price_current]])/Sales[[#This Row],[Price_retail]] -> 0.39809976 | W5: {=_xlfn.IFS(Sales[[#This Row],[Discount]]=0%,"No Discount",Sales[[#This Row],[Discount]]<=20%,"Light",Sales[[#This Row],[Discount]]<=50%,"Moderate",Sales[[#This Row],[Discount]]<=80%,"High", TRUE,"Very High")} -> Moderate
A6: ZL100288 | B6: https://www.zalando.de/lacoste-essential-polo---rust-zl100004/ | C6: Lacoste | D6: Essential POLO - RUST | E6: Men's T-Shirts & Polos | F6: Polo Shirts | G6: Pique Polos | H6: Rust | I6: XS | J6: 32.81 | K6: 13.19 | L6: SALE | M6: EUR | N6: 535 | O6: 3.3 | P6: 34.0 | S6: Yes | T6: 44955 | U6: https://img01.ztat.net/article/ZL100004.jpg | V6: =(Sales[[#This Row],[Price_retail]]-Sales[[#This Row],[Price_current]])/Sales[[#This Row],[Price_retail]] -> 0.59798842 | W6: {=_xlfn.IFS(Sales[[#This Row],[Discount]]=0%,"No Discount",Sales[[#This Row],[Discount]]<=20%,"Light",Sales[[#This Row],[Discount]]<=50%,"Moderate",Sales[[#This Row],[Discount]]<=80%,"High", TRUE,"Very High")} -> High
A7: ZL100005 | B7: https://www.zalando.de/wrangler-basic-t-shirt---mint-zl100005/ | C7: Wrangler | D7: Basic T-SHIRT - MINT | E7: Men's T-Shirts & Polos | F7: T-Shirts | G7: Basic T-Shirts | H7: Mint | I7: XS | J7: 16.77 | K7: 16.77 | L7: Regular Price | M7: EUR | N7: 497 | O7: 4.6 | P7: 32.0 | S7: Yes | T7: 44955 | U7: https://img01.ztat.net/article/ZL100005.jpg | V7: =(Sales[[#This Row],[Price_retail]]-Sales[[#This Row],[Price_current]])/Sales[[#This Row],[Price_retail]] -> 0 | W7: {=_xlfn.IFS(Sales[[#This Row],[Discount]]=0%,"No Discount",Sales[[#This Row],[Discount]]<=20%,"Light",Sales[[#This Row],[Discount]]<=50%,"Moderate",Sales[[#This Row],[Discount]]<=80%,"High", TRUE,"Very High")} -> No Discount
A8: ZL100006 | B8: https://www.zalando.de/eterna-regular-fit-t-shirt---white-zl100006/ | C8: Eterna | D8: Regular Fit T-SHIRT - WHITE | E8: Men's T-Shirts & Polos | F8: T-Shirts | G8: Long Sleeve T-Shirts | H8: White | I8: S | J8: 10.3 | K8: 7.86 | L8: SALE | M8: EUR | N8: 524 | O8: 3.5 | P8: 27.0 | S8: No | T8: 44955 | U8: https://img01.ztat.net/article/ZL100006.jpg | V8: =(Sales[[#This Row],[Price_retail]]-Sales[[#This Row],[Price_current]])/Sales[[#This Row],[Price_retail]] -> 0.2368932 | W8: {=_xlfn.IFS(Sales[[#This Row],[Discount]]=0%,"No Discount",Sales[[#This Row],[Discount]]<=20%,"Light",Sales[[#This Row],[Discount]]<=50%,"Moderate",Sales[[#This Row],[Discount]]<=80%,"High", TRUE,"Very High")} -> Moderate
A9: ZL100007 | B9: https://www.zalando.de/nike-basic-t-shirt---bordeaux-zl100007/ | C9: Nike | D9: Basic T-SHIRT - BORDEAUX | E9: Men's T-Shirts & Polos | F9: T-Shirts | G9: Print T-Shirts | H9: Bordeaux | I9: XS | J9: 15.61 | K9: 15.61 | L9: Regular Price | M9: EUR | N9: 963 | O9: 3.7 | P9: 38.0 | S9: Yes | T9: 44955 | U9: https://img01.ztat.net/article/ZL100007.jpg | V9: =(Sales[[#This Row],[Price_retail]]-Sales[[#This Row],[Price_current]])/Sales[[#This Row],[Price_retail]] -> 0 | W9: {=_xlfn.IFS(Sales[[#This Row],[Discount]]=0%,"No Discount",Sales[[#This Row],[Discount]]<=20%,"Light",Sales[[#This Row],[Discount]]<=50%,"Moderate",Sales[[#This Row],[Discount]]<=80%,"High", TRUE,"Very High")} -> No Discount
A10: ZL100008 | B10: https://www.zalando.de/adidas-performance-print-t-shirt---khaki-zl100008/ | C10: Adidas Performance | D10: Print T-SHIRT - KHAKI | E10: Men's T-Shirts & Polos | F10: T-Shirts | G10: Slim Fit T-Shirts | H10: Khaki | I10: S | J10: 15.06 | K10: 6.31 | L10: SALE | M10: EUR | N10: 557 | O10: 3.4 | P10: 41.0 | S10: No | T10: 44955 | U10: https://img01.ztat.net/article/ZL100008.jpg | V10: =(Sales[[#This Row],[Price_retail]]-Sales[[#This Row],[Price_current]])/Sales[[#This Row],[Price_retail]] -> 0.5810093 | W10: {=_xlfn.IFS(Sales[[#This Row],[Discount]]=0%,"No Discount",Sales[[#This Row],[Discount]]<=20%,"Light",Sales[[#This Row],[Discount]]<=50%,"Moderate",Sales[[#This Row],[Discount]]<=80%,"High", TRUE,"Very High")} -> High
A11: ZL100009 | B11: https://www.zalando.de/jack-and-jones-slim-fit-polo---denim-blue-zl100009/ | C11: Jack & Jones | D11: Slim Fit POLO - DENIM BLUE | E11: Men's T-Shirts & Polos | F11: Polo Shirts | G11: Slim Fit Polos | H11: Denim Blue | I11: S | J11: 8.99 | K11: 8.99 | L11: Regular Price | M11: EUR | N11: 741 | O11: 3.7 | P11: 43.0 | S11: No | T11: 44955 | U11: https://img01.ztat.net/article/ZL100009.jpg | V11: =(Sales[[#This Row],[Price_retail]]-Sales[[#This Row],[Price_current]])/Sales[[#This Row],[Price_retail]] -> 0 | W11: {=_xlfn.IFS(Sales[[#This Row],[Discount]]=0%,"No Discount",Sales[[#This Row],[Discount]]<=20%,"Light",Sales[[#This Row],[Discount]]<=50%,"Moderate",Sales[[#This Row],[Discount]]<=80%,"High", TRUE,"Very High")} -> No Discount
A12: ZL100010 | B12: https://www.zalando.de/j.lindeberg-slim-fit-polo---beige-zl100010/ | C12: J.Lindeberg | D12: Slim Fit POLO - BEIGE | E12: Men's T-Shirts & Polos | F12: Polo Shirts | G12: Pique Polos | H12: Beige | I12: XS | J12: 11.49 | K12: 8.22 | L12: SALE | M12: EUR | N12: 442 | O12: 3.2 | P12: 35.0 | S12: No | T12: 44955 | U12: https://img01.ztat.net/article/ZL100010.jpg | V12: =(Sales[[#This Row],[Price_retail]]-Sales[[#This Row],[Price_current]])/Sales[[#This Row],[Price_retail]] -> 0.2845953 | W12: {=_xlfn.IFS(Sales[[#This Row],[Discount]]=0%,"No Discount",Sales[[#This Row],[Discount]]<=20%,"Light",Sales[[#This Row],[Discount]]<=50%,"Moderate",Sales[[#This Row],[Discount]]<=80%,"High", TRUE,"Very High")} -> Moderate
A13: ZL100011 | B13: https://www.zalando.de/teddy-smith-regular-fit-polo---beige-zl100011/ | C13: Teddy Smith | D13: Regular Fit POLO - BEIGE | E13: Men's T-Shirts & Polos | F13: Polo Shirts | G13: Slim Fit Polos | H13: Beige | I13: XS | J13: 18.59 | K13: 13.08 | L13: SALE | M13: EUR | N13: 793 | O13: 4.1 | P13: 41.0 | S13: Yes | T13: 44955 | U13: https://img01.ztat.net/article/ZL100011.jpg | V13: =(Sales[[#This Row],[Price_retail]]-Sales[[#This Row],[Price_current]])/Sales[[#This Row],[Price_retail]] -> 0.29639591 | W13: {=_xlfn.IFS(Sales[[#This Row],[Discount]]=0%,"No Discount",Sales[[#This Row],[Discount]]<=20%,"Light",Sales[[#This Row],[Discount]]<=50%,"Moderate",Sales[[#This Row],[Discount]]<=80%,"High", TRUE,"Very High")} -> Moderate
A14: ZL100012 | B14: https://www.zalando.de/pier-one-regular-fit-t-shirt---rust-zl100012/ | C14: Pier One | D14: Regular Fit T-SHIRT - RUST | E14: Men's T-Shirts & Polos | F14: T-Shirts | G14: Basic T-Shirts | H14: Rust | I14: S | J14: 12.39 | K14: 12.39 | L14: Regular Price | M14: EUR | N14: 217 | O14: 4.2 | P14: 35.0 | S14: Yes | T14: 44955 | U14: https://img01.ztat.net/article/ZL100012.jpg | V14: =(Sales[[#This Row],[Price_retail]]-Sales[[#This Row],[Price_current]])/Sales[[#This Row],[Price_retail]] -> 0 | W14: {=_xlfn.IFS(Sales[[#This Row],[Discount]]=0%,"No Discount",Sales[[#This Row],[Discount]]<=20%,"Light",Sales[[#This Row],[Discount]]<=50%,"Moderate",Sales[[#This Row],[Discount]]<=80%,"High", TRUE,"Very High")} -> No Discount
... A27: ZL100025 | B27: https://www.zalando.de/nike-slim-fit-t-shirt---red-zl100025/ | C27: Nike | D27: Slim Fit T-SHIRT - RED | E27: Men's T-Shirts & Polos | F27: T-Shirts | G27: Print T-Shirts | H27: Red | I27: M | J27: 25.11 | K27: 25.11 | L27: Regular Price | M27: EUR | N27: 797 | O27: 0 | P27: 32.0 | S27: Yes | T27: 44955 | U27: https://img01.ztat.net/article/ZL100025.jpg | V27: =(Sales[[#This Row],[Price_retail]]-Sales[[#This Row],[Price_current]])/Sales[[#This Row],[Price_retail]] -> 0 | W27: {=_xlfn.IFS(Sales[[#This Row],[Discount]]=0%,"No Discount",Sales[[#This Row],[Discount]]<=20%,"Light",Sales[[#This Row],[Discount]]<=50%,"Moderate",Sales[[#This Row],[Discount]]<=80%,"High", TRUE,"Very High")} -> No Discount
A28: ZL100026 | B28: https://www.zalando.de/adidas-originals-basic-t-shirt---bordeaux-zl100026/ | C28: Adidas Originals | D28: Basic T-SHIRT - BORDEAUX | E28: Men's T-Shirts & Polos | F28: T-Shirts | G28: Long Sleeve T-Shirts | H28: Bordeaux | J28: 13.82 | K28: 13.82 | L28: Regular Price | M28: EUR | N28: 273 | O28: 0 | P28: 40.0 | S28: Yes | T28: 44955 | U28: https://img01.ztat.net/article/ZL100026.jpg | V28: =(Sales[[#This Row],[Price_retail]]-Sales[[#This Row],[Price_current]])/Sales[[#This Row],[Price_retail]] -> 0 | W28: {=_xlfn.IFS(Sales[[#This Row],[Discount]]=0%,"No Discount",Sales[[#This Row],[Discount]]<=20%,"Light",Sales[[#This Row],[Discount]]<=50%,"Moderate",Sales[[#This Row],[Discount]]<=80%,"High", TRUE,"Very High")} -> No Discount
A29: ZL100027 | B29: https://www.zalando.de/nike-regular-fit-polo---bordeaux-zl100027/ | C29: Nike | D29: Regular Fit POLO - BORDEAUX | E29: Men's T-Shirts & Polos | F29: Polo Shirts | G29: Basic Polos | H29: Bordeaux | I29: XS | J29: 30.39 | K29: 30.39 | L29: Regular Price | M29: EUR | N29: 374 | O29: 3.4 | P29: N/A | S29: No | T29: 44955 | U29: https://img01.ztat.net/article/ZL100027.jpg | V29: =(Sales[[#This Row],[Price_retail]]-Sales[[#This Row],[Price_current]])/Sales[[#This Row],[Price_retail]] -> 0 | W29: {=_xlfn.IFS(Sales[[#This Row],[Discount]]=0%,"No Discount",Sales[[#This Row],[Discount]]<=20%,"Light",Sales[[#This Row],[Discount]]<=50%,"Moderate",Sales[[#This Row],[Discount]]<=80%,"High", TRUE,"Very High")} -> No Discount
A30: ZL100028 | B30: https://www.zalando.de/jack-jones-junior-essential-polo---off-white-zl100028/ | C30: Jack & Jones Junior | D30: Essential Polo - Off White | E30: Men's T-Shirts & Polos | F30: Polo Shirts | G30: Pique Polos | H30: Off White | I30: M | J30: 17.76 | K30: 17.76 | L30: Regular Price | M30: EUR | N30: 727 | O30: 4.1 | P30: 36.0 | S30: Yes | T30: 44955 | U30: https://img01.ztat.net/article/ZL100028.jpg | V30: =(Sales[[#This Row],[Price_retail]]-Sales[[#This Row],[Price_current]])/Sales[[#This Row],[Price_retail]] -> 0 | W30: {=_xlfn.IFS(Sales[[#This Row],[Discount]]=0%,"No Discount",Sales[[#This Row],[Discount]]<=20%,"Light",Sales[[#This Row],[Discount]]<=50%,"Moderate",Sales[[#This Row],[Discount]]<=80%,"High", TRUE,"Very High")} -> No Discount
A31: ZL100029 | B31: https://www.zalando.de/nike-basic-polo---black-zl100029/ | C31: Nike | D31: Basic POLO - BLACK | E31: Men's T-Shirts & Polos | F31: Polo Shirts | G31: Slim Fit Polos | H31: Black | I31: XS | J31: 19.84 | K31: 19.84 | L31: Regular Price | M31: EUR | N31: 380 | O31: 4.3 | P31: 30.0 | S31: No | T31: 44955 | U31: https://img01.ztat.net/article/ZL100029.jpg | V31: =(Sales[[#This Row],[Price_retail]]-Sales[[#This Row],[Price_current]])/Sales[[#This Row],[Price_retail]] -> 0 | W31: {=_xlfn.IFS(Sales[[#This Row],[Discount]]=0%,"No Discount",Sales[[#This Row],[Discount]]<=20%,"Light",Sales[[#This Row],[Discount]]<=50%,"Moderate",Sales[[#This Row],[Discount]]<=80%,"High", TRUE,"Very High")} -> No Discount
A32: ZL100030 | B32: https://www.zalando.de/umbro-essential-t-shirt---red-zl100030/ | C32: Umbro | D32: Essential T-SHIRT - RED | E32: Men's T-Shirts & Polos | F32: T-Shirts | G32: Basic T-Shirts | H32: Red | I32: S | J32: 21.06 | K32: 21.06 | L32: Regular Price | M32: EUR | N32: 429 | O32: 3.7 | P32: 38.0 | S32: Yes | T32: 44955 | U32: https://img01.ztat.net/article/ZL100030.jpg | V32: =(Sales[[#This Row],[Price_retail]]-Sales[[#This Row],[Price_current]])/Sales[[#This Row],[Price_retail]] -> 0 | W32: {=_xlfn.IFS(Sales[[#This Row],[Discount]]=0%,"No Discount",Sales[[#This Row],[Discount]]<=20%,"Light",Sales[[#This Row],[Discount]]<=50%,"Moderate",Sales[[#This Row],[Discount]]<=80%,"High", TRUE,"Very High")} -> No Discount
A33: ZL100031 | B33: https://www.zalando.de/boss-regular-fit-polo---off-white-zl100031/ | C33: Boss | D33: Regular Fit POLO - OFF WHITE | E33: Men's T-Shirts & Polos | F33: Polo Shirts | G33: Slim Fit Polos | H33: Off White | I33: XS | J33: 16.83 | K33: 9.95 | L33: SALE | M33: EUR | N33: 34 | O33: 4.1 | P33: 29.0 | S33: Yes | T33: 44955 | U33: https://img01.ztat.net/article/ZL100031.jpg | V33: =(Sales[[#This Row],[Price_retail]]-Sales[[#This Row],[Price_current]])/Sales[[#This Row],[Price_retail]] -> 0.40879382 | W33: {=_xlfn.IFS(Sales[[#This Row],[Discount]]=0%,"No Discount",Sales[[#This Row],[Discount]]<=20%,"Light",Sales[[#This Row],[Discount]]<=50%,"Moderate",Sales[[#This Row],[Discount]]<=80%,"High", TRUE,"Very High")} -> Moderate
A34: ZL100032 | B34: https://www.zalando.de/timberland-slim-fit-t-shirt---dark-green-zl100032/ | C34: Timberland | D34: Slim Fit T-SHIRT - DARK GREEN | E34: Men's T-Shirts & Polos | F34: T-Shirts | G34: Slim Fit T-Shirts | H34: Dark Green | I34: XS | J34: 20.82 | K34: 20.82 | L34: Regular Price | M34: EUR | N34: 226 | O34: 3.4 | P34: 29.0 | S34: Yes | T34: 44955 | U34: https://img01.ztat.net/article/ZL100032.jpg | V34: =(Sales[[#This Row],[Price_retail]]-Sales[[#This Row],[Price_current]])/Sales[[#This Row],[Price_retail]] -> 0 | W34: {=_xlfn.IFS(Sales[[#This Row],[Discount]]=0%,"No Discount",Sales[[#This Row],[Discount]]<=20%,"Light",Sales[[#This Row],[Discount]]<=50%,"Moderate",Sales[[#This Row],[Discount]]<=80%,"High", TRUE,"Very High")} -> No Discount
A35: ZL100033 | B35: https://www.zalando.de/only-and-sons-denim-regular-fit-polo---khaki-zl100033/ | C35: Only & Sons | D35: Regular Fit POLO - KHAKI | E35: Men's T-Shirts & Polos | F35: Polo Shirts | G35: Pique Polos | H35: Khaki | I35: XS | J35: 26.46 | K35: 26.46 | L35: Regular Price | M35: EUR | N35: 937 | O35: 0 | P35: 31.0 | S35: Yes | T35: 44955 | U35: https://img01.ztat.net/article/ZL100033.jpg | V35: =(Sales[[#This Row],[Price_retail]]-Sales[[#This Row],[Price_current]])/Sales[[#This Row],[Price_retail]] -> 0 | W35: {=_xlfn.IFS(Sales[[#This Row],[Discount]]=0%,"No Discount",Sales[[#This Row],[Discount]]<=20%,"Light",Sales[[#This Row],[Discount]]<=50%,"Moderate",Sales[[#This Row],[Discount]]<=80%,"High", TRUE,"Very High")} -> No Discount
A36: ZL100034 | B36: https://www.zalando.de/diesel-slim-fit-polo---royal-blue-zl100034/ | C36: Diesel | D36: Slim Fit POLO - ROYAL BLUE | E36: Men's T-Shirts & Polos | F36: Polo Shirts | G36: Basic Polos | H36: Royal Blue | I36: M | J36: 15.22 | K36: 7.41 | L36: SALE | M36: EUR | N36: 53 | O36: 0 | P36: 28.0 | S36: Yes | T36: 44955 | U36: https://img01.ztat.net/article/ZL100034.jpg | V36: =(Sales[[#This Row],[Price_retail]]-Sales[[#This Row],[Price_current]])/Sales[[#This Row],[Price_retail]] -> 0.5131406 | W36: {=_xlfn.IFS(Sales[[#This Row],[Discount]]=0%,"No Discount",Sales[[#This Row],[Discount]]<=20%,"Light",Sales[[#This Row],[Discount]]<=50%,"Moderate",Sales[[#This Row],[Discount]]<=80%,"High", TRUE,"Very High")} -> High
A37: ZL100035 | B37: https://www.zalando.de/kappa-print-t-shirt---royal-blue-zl100035/ | C37: Kappa | D37: Print T-SHIRT - ROYAL BLUE | E37: Men's T-Shirts & Polos | F37: T-Shirts | G37: Slim Fit T-Shirts | H37: Royal Blue | I37: XS | J37: 8.99 | K37: 6.41 | L37: SALE | M37: EUR | N37: 922 | O37: 4.6 | P37: 33.0 | S37: Yes | T37: 44955 | U37: https://img01.ztat.net/article/ZL100035.jpg | V37: =(Sales[[#This Row],[Price_retail]]-Sales[[#This Row],[Price_current]])/Sales[[#This Row],[Price_retail]] -> 0.28698554 | W37: {=_xlfn.IFS(Sales[[#This Row],[Discount]]=0%,"No Discount",Sales[[#This Row],[Discount]]<=20%,"Light",Sales[[#This Row],[Discount]]<=50%,"Moderate",Sales[[#This Row],[Discount]]<=80%,"High", TRUE,"Very High")} -> Moderate
A38: ZL100036 | B38: https://www.zalando.de/anerkjendt-print-t-shirt---dark-blue-zl100036/ | C38: Anerkjendt | D38: Print T-SHIRT - DARK BLUE | E38: Men's T-Shirts & Polos | F38: T-Shirts | G38: Print T-Shirts | H38: Dark Blue | I38: XS | J38: 18.43 | K38: 18.43 | L38: Regular Price | M38: EUR | N38: 866 | O38: 4.1 | P38: 29.0 | S38: Yes | T38: 44955 | U38: https://img01.ztat.net/article/ZL100036.jpg | V38: =(Sales[[#This Row],[Price_retail]]-Sales[[#This Row],[Price_current]])/Sales[[#This Row],[Price_retail]] -> 0 | W38: {=_xlfn.IFS(Sales[[#This Row],[Discount]]=0%,"No Discount",Sales[[#This Row],[Discount]]<=20%,"Light",Sales[[#This Row],[Discount]]<=50%,"Moderate",Sales[[#This Row],[Discount]]<=80%,"High", TRUE,"Very High")} -> No Discount
A39: ZL100037 | B39: https://www.zalando.de/umbro-print-polo---light-grey-zl100037/ | C39: Umbro | D39: Print POLO - LIGHT GREY | E39: Men's T-Shirts & Polos | F39: Polo Shirts | G39: Slim Fit Polos | H39: Light Grey | I39: M | J39: 8.99 | K39: 5.17 | L39: SALE | M39: EUR | N39: 143 | O39: 3.4 | P39: 30.0 | S39: Yes | T39: 44955 | U39: https://img01.ztat.net/article/ZL100037.jpg | V39: =(Sales[[#This Row],[Price_retail]]-Sales[[#This Row],[Price_current]])/Sales[[#This Row],[Price_retail]] -> 0.42491657 | W39: {=_xlfn.IFS(Sales[[#This Row],[Discount]]=0%,"No Discount",Sales[[#This Row],[Discount]]<=20%,"Light",Sales[[#This Row],[Discount]]<=50%,"Moderate",Sales[[#This Row],[Discount]]<=80%,"High", TRUE,"Very High")} -> Moderate
A40: ZL100038 | B40: https://www.zalando.de/name-it-regular-fit-polo---bordeaux-zl100038/ | C40: Name It | D40: Regular Fit POLO - BORDEAUX | E40: Men's T-Shirts & Polos | F40: Polo Shirts | G40: Basic Polos | H40: Bordeaux | I40: S | J40: 18.28 | K40: 18.28 | L40: Regular Price | M40: EUR | N40: 763 | O40: 3.5 | P40: 31.0 | S40: Yes | T40: 44955 | U40: https://img01.ztat.net/article/ZL100038.jpg | V40: =(Sales[[#This Row],[Price_retail]]-Sales[[#This Row],[Price_current]])/Sales[[#This Row],[Price_retail]] -> 0 | W40: {=_xlfn.IFS(Sales[[#This Row],[Discount]]=0%,"No Discount",Sales[[#This Row],[Discount]]<=20%,"Light",Sales[[#This Row],[Discount]]<=50%,"Moderate",Sales[[#This Row],[Discount]]<=80%,"High", TRUE,"Very High")} -> No Discount
... A54: ZL100052 | B54: https://www.zalando.de/gap-basic-polo---dark-green-zl100052/ | C54: Gap | D54: Basic POLO - DARK GREEN | E54: Men's T-Shirts & Polos | F54: Polo Shirts | G54: Basic Polos | H54: Dark Green | I54: S | J54: 22.53 | K54: 22.53 | L54: Regular Price | M54: EUR | N54: 158 | O54: 3.3 | P54: 30.0 | S54: Yes | T54: 44955 | U54: https://img01.ztat.net/article/ZL100052.jpg | V54: =(Sales[[#This Row],[Price_retail]]-Sales[[#This Row],[Price_current]])/Sales[[#This Row],[Price_retail]] -> 0 | W54: {=_xlfn.IFS(Sales[[#This Row],[Discount]]=0%,"No Discount",Sales[[#This Row],[Discount]]<=20%,"Light",Sales[[#This Row],[Discount]]<=50%,"Moderate",Sales[[#This Row],[Discount]]<=80%,"High", TRUE,"Very High")} -> No Discount
A55: ZL100053 | B55: https://www.zalando.de/topman-print-t-shirt---dark-green-zl100053/ | C55: Topman | D55: Print T-SHIRT - DARK GREEN | E55: Men's T-Shirts & Polos | F55: T-Shirts | G55: Long Sleeve T-Shirts | H55: Dark Green | J55: 27.26 | K55: 27.26 | L55: NEW | M55: EUR | N55: 734 | O55: 4.4 | P55: 0 | S55: Yes | T55: 44955 | U55: https://img01.ztat.net/article/ZL100053.jpg | V55: =(Sales[[#This Row],[Price_retail]]-Sales[[#This Row],[Price_current]])/Sales[[#This Row],[Price_retail]] -> 0 | W55: {=_xlfn.IFS(Sales[[#This Row],[Discount]]=0%,"No Discount",Sales[[#This Row],[Discount]]<=20%,"Light",Sales[[#This Row],[Discount]]<=50%,"Moderate",Sales[[#This Row],[Discount]]<=80%,"High", TRUE,"Very High")} -> No Discount
A56: ZL100054 | B56: https://www.zalando.de/craft-basic-polo---denim-blue-zl100054/ | C56: Craft | D56: Basic POLO - DENIM BLUE | E56: Men's T-Shirts & Polos | F56: Polo Shirts | G56: Pique Polos | H56: Denim Blue | I56: XS | J56: 9.7 | K56: 4.88 | L56: SALE | M56: EUR | N56: 228 | O56: 3.2 | P56: 37.0 | S56: Yes | T56: 44955 | U56: https://img01.ztat.net/article/ZL100054.jpg | V56: =(Sales[[#This Row],[Price_retail]]-Sales[[#This Row],[Price_current]])/Sales[[#This Row],[Price_retail]] -> 0.49690722 | W56: {=_xlfn.IFS(Sales[[#This Row],[Discount]]=0%,"No Discount",Sales[[#This Row],[Discount]]<=20%,"Light",Sales[[#This Row],[Discount]]<=50%,"Moderate",Sales[[#This Row],[Discount]]<=80%,"High", TRUE,"Very High")} -> Moderate
A57: ZL100055 | B57: https://www.zalando.de/only-and-sons-denim-essential-polo---rust-zl100055/ | C57: Only & Sons | D57: Essential POLO - RUST | E57: Men's T-Shirts & Polos | F57: Polo Shirts | G57: Slim Fit Polos | I57: S | J57: 16.03 | K57: 13.1 | L57: SALE | M57: EUR | N57: 286 | O57: 3.3 | P57: 33.0 | S57: Yes | T57: 44955 | U57: https://img01.ztat.net/article/ZL100055.jpg | V57: =(Sales[[#This Row],[Price_retail]]-Sales[[#This Row],[Price_current]])/Sales[[#This Row],[Price_retail]] -> 0.18278228 | W57: {=_xlfn.IFS(Sales[[#This Row],[Discount]]=0%,"No Discount",Sales[[#This Row],[Discount]]<=20%,"Light",Sales[[#This Row],[Discount]]<=50%,"Moderate",Sales[[#This Row],[Discount]]<=80%,"High", TRUE,"Very High")} -> Light
A58: ZL100056 | B58: https://www.zalando.de/anerkjendt-slim-fit-t-shirt---white-zl100056/ | C58: Anerkjendt | D58: Slim Fit T-SHIRT - WHITE | E58: Men's T-Shirts & Polos | F58: T-Shirts | G58: Print T-Shirts | H58: White | I58: XS | J58: 31.71 | K58: 18.25 | L58: SALE | M58: EUR | N58: 643 | O58: 3.8 | P58: 40.0 | S58: Yes | T58: 44955 | U58: https://img01.ztat.net/article/ZL100056.jpg | V58: =(Sales[[#This Row],[Price_retail]]-Sales[[#This Row],[Price_current]])/Sales[[#This Row],[Price_retail]] -> 0.42447178 | W58: {=_xlfn.IFS(Sales[[#This Row],[Discount]]=0%,"No Discount",Sales[[#This Row],[Discount]]<=20%,"Light",Sales[[#This Row],[Discount]]<=50%,"Moderate",Sales[[#This Row],[Discount]]<=80%,"High", TRUE,"Very High")} -> Moderate
A59: ZL100057 | B59: https://www.zalando.de/levi's-print-polo---beige-zl100057/ | C59: Levi's | D59: Print POLO - BEIGE | E59: Men's T-Shirts & Polos | F59: Polo Shirts | G59: Pique Polos | H59: Beige | I59: S | J59: 22.85 | K59: 22.85 | L59: Regular Price | M59: EUR | N59: 300 | O59: 4.5 | P59: 0 | S59: Yes | T59: 44955 | U59: https://img01.ztat.net/article/ZL100057.jpg | V59: =(Sales[[#This Row],[Price_retail]]-Sales[[#This Row],[Price_current]])/Sales[[#This Row],[Price_retail]] -> 0 | W59: {=_xlfn.IFS(Sales[[#This Row],[Discount]]=0%,"No Discount",Sales[[#This Row],[Discount]]<=20%,"Light",Sales[[#This Row],[Discount]]<=50%,"Moderate",Sales[[#This Row],[Discount]]<=80%,"High", TRUE,"Very High")} -> No Discount
A60: ZL100058 | B60: https://www.zalando.de/hummel-essential-t-shirt---grey-melange-zl100058/ | C60: Hummel | D60: Essential T-Shirt - Grey Melange | E60: Men's T-Shirts & Polos | F60: T-Shirts | G60: Long Sleeve T-Shirts | H60: Grey Melange | I60: XS | J60: 24.8 | K60: 16.8 | L60: SALE | M60: EUR | N60: 730 | O60: 3.5 | P60: 38.0 | S60: Yes | T60: 44955 | U60: https://img01.ztat.net/article/ZL100058.jpg | V60: =(Sales[[#This Row],[Price_retail]]-Sales[[#This Row],[Price_current]])/Sales[[#This Row],[Price_retail]] -> 0.32258065 | W60: {=_xlfn.IFS(Sales[[#This Row],[Discount]]=0%,"No Discount",Sales[[#This Row],[Discount]]<=20%,"Light",Sales[[#This Row],[Discount]]<=50%,"Moderate",Sales[[#This Row],[Discount]]<=80%,"High", TRUE,"Very High")} -> Moderate
A61: ZL100059 | B61: https://www.zalando.de/adidas-performance-regular-fit-polo---dark-blue-zl100059/ | C61: Adidas Performance | D61: Regular Fit POLO - DARK BLUE | E61: Men's T-Shirts & Polos | F61: Polo Shirts | G61: Basic Polos | H61: Dark Blue | I61: XS | J61: 33.19 | K61: 33.19 | L61: Regular Price | M61: EUR | N61: 782 | O61: 0 | P61: 46.0 | S61: Yes | T61: 44955 | U61: https://img01.ztat.net/article/ZL100059.jpg | V61: =(Sales[[#This Row],[Price_retail]]-Sales[[#This Row],[Price_current]])/Sales[[#This Row],[Price_retail]] -> 0 | W61: {=_xlfn.IFS(Sales[[#This Row],[Discount]]=0%,"No Discount",Sales[[#This Row],[Discount]]<=20%,"Light",Sales[[#This Row],[Discount]]<=50%,"Moderate",Sales[[#This Row],[Discount]]<=80%,"High", TRUE,"Very High")} -> No Discount
A62: ZL100060 | B62: https://www.zalando.de/digel-regular-fit-polo---anthracite-zl100060/ | C62: Digel | D62: Regular Fit POLO - ANTHRACITE | E62: Men's T-Shirts & Polos | F62: Polo Shirts | G62: Slim Fit Polos | H62: Anthracite | I62: M | J62: 32.96 | K62: 32.96 | L62: Regular Price | M62: EUR | N62: 678 | O62: 0 | P62: 24.0 | S62: Yes | T62: 44955 | U62: https://img01.ztat.net/article/ZL100060.jpg | V62: =(Sales[[#This Row],[Price_retail]]-Sales[[#This Row],[Price_current]])/Sales[[#This Row],[Price_retail]] -> 0 | W62: {=_xlfn.IFS(Sales[[#This Row],[Discount]]=0%,"No Discount",Sales[[#This Row],[Discount]]<=20%,"Light",Sales[[#This Row],[Discount]]<=50%,"Moderate",Sales[[#This Row],[Discount]]<=80%,"High", TRUE,"Very High")} -> No Discount
A63: ZL100061 | B63: https://www.zalando.de/nike-slim-fit-t-shirt---beige-zl100061/ | C63: Nike | D63: Slim Fit T-SHIRT - BEIGE | E63: Men's T-Shirts & Polos | F63: T-Shirts | G63: Long Sleeve T-Shirts | H63: Beige | I63: S | J63: 27.54 | K63: 27.54 | L63: Regular Price | M63: EUR | N63: 297 | O63: 4.7 | P63: 35.0 | S63: Yes | T63: 44955 | U63: https://img01.ztat.net/article/ZL100061.jpg | V63: =(Sales[[#This Row],[Price_retail]]-Sales[[#This Row],[Price_current]])/Sales[[#This Row],[Price_retail]] -> 0 | W63: {=_xlfn.IFS(Sales[[#This Row],[Discount]]=0%,"No Discount",Sales[[#This Row],[Discount]]<=20%,"Light",Sales[[#This Row],[Discount]]<=50%,"Moderate",Sales[[#This Row],[Discount]]<=80%,"High", TRUE,"Very High")} -> No Discount
A64: ZL100062 | B64: https://www.zalando.de/jack-jones-junior-regular-fit-t-shirt---navy-zl100062/ | C64: Jack & Jones Junior | D64: Regular Fit T-SHIRT - NAVY | E64: Men's T-Shirts & Polos | F64: T-Shirts | G64: Print T-Shirts | H64: Navy | I64: XS | J64: 16.94 | K64: 16.94 | L64: Regular Price | M64: EUR | N64: 956 | O64: 3.5 | P64: 32.0 | S64: Yes | T64: 44955 | U64: https://img01.ztat.net/article/ZL100062.jpg | V64: =(Sales[[#This Row],[Price_retail]]-Sales[[#This Row],[Price_current]])/Sales[[#This Row],[Price_retail]] -> 0 | W64: {=_xlfn.IFS(Sales[[#This Row],[Discount]]=0%,"No Discount",Sales[[#This Row],[Discount]]<=20%,"Light",Sales[[#This Row],[Discount]]<=50%,"Moderate",Sales[[#This Row],[Discount]]<=80%,"High", TRUE,"Very High")} -> No Discount
A65: ZL100063 | B65: https://www.zalando.de/tommy-hilfiger-essential-polo---dark-blue-zl100063/ | C65: Tommy Hilfiger | D65: Essential POLO - DARK BLUE | E65: Men's T-Shirts & Polos | F65: Polo Shirts | G65: Slim Fit Polos | I65: XS | J65: 12.68 | K65: 10.81 | L65: SALE | M65: EUR | N65: 332 | O65: 4.9 | P65: 31.0 | S65: Yes | T65: 44955 | U65: https://img01.ztat.net/article/ZL100063.jpg | V65: =(Sales[[#This Row],[Price_retail]]-Sales[[#This Row],[Price_current]])/Sales[[#This Row],[Price_retail]] -> 0.14747634 | W65: {=_xlfn.IFS(Sales[[#This Row],[Discount]]=0%,"No Discount",Sales[[#This Row],[Discount]]<=20%,"Light",Sales[[#This Row],[Discount]]<=50%,"Moderate",Sales[[#This Row],[Discount]]<=80%,"High", TRUE,"Very High")} -> Light
A66: ZL100064 | B66: https://www.zalando.de/tommy-hilfiger-regular-fit-polo---mint-zl100064/ | C66: Tommy Hilfiger | D66: Regular Fit Polo - Mint | E66: Men's T-Shirts & Polos | F66: Polo Shirts | G66: Basic Polos | H66: Mint | I66: S | J66: 16.56 | K66: 16.56 | L66: Regular Price | M66: EUR | N66: 829 | O66: 4.4 | P66: 32.0 | S66: No | T66: 44955 | U66: https://img01.ztat.net/article/ZL100064.jpg | V66: =(Sales[[#This Row],[Price_retail]]-Sales[[#This Row],[Price_current]])/Sales[[#This Row],[Price_retail]] -> 0 | W66: {=_xlfn.IFS(Sales[[#This Row],[Discount]]=0%,"No Discount",Sales[[#This Row],[Discount]]<=20%,"Light",Sales[[#This Row],[Discount]]<=50%,"Moderate",Sales[[#This Row],[Discount]]<=80%,"High", TRUE,"Very High")} -> No Discount
A67: ZL100065 | B67: https://www.zalando.de/tommy-hilfiger-print-t-shirt---beige-zl100065/ | C67: Tommy Hilfiger | D67: Print T-SHIRT - BEIGE | E67: Men's T-Shirts & Polos | F67: T-Shirts | G67: Print T-Shirts | H67: Beige | I67: S | J67: 11.66 | K67: 11.66 | L67: Regular Price | M67: EUR | N67: 225 | O67: 4.9 | P67: 43.0 | S67: No | T67: 44955 | U67: https://img01.ztat.net/article/ZL100065.jpg | V67: =(Sales[[#This Row],[Price_retail]]-Sales[[#This Row],[Price_current]])/Sales[[#This Row],[Price_retail]] -> 0 | W67: {=_xlfn.IFS(Sales[[#This Row],[Discount]]=0%,"No Discount",Sales[[#This Row],[Discount]]<=20%,"Light",Sales[[#This Row],[Discount]]<=50%,"Moderate",Sales[[#This Row],[Discount]]<=80%,"High", TRUE,"Very High")} -> No Discount
A68: ZL100066 | B68: https://www.zalando.de/nike-essential-polo---anthracite-zl100066/ | C68: Nike | D68: Essential POLO - ANTHRACITE | E68: Men's T-Shirts & Polos | F68: Polo Shirts | G68: Pique Polos | H68: Anthracite | I68: M | J68: 8.99 | K68: 5.83 | L68: SALE | M68: EUR | N68: 533 | O68: 3.6 | P68: 39.0 | S68: Yes | T68: 44955 | U68: https://img01.ztat.net/article/ZL100066.jpg | V68: =(Sales[[#This Row],[Price_retail]]-Sales[[#This Row],[Price_current]])/Sales[[#This Row],[Price_retail]] -> 0.35150167 | W68: {=_xlfn.IFS(Sales[[#This Row],[Discount]]=0%,"No Discount",Sales[[#This Row],[Discount]]<=20%,"Light",Sales[[#This Row],[Discount]]<=50%,"Moderate",Sales[[#This Row],[Discount]]<=80%,"High", TRUE,"Very High")} -> Moderate
A69: ZL100067 | B69: https://www.zalando.de/adidas-originals-print-t-shirt---white-zl100067/ | C69: Adidas Originals | D69: Print T-SHIRT - WHITE | E69: Men's T-Shirts & Polos | F69: T-Shirts | G69: Long Sleeve T-Shirts | H69: White | I69: S | J69: 13.41 | K69: 6.23 | L69: SALE | M69: EUR | N69: 818 | O69: 5.0 | P69: 32.0 | S69: Yes | T69: 44955 | U69: https://img01.ztat.net/article/ZL100067.jpg | V69: =(Sales[[#This Row],[Price_retail]]-Sales[[#This Row],[Price_current]])/Sales[[#This Row],[Price_retail]] -> 0.53542133 | W69: {=_xlfn.IFS(Sales[[#This Row],[Discount]]=0%,"No Discount",Sales[[#This Row],[Discount]]<=20%,"Light",Sales[[#This Row],[Discount]]<=50%,"Moderate",Sales[[#This Row],[Discount]]<=80%,"High", TRUE,"Very High")} -> High
A70: ZL100068 | B70: https://www.zalando.de/converse-regular-fit-polo---bordeaux-zl100068/ | C70: Converse | D70: Regular Fit POLO - BORDEAUX | E70: Men's T-Shirts & Polos | F70: Polo Shirts | G70: Basic Polos | I70: M | J70: 19.04 | K70: 19.04 | L70: Regular Price | M70: EUR | N70: 631 | O70: 0 | P70: 25.0 | S70: Yes | T70: 44955 | U70: https://img01.ztat.net/article/ZL100068.jpg | V70: =(Sales[[#This Row],[Price_retail]]-Sales[[#This Row],[Price_current]])/Sales[[#This Row],[Price_retail]] -> 0 | W70: {=_xlfn.IFS(Sales[[#This Row],[Discount]]=0%,"No Discount",Sales[[#This Row],[Discount]]<=20%,"Light",Sales[[#This Row],[Discount]]<=50%,"Moderate",Sales[[#This Row],[Discount]]<=80%,"High", TRUE,"Very High")} -> No Discount
A71: ZL100069 | B71: https://www.zalando.de/boss-orange-print-polo---black-zl100069/ | C71: Boss Orange | D71: Print POLO - BLACK | E71: Men's T-Shirts & Polos | F71: Polo Shirts | G71: Pique Polos | H71: Black | I71: XS | J71: 11.32 | K71: 9.11 | L71: SALE | M71: EUR | N71: 15 | O71: 3.5 | P71: 32.0 | S71: No | T71: 44955 | U71: https://img01.ztat.net/article/ZL100069.jpg | V71: =(Sales[[#This Row],[Price_retail]]-Sales[[#This Row],[Price_current]])/Sales[[#This Row],[Price_retail]] -> 0.19522968 | W71: {=_xlfn.IFS(Sales[[#This Row],[Discount]]=0%,"No Discount",Sales[[#This Row],[Discount]]<=20%,"Light",Sales[[#This Row],[Discount]]<=50%,"Moderate",Sales[[#This Row],[Discount]]<=80%,"High", TRUE,"Very High")} -> Light
A72: ZL100070 | B72: https://www.zalando.de/nike-basic-t-shirt---light-grey-zl100070/ | C72: Nike | D72: Basic T-SHIRT - LIGHT GREY | E72: Men's T-Shirts & Polos | F72: T-Shirts | G72: Long Sleeve T-Shirts | H72: Light Grey | I72: XS | J72: 14.07 | K72: 14.07 | L72: Regular Price | M72: EUR | N72: 437 | O72: 4.9 | P72: 29.0 | S72: Yes | T72: 44955 | U72: https://img01.ztat.net/article/ZL100070.jpg | V72: =(Sales[[#This Row],[Price_retail]]-Sales[[#This Row],[Price_current]])/Sales[[#This Row],[Price_retail]] -> 0 | W72: {=_xlfn.IFS(Sales[[#This Row],[Discount]]=0%,"No Discount",Sales[[#This Row],[Discount]]<=20%,"Light",Sales[[#This Row],[Discount]]<=50%,"Moderate",Sales[[#This Row],[Discount]]<=80%,"High", TRUE,"Very High")} -> No Discount
A73: ZL100071 | B73: https://www.zalando.de/tommy-hilfiger-print-t-shirt---beige-zl100071/ | C73: Tommy Hilfiger | D73: Print T-SHIRT - BEIGE | E73: Men's T-Shirts & Polos | F73: T-Shirts | G73: Basic T-Shirts | H73: Beige | I73: S | J73: 14.37 | K73: 9.82 | L73: SALE | M73: EUR | N73: 609 | O73: 4.9 | P73: 23.0 | S73: Yes | T73: 44955 | U73: https://img01.ztat.net/article/ZL100071.jpg | V73: =(Sales[[#This Row],[Price_retail]]-Sales[[#This Row],[Price_current]])/Sales[[#This Row],[Price_retail]] -> 0.31663187 | W73: {=_xlfn.IFS(Sales[[#This Row],[Discount]]=0%,"No Discount",Sales[[#This Row],[Discount]]<=20%,"Light",Sales[[#This Row],[Discount]]<=50%,"Moderate",Sales[[#This Row],[Discount]]<=80%,"High", TRUE,"Very High")} -> Moderate
A74: ZL100072 | B74: https://www.zalando.de/mazine-slim-fit-t-shirt---khaki-zl100072/ | C74: Mazine | D74: Slim Fit T-SHIRT - KHAKI | E74: Men's T-Shirts & Polos | F74: T-Shirts | G74: Basic T-Shirts | H74: Khaki | J74: 32.99 | K74: 26.01 | L74: SALE | M74: EUR | N74: 259 | O74: 3.3 | P74: 37.0 | S74: No | T74: 44955 | U74: https://img01.ztat.net/article/ZL100072.jpg | V74: =(Sales[[#This Row],[Price_retail]]-Sales[[#This Row],[Price_current]])/Sales[[#This Row],[Price_retail]] -> 0.21157927 | W74: {=_xlfn.IFS(Sales[[#This Row],[Discount]]=0%,"No Discount",Sales[[#This Row],[Discount]]<=20%,"Light",Sales[[#This Row],[Discount]]<=50%,"Moderate",Sales[[#This Row],[Discount]]<=80%,"High", TRUE,"Very High")} -> Moderate
A75: ZL100073 | B75: https://www.zalando.de/denim-and-supply-regular-fit-t-shirt---light-grey-zl100073/ | C75: Denim & Supply | D75: Regular Fit T-SHIRT - LIGHT GREY | E75: Men's T-Shirts & Polos | F75: T-Shirts | G75: Long Sleeve T-Shirts | H75: Light Grey | I75: XS | J75: 12.84 | K75: 9.32 | L75: SALE | M75: EUR | N75: 516 | O75: 0 | P75: 35.0 | S75: No | T75: 44955 | U75: https://img01.ztat.net/article/ZL100073.jpg | V75: =(Sales[[#This Row],[Price_retail]]-Sales[[#This Row],[Price_current]])/Sales[[#This Row],[Price_retail]] -> 0.2741433 | W75: {=_xlfn.IFS(Sales[[#This Row],[Discount]]=0%,"No Discount",Sales[[#This Row],[Discount]]<=20%,"Light",Sales[[#This Row],[Discount]]<=50%,"Moderate",Sales[[#This Row],[Discount]]<=80%,"High", TRUE,"Very High")} -> Moderate
A76: ZL100074 | B76: https://www.zalando.de/nn07-essential-t-shirt---rust-zl100074/ | C76: Nike | D76: Essential T-SHIRT - RUST | E76: Men's T-Shirts & Polos | F76: T-Shirts | G76: Basic T-Shirts | H76: Rust | I76: M | J76: 32.99 | K76: 16.43 | L76: SALE | M76: EUR | N76: 598 | O76: 0 | P76: 34.0 | S76: Yes | T76: 44955 | U76: https://img01.ztat.net/article/ZL100074.jpg | V76: =(Sales[[#This Row],[Price_retail]]-Sales[[#This Row],[Price_current]])/Sales[[#This Row],[Price_retail]] -> 0.50197029 | W76: {=_xlfn.IFS(Sales[[#This Row],[Discount]]=0%,"No Discount",Sales[[#This Row],[Discount]]<=20%,"Light",Sales[[#This Row],[Discount]]<=50%,"Moderate",Sales[[#This Row],[Discount]]<=80%,"High", TRUE,"Very High")} -> High
A77: ZL100075 | B77: https://www.zalando.de/jackandjones-plus-basic-t-shirt---mint-zl100075/ | C77: Jack & Jones Plus | D77: Basic T-SHIRT - MINT | E77: Men's T-Shirts & Polos | F77: T-Shirts | G77: Long Sleeve T-Shirts | H77: Mint | I77: S | J77: 8.99 | K77: 8.99 | L77: Regular Price | M77: EUR | N77: 174 | O77: 4.5 | P77: 40.0 | S77: Yes | T77: 44955 | U77: https://img01.ztat.net/article/ZL100075.jpg | V77: =(Sales[[#This Row],[Price_retail]]-Sales[[#This Row],[Price_current]])/Sales[[#This Row],[Price_retail]] -> 0 | W77: {=_xlfn.IFS(Sales[[#This Row],[Discount]]=0%,"No Discount",Sales[[#This Row],[Discount]]<=20%,"Light",Sales[[#This Row],[Discount]]<=50%,"Moderate",Sales[[#This Row],[Discount]]<=80%,"High", TRUE,"Very High")} -> No Discount
A78: ZL100076 | B78: https://www.zalando.de/vans-essential-polo---off-white-zl100076/ | C78: Vans | D78: Essential POLO - OFF WHITE | E78: Men's T-Shirts & Polos | F78: Polo Shirts | G78: Basic Polos | H78: Off White | I78: M | J78: 32.83 | K78: 23.07 | L78: SALE | M78: EUR | N78: 487 | O78: 4.8 | P78: 41.0 | S78: Yes | T78: 44955 | U78: https://img01.ztat.net/article/ZL100076.jpg | V78: =(Sales[[#This Row],[Price_retail]]-Sales[[#This Row],[Price_current]])/Sales[[#This Row],[Price_retail]] -> 0.29728906 | W78: {=_xlfn.IFS(Sales[[#This Row],[Discount]]=0%,"No Discount",Sales[[#This Row],[Discount]]<=20%,"Light",Sales[[#This Row],[Discount]]<=50%,"Moderate",Sales[[#This Row],[Discount]]<=80%,"High", TRUE,"Very High")} -> Moderate
A79: ZL100077 | B79: https://www.zalando.de/dickies-print-polo---white-zl100077/ | C79: Dickies | D79: Print POLO - WHITE | E79: Men's T-Shirts & Polos | F79: Polo Shirts | G79: Pique Polos | H79: White | I79: S | J79: 31.93 | K79: 16.02 | L79: SALE | M79: EUR | N79: 971 | O79: 3.1 | P79: 0 | S79: Yes | T79: 44955 | U79: https://img01.ztat.net/article/ZL100077.jpg | V79: =(Sales[[#This Row],[Price_retail]]-Sales[[#This Row],[Price_current]])/Sales[[#This Row],[Price_retail]] -> 0.49827748 | W79: {=_xlfn.IFS(Sales[[#This Row],[Discount]]=0%,"No Discount",Sales[[#This Row],[Discount]]<=20%,"Light",Sales[[#This Row],[Discount]]<=50%,"Moderate",Sales[[#This Row],[Discount]]<=80%,"High", TRUE,"Very High")} -> Moderate
A80: ZL100078 | B80: https://www.zalando.de/herrlicher-essential-polo---grey-melange-zl100078/ | C80: Herrlicher | D80: Essential POLO - GREY MELANGE | E80: Men's T-Shirts & Polos | F80: Polo Shirts | G80: Basic Polos | H80: Grey Melange | I80: S | J80: 25.69 | K80: 13.79 | L80: SALE | M80: EUR | N80: 927 | O80: 0 | P80: 38.0 | S80: Yes | T80: 44955 | U80: https://img01.ztat.net/article/ZL100078.jpg | V80: =(Sales[[#This Row],[Price_retail]]-Sales[[#This Row],[Price_current]])/Sales[[#This Row],[Price_retail]] -> 0.46321526 | W80: {=_xlfn.IFS(Sales[[#This Row],[Discount]]=0%,"No Discount",Sales[[#This Row],[Discount]]<=20%,"Light",Sales[[#This Row],[Discount]]<=50%,"Moderate",Sales[[#This Row],[Discount]]<=80%,"High", TRUE,"Very High")} -> Moderate
A81: ZL100079 | B81: https://www.zalando.de/produkt-slim-fit-t-shirt---rust-zl100079/ | C81: Produkt | D81: Slim Fit T-SHIRT - RUST | E81: Men's T-Shirts & Polos | F81: T-Shirts | G81: Slim Fit T-Shirts | H81: Rust | I81: S | J81: 8.99 | K81: 6.41 | L81: SALE | M81: EUR | N81: 671 | O81: 0 | P81: 33.0 | S81: No | T81: 44955 | U81: https://img01.ztat.net/article/ZL100079.jpg | V81: =(Sales[[#This Row],[Price_retail]]-Sales[[#This Row],[Price_current]])/Sales[[#This Row],[Price_retail]] -> 0.28698554 | W81: {=_xlfn.IFS(Sales[[#This Row],[Discount]]=0%,"No Discount",Sales[[#This Row],[Discount]]<=20%,"Light",Sales[[#This Row],[Discount]]<=50%,"Moderate",Sales[[#This Row],[Discount]]<=80%,"High", TRUE,"Very High")} -> Moderate
A82: ZL100080 | B82: https://www.zalando.de/nn07-basic-t-shirt---olive-zl100080/ | C82: Nike | D82: Basic T-SHIRT - OLIVE | E82: Men's T-Shirts & Polos | F82: T-Shirts | G82: Long Sleeve T-Shirts | H82: Olive | I82: XS | J82: 27.4 | K82: 27.4 | L82: Regular Price | M82: EUR | N82: 805 | O82: 4.8 | P82: 44.0 | S82: No | T82: 44955 | U82: https://img01.ztat.net/article/ZL100080.jpg | V82: =(Sales[[#This Row],[Price_retail]]-Sales[[#This Row],[Price_current]])/Sales[[#This Row],[Price_retail]] -> 0 | W82: {=_xlfn.IFS(Sales[[#This Row],[Discount]]=0%,"No Discount",Sales[[#This Row],[Discount]]<=20%,"Light",Sales[[#This Row],[Discount]]<=50%,"Moderate",Sales[[#This Row],[Discount]]<=80%,"High", TRUE,"Very High")} -> No Discount
A83: ZL100081 | B83: https://www.zalando.de/fila-slim-fit-polo---white-zl100081/ | C83: Fila | D83: Slim Fit POLO - WHITE | E83: Men's T-Shirts & Polos | F83: Polo Shirts | G83: Pique Polos | H83: White | I83: XS | J83: 15.22 | K83: 15.22 | L83: Regular Price | M83: EUR | N83: 288 | O83: 4.4 | P83: 31.0 | S83: Yes | T83: 44955 | U83: https://img01.ztat.net/article/ZL100081.jpg | V83: =(Sales[[#This Row],[Price_retail]]-Sales[[#This Row],[Price_current]])/Sales[[#This Row],[Price_retail]] -> 0 | W83: {=_xlfn.IFS(Sales[[#This Row],[Discount]]=0%,"No Discount",Sales[[#This Row],[Discount]]<=20%,"Light",Sales[[#This Row],[Discount]]<=50%,"Moderate",Sales[[#This Row],[Discount]]<=80%,"High", TRUE,"Very High")} -> No Discount
A84: ZL100082 | B84: https://www.zalando.de/nike-print-polo---anthracite-zl100082/ | C84: Nike | D84: Print POLO - ANTHRACITE | E84: Men's T-Shirts & Polos | F84: Polo Shirts | G84: Pique Polos | H84: Anthracite | I84: XS | J84: 8.99 | K84: 6.57 | L84: SALE | M84: EUR | N84: 485 | O84: 3.4 | P84: 32.0 | S84: No | T84: 44955 | U84: https://img01.ztat.net/article/ZL100082.jpg | V84: =(Sales[[#This Row],[Price_retail]]-Sales[[#This Row],[Price_current]])/Sales[[#This Row],[Price_retail]] -> 0.26918799 | W84: {=_xlfn.IFS(Sales[[#This Row],[Discount]]=0%,"No Discount",Sales[[#This Row],[Discount]]<=20%,"Light",Sales[[#This Row],[Discount]]<=50%,"Moderate",Sales[[#This Row],[Discount]]<=80%,"High", TRUE,"Very High")} -> Moderate
A85: ZL100083 | B85: https://www.zalando.de/celio-basic-polo---khaki-zl100083/ | C85: Celio | D85: Basic POLO - KHAKI | E85: Men's T-Shirts & Polos | F85: Polo Shirts | G85: Slim Fit Polos | H85: Khaki | I85: XS | J85: 31.94 | K85: 24.83 | L85: SALE | M85: EUR | N85: 648 | O85: 0 | P85: 42.0 | S85: Yes | T85: 44955 | U85: https://img01.ztat.net/article/ZL100083.jpg | V85: =(Sales[[#This Row],[Price_retail]]-Sales[[#This Row],[Price_current]])/Sales[[#This Row],[Price_retail]] -> 0.22260488 | W85: {=_xlfn.IFS(Sales[[#This Row],[Discount]]=0%,"No Discount",Sales[[#This Row],[Discount]]<=20%,"Light",Sales[[#This Row],[Discount]]<=50%,"Moderate",Sales[[#This Row],[Discount]]<=80%,"High", TRUE,"Very High")} -> Moderate
A86: ZL100084 | B86: https://www.zalando.de/burton-basic-polo---grey-melange-zl100084/ | C86: Burton Menswear London | D86: Basic POLO - GREY MELANGE | E86: Men's T-Shirts & Polos | F86: Polo Shirts | G86: Pique Polos | H86: Grey Melange | I86: S | J86: 34.62 | K86: 27.06 | L86: SALE | M86: EUR | N86: 294 | O86: 4.5 | P86: 35.0 | S86: No | T86: 44955 | U86: https://img01.ztat.net/article/ZL100084.jpg | V86: =(Sales[[#This Row],[Price_retail]]-Sales[[#This Row],[Price_current]])/Sales[[#This Row],[Price_retail]] -> 0.21837088 | W86: {=_xlfn.IFS(Sales[[#This Row],[Discount]]=0%,"No Discount",Sales[[#This Row],[Discount]]<=20%,"Light",Sales[[#This Row],[Discount]]<=50%,"Moderate",Sales[[#This Row],[Discount]]<=80%,"High", TRUE,"Very High")} -> Moderate
... A104: ZL100102 | B104: https://www.zalando.de/nike-sportswear-basic-polo---navy-zl100102/ | C104: Nike Sportswear | D104: Basic POLO - NAVY | E104: Men's T-Shirts & Polos | F104: Polo Shirts | G104: Pique Polos | H104: Navy | I104: XS | J104: 10.04 | K104: 10.04 | L104: Regular Price | M104: EUR | N104: 51 | O104: 4.6 | P104: 32.0 | S104: Yes | T104: 44955 | U104: https://img01.ztat.net/article/ZL100102.jpg | V104: =(Sales[[#This Row],[Price_retail]]-Sales[[#This Row],[Price_current]])/Sales[[#This Row],[Price_retail]] -> 0 | W104: {=_xlfn.IFS(Sales[[#This Row],[Discount]]=0%,"No Discount",Sales[[#This Row],[Discount]]<=20%,"Light",Sales[[#This Row],[Discount]]<=50%,"Moderate",Sales[[#This Row],[Discount]]<=80%,"High", TRUE,"Very High")} -> No Discount
A105: ZL100103 | B105: https://www.zalando.de/blend-regular-fit-polo---red-zl100103/ | C105: Blend | D105: Regular Fit POLO - RED | E105: Men's T-Shirts & Polos | F105: Polo Shirts | G105: Slim Fit Polos | H105: Red | J105: 14.01 | K105: 14.01 | L105: Regular Price | M105: EUR | N105: 837 | O105: 3.2 | P105: 34.0 | S105: Yes | T105: 44955 | U105: https://img01.ztat.net/article/ZL100103.jpg | V105: =(Sales[[#This Row],[Price_retail]]-Sales[[#This Row],[Price_current]])/Sales[[#This Row],[Price_retail]] -> 0 | W105: {=_xlfn.IFS(Sales[[#This Row],[Discount]]=0%,"No Discount",Sales[[#This Row],[Discount]]<=20%,"Light",Sales[[#This Row],[Discount]]<=50%,"Moderate",Sales[[#This Row],[Discount]]<=80%,"High", TRUE,"Very High")} -> No Discount
A106: ZL100104 | B106: https://www.zalando.de/timberland-pro-basic-polo---dark-green-zl100104/ | C106: Timberland Pro | D106: Basic POLO - DARK GREEN | E106: Men's T-Shirts & Polos | F106: Polo Shirts | G106: Basic Polos | H106: Dark Green | J106: 18.32 | K106: 18.32 | L106: Regular Price | M106: EUR | N106: 623 | O106: N/A | P106: 0 | S106: No | T106: 44955 | U106: https://img01.ztat.net/article/ZL100104.jpg | V106: =(Sales[[#This Row],[Price_retail]]-Sales[[#This Row],[Price_current]])/Sales[[#This Row],[Price_retail]] -> 0 | W106: {=_xlfn.IFS(Sales[[#This Row],[Discount]]=0%,"No Discount",Sales[[#This Row],[Discount]]<=20%,"Light",Sales[[#This Row],[Discount]]<=50%,"Moderate",Sales[[#This Row],[Discount]]<=80%,"High", TRUE,"Very High")} -> No Discount
A107: ZL100105 | B107: https://www.zalando.de/bershka-regular-fit-polo---bordeaux-zl100105/ | C107: Bershka | D107: Regular Fit POLO - BORDEAUX | E107: Men's T-Shirts & Polos | F107: Polo Shirts | G107: Basic Polos | H107: Bordeaux | I107: S | J107: 8.99 | K107: 8.99 | L107: Regular Price | M107: EUR | N107: 887 | O107: 4.7 | P107: 30.0 | S107: No | T107: 44955 | U107: https://img01.ztat.net/article/ZL100105.jpg | V107: =(Sales[[#This Row],[Price_retail]]-Sales[[#This Row],[Price_current]])/Sales[[#This Row],[Price_retail]] -> 0 | W107: {=_xlfn.IFS(Sales[[#This Row],[Discount]]=0%,"No Discount",Sales[[#This Row],[Discount]]<=20%,"Light",Sales[[#This Row],[Discount]]<=50%,"Moderate",Sales[[#This Row],[Discount]]<=80%,"High", TRUE,"Very High")} -> No Discount
A108: ZL100106 | B108: https://www.zalando.de/nike-basic-polo---rust-zl100106/ | C108: Nike | D108: Basic POLO - RUST | E108: Men's T-Shirts & Polos | F108: Polo Shirts | G108: Pique Polos | I108: XS | J108: 8.99 | K108: 8.99 | L108: Regular Price | M108: EUR | N108: 640 | O108: 4.6 | P108: 41.0 | S108: Yes | T108: 44955 | U108: https://img01.ztat.net/article/ZL100106.jpg | V108: =(Sales[[#This Row],[Price_retail]]-Sales[[#This Row],[Price_current]])/Sales[[#This Row],[Price_retail]] -> 0 | W108: {=_xlfn.IFS(Sales[[#This Row],[Discount]]=0%,"No Discount",Sales[[#This Row],[Discount]]<=20%,"Light",Sales[[#This Row],[Discount]]<=50%,"Moderate",Sales[[#This Row],[Discount]]<=80%,"High", TRUE,"Very High")} -> No Discount
A109: ZL100107 | B109: https://www.zalando.de/peter-werth-regular-fit-polo---white-zl100107/ | C109: Peter Werth | D109: Regular Fit POLO - WHITE | E109: Men's T-Shirts & Polos | F109: Polo Shirts | G109: Basic Polos | H109: White | I109: XS | J109: 13.27 | K109: 11.33 | L109: SALE | M109: EUR | N109: 697 | O109: 3.9 | P109: 38.0 | S109: No | T109: 44955 | U109: https://img01.ztat.net/article/ZL100107.jpg | V109: =(Sales[[#This Row],[Price_retail]]-Sales[[#This Row],[Price_current]])/Sales[[#This Row],[Price_retail]] -> 0.14619442 | W109: {=_xlfn.IFS(Sales[[#This Row],[Discount]]=0%,"No Discount",Sales[[#This Row],[Discount]]<=20%,"Light",Sales[[#This Row],[Discount]]<=50%,"Moderate",Sales[[#This Row],[Discount]]<=80%,"High", TRUE,"Very High")} -> Light
A110: ZL100108 | B110: https://www.zalando.de/nike-basic-polo---black-zl100108/ | C110: Nike | D110: Basic POLO - BLACK | E110: Men's T-Shirts & Polos | F110: Polo Shirts | G110: Slim Fit Polos | H110: Black | I110: S | J110: 20.09 | K110: 20.09 | L110: Regular Price | M110: EUR | N110: 447 | O110: 3.1 | P110: 35.0 | S110: Yes | T110: 44955 | U110: https://img01.ztat.net/article/ZL100108.jpg | V110: =(Sales[[#This Row],[Price_retail]]-Sales[[#This Row],[Price_current]])/Sales[[#This Row],[Price_retail]] -> 0 | W110: {=_xlfn.IFS(Sales[[#This Row],[Discount]]=0%,"No Discount",Sales[[#This Row],[Discount]]<=20%,"Light",Sales[[#This Row],[Discount]]<=50%,"Moderate",Sales[[#This Row],[Discount]]<=80%,"High", TRUE,"Very High")} -> No Discount
A111: ZL100109 | B111: https://www.zalando.de/denim-and-supply-essential-t-shirt---white-zl100109/ | C111: Denim & Supply | D111: Essential T-SHIRT - WHITE | E111: Men's T-Shirts & Polos | F111: T-Shirts | G111: Slim Fit T-Shirts | H111: White | I111: M | J111: 23.55 | K111: 9.29 | L111: SALE | M111: EUR | N111: 983 | O111: 3.3 | P111: 36.0 | S111: Yes | T111: 44955 | U111: https://img01.ztat.net/article/ZL100109.jpg | V111: =(Sales[[#This Row],[Price_retail]]-Sales[[#This Row],[Price_current]])/Sales[[#This Row],[Price_retail]] -> 0.60552017 | W111: {=_xlfn.IFS(Sales[[#This Row],[Discount]]=0%,"No Discount",Sales[[#This Row],[Discount]]<=20%,"Light",Sales[[#This Row],[Discount]]<=50%,"Moderate",Sales[[#This Row],[Discount]]<=80%,"High", TRUE,"Very High")} -> High
A112: ZL100110 | B112: https://www.zalando.de/nike-essential-polo---dark-green-zl100110/ | C112: Nike | D112: Essential POLO - DARK GREEN | E112: Men's T-Shirts & Polos | F112: Polo Shirts | G112: Slim Fit Polos | H112: Dark Green | I112: S | J112: 8.99 | K112: 6.57 | L112: SALE | M112: EUR | N112: 180 | O112: 3.1 | P112: 33.0 | S112: Yes | T112: 44955 | U112: https://img01.ztat.net/article/ZL100110.jpg | V112: =(Sales[[#This Row],[Price_retail]]-Sales[[#This Row],[Price_current]])/Sales[[#This Row],[Price_retail]] -> 0.26918799 | W112: {=_xlfn.IFS(Sales[[#This Row],[Discount]]=0%,"No Discount",Sales[[#This Row],[Discount]]<=20%,"Light",Sales[[#This Row],[Discount]]<=50%,"Moderate",Sales[[#This Row],[Discount]]<=80%,"High", TRUE,"Very High")} -> Moderate
A113: ZL100111 | B113: https://www.zalando.de/urban-classics-regular-fit-t-shirt---anthracite-zl100111/ | C113: Urban Classics | D113: Regular Fit T-SHIRT - ANTHRACITE | E113: Men's T-Shirts & Polos | F113: T-Shirts | G113: Basic T-Shirts | H113: Anthracite | I113: S | J113: 22.2 | K113: 21.09 | L113: SALE | M113: EUR | N113: 276 | O113: 4.2 | P113: 47.0 | S113: Yes | T113: 44955 | U113: https://img01.ztat.net/article/ZL100111.jpg | V113: =(Sales[[#This Row],[Price_retail]]-Sales[[#This Row],[Price_current]])/Sales[[#This Row],[Price_retail]] -> 0.05 | W113: {=_xlfn.IFS(Sales[[#This Row],[Discount]]=0%,"No Discount",Sales[[#This Row],[Discount]]<=20%,"Light",Sales[[#This Row],[Discount]]<=50%,"Moderate",Sales[[#This Row],[Discount]]<=80%,"High", TRUE,"Very High")} -> Light
A114: ZL100112 | B114: https://www.zalando.de/baldessarini-basic-t-shirt---off-white-zl100112/ | C114: Baldessarini | D114: Basic T-SHIRT - OFF WHITE | E114: Men's T-Shirts & Polos | F114: T-Shirts | G114: Slim Fit T-Shirts | I114: S | J114: 13.67 | K114: 13.67 | L114: NEW | M114: EUR | N114: 24 | O114: 3.2 | P114: 32.0 | S114: No | T114: 44955 | U114: https://img01.ztat.net/article/ZL100112.jpg | V114: =(Sales[[#This Row],[Price_retail]]-Sales[[#This Row],[Price_current]])/Sales[[#This Row],[Price_retail]] -> 0 | W114: {=_xlfn.IFS(Sales[[#This Row],[Discount]]=0%,"No Discount",Sales[[#This Row],[Discount]]<=20%,"Light",Sales[[#This Row],[Discount]]<=50%,"Moderate",Sales[[#This Row],[Discount]]<=80%,"High", TRUE,"Very High")} -> No Discount
A115: ZL100113 | B115: https://www.zalando.de/calvin-klein-essential-t-shirt---red-zl100113/ | C115: Calvin Klein | D115: Essential T-SHIRT - RED | E115: Men's T-Shirts & Polos | F115: T-Shirts | G115: Print T-Shirts | H115: Red | I115: S | J115: 9.62 | K115: 8.12 | L115: SALE | M115: EUR | N115: 415 | O115: 3.8 | P115: 37.0 | S115: Yes | T115: 44955 | U115: https://img01.ztat.net/article/ZL100113.jpg | V115: =(Sales[[#This Row],[Price_retail]]-Sales[[#This Row],[Price_current]])/Sales[[#This Row],[Price_retail]] -> 0.15592516 | W115: {=_xlfn.IFS(Sales[[#This Row],[Discount]]=0%,"No Discount",Sales[[#This Row],[Discount]]<=20%,"Light",Sales[[#This Row],[Discount]]<=50%,"Moderate",Sales[[#This Row],[Discount]]<=80%,"High", TRUE,"Very High")} -> Light
A116: ZL100114 | B116: https://www.zalando.de/adidas-performance-essential-polo---off-white-zl100114/ | C116: Adidas Performance | D116: Essential POLO - OFF WHITE | E116: Men's T-Shirts & Polos | F116: Polo Shirts | G116: Slim Fit Polos | H116: Off White | I116: M | J116: 10.95 | K116: 10.95 | L116: Regular Price | M116: EUR | N116: 200 | O116: 3.5 | P116: 26.0 | S116: Yes | T116: 44955 | U116: https://img01.ztat.net/article/ZL100114.jpg | V116: =(Sales[[#This Row],[Price_retail]]-Sales[[#This Row],[Price_current]])/Sales[[#This Row],[Price_retail]] -> 0 | W116: {=_xlfn.IFS(Sales[[#This Row],[Discount]]=0%,"No Discount",Sales[[#This Row],[Discount]]<=20%,"Light",Sales[[#This Row],[Discount]]<=50%,"Moderate",Sales[[#This Row],[Discount]]<=80%,"High", TRUE,"Very High")} -> No Discount
A117: ZL100115 | B117: https://www.zalando.de/nike-print-polo---grey-melange-zl100115/ | C117: Nike | D117: Print POLO - GREY MELANGE | E117: Men's T-Shirts & Polos | F117: Polo Shirts | G117: Slim Fit Polos | H117: Grey Melange | I117: XS | J117: 24.31 | K117: 24.31 | L117: Regular Price | M117: EUR | N117: 827 | O117: 3.8 | P117: 38.0 | S117: Yes | T117: 44955 | U117: https://img01.ztat.net/article/ZL100115.jpg | V117: =(Sales[[#This Row],[Price_retail]]-Sales[[#This Row],[Price_current]])/Sales[[#This Row],[Price_retail]] -> 0 | W117: {=_xlfn.IFS(Sales[[#This Row],[Discount]]=0%,"No Discount",Sales[[#This Row],[Discount]]<=20%,"Light",Sales[[#This Row],[Discount]]<=50%,"Moderate",Sales[[#This Row],[Discount]]<=80%,"High", TRUE,"Very High")} -> No Discount
A118: ZL100116 | B118: https://www.zalando.de/selected-homme-essential-t-shirt---bordeaux-zl100116/ | C118: Selected Homme | D118: Essential T-SHIRT - BORDEAUX | E118: Men's T-Shirts & Polos | F118: T-Shirts | G118: Slim Fit T-Shirts | H118: Bordeaux | I118: M | J118: 18.19 | K118: 6.76 | L118: SALE | M118: EUR | N118: 893 | O118: 3.1 | P118: 33.0 | S118: Yes | T118: 44955 | U118: https://img01.ztat.net/article/ZL100116.jpg | V118: =(Sales[[#This Row],[Price_retail]]-Sales[[#This Row],[Price_current]])/Sales[[#This Row],[Price_retail]] -> 0.62836723 | W118: {=_xlfn.IFS(Sales[[#This Row],[Discount]]=0%,"No Discount",Sales[[#This Row],[Discount]]<=20%,"Light",Sales[[#This Row],[Discount]]<=50%,"Moderate",Sales[[#This Row],[Discount]]<=80%,"High", TRUE,"Very High")} -> High
A119: ZL100117 | B119: https://www.zalando.de/jordan-basic-t-shirt---olive-zl100117/ | C119: Jordan | D119: Basic T-SHIRT - OLIVE | E119: Men's T-Shirts & Polos | F119: T-Shirts | G119: Basic T-Shirts | H119: Olive | I119: XS | J119: 16.08 | K119: 12.13 | L119: SALE | M119: EUR | N119: 953 | O119: 3.3 | P119: 41.0 | S119: Yes | T119: 44955 | U119: https://img01.ztat.net/article/ZL100117.jpg | V119: =(Sales[[#This Row],[Price_retail]]-Sales[[#This Row],[Price_current]])/Sales[[#This Row],[Price_retail]] -> 0.24564677 | W119: {=_xlfn.IFS(Sales[[#This Row],[Discount]]=0%,"No Discount",Sales[[#This Row],[Discount]]<=20%,"Light",Sales[[#This Row],[Discount]]<=50%,"Moderate",Sales[[#This Row],[Discount]]<=80%,"High", TRUE,"Very High")} -> Moderate
A120: ZL100118 | B120: https://www.zalando.de/seidensticker-basic-polo---rust-zl100118/ | C120: Seidensticker | D120: Basic POLO - RUST | E120: Men's T-Shirts & Polos | F120: Polo Shirts | G120: Slim Fit Polos | H120: Rust | I120: M | J120: 17.88 | K120: 17.88 | L120: Regular Price | M120: EUR | N120: 865 | O120: N/A | P120: 36.0 | S120: No | T120: 44955 | U120: https://img01.ztat.net/article/ZL100118.jpg | V120: =(Sales[[#This Row],[Price_retail]]-Sales[[#This Row],[Price_current]])/Sales[[#This Row],[Price_retail]] -> 0 | W120: {=_xlfn.IFS(Sales[[#This Row],[Discount]]=0%,"No Discount",Sales[[#This Row],[Discount]]<=20%,"Light",Sales[[#This Row],[Discount]]<=50%,"Moderate",Sales[[#This Row],[Discount]]<=80%,"High", TRUE,"Very High")} -> No Discount
A121: ZL100119 | B121: https://www.zalando.de/only-and-sons-denim-print-polo---bordeaux-zl100119/ | C121: Only & Sons | D121: Print POLO - BORDEAUX | E121: Men's T-Shirts & Polos | F121: Polo Shirts | G121: Pique Polos | H121: Bordeaux | I121: S | J121: 26.06 | K121: 26.06 | L121: Regular Price | M121: EUR | N121: 395 | O121: 4.0 | P121: 30.0 | S121: Yes | T121: 44955 | U121: https://img01.ztat.net/article/ZL100119.jpg | V121: =(Sales[[#This Row],[Price_retail]]-Sales[[#This Row],[Price_current]])/Sales[[#This Row],[Price_retail]] -> 0 | W121: {=_xlfn.IFS(Sales[[#This Row],[Discount]]=0%,"No Discount",Sales[[#This Row],[Discount]]<=20%,"Light",Sales[[#This Row],[Discount]]<=50%,"Moderate",Sales[[#This Row],[Discount]]<=80%,"High", TRUE,"Very High")} -> No Discount
A122: ZL100120 | B122: https://www.zalando.de/pier-one-regular-fit-polo---light-grey-zl100120/ | C122: Pier One | D122: Regular Fit POLO - LIGHT GREY | E122: Men's T-Shirts & Polos | F122: Polo Shirts | G122: Basic Polos | H122: Light Grey | I122: S | J122: 28.28 | K122: 28.28 | L122: Regular Price | M122: EUR | N122: 880 | O122: 4.9 | P122: 45.0 | S122: Yes | T122: 44955 | U122: https://img01.ztat.net/article/ZL100120.jpg | V122: =(Sales[[#This Row],[Price_retail]]-Sales[[#This Row],[Price_current]])/Sales[[#This Row],[Price_retail]] -> 0 | W122: {=_xlfn.IFS(Sales[[#This Row],[Discount]]=0%,"No Discount",Sales[[#This Row],[Discount]]<=20%,"Light",Sales[[#This Row],[Discount]]<=50%,"Moderate",Sales[[#This Row],[Discount]]<=80%,"High", TRUE,"Very High")} -> No Discount
A123: ZL100121 | B123: https://www.zalando.de/jack-jones-junior-print-t-shirt---red-zl100121/ | C123: Jack & Jones Junior | D123: Print T-SHIRT - RED | E123: Men's T-Shirts & Polos | F123: T-Shirts | G123: Slim Fit T-Shirts | H123: Red | I123: S | J123: 16.12 | K123: 8.56 | L123: SALE | M123: EUR | N123: 66 | O123: 4.3 | P123: 33.0 | S123: Yes | T123: 44955 | U123: https://img01.ztat.net/article/ZL100121.jpg | V123: =(Sales[[#This Row],[Price_retail]]-Sales[[#This Row],[Price_current]])/Sales[[#This Row],[Price_retail]] -> 0.46898263 | W123: {=_xlfn.IFS(Sales[[#This Row],[Discount]]=0%,"No Discount",Sales[[#This Row],[Discount]]<=20%,"Light",Sales[[#This Row],[Discount]]<=50%,"Moderate",Sales[[#This Row],[Discount]]<=80%,"High", TRUE,"Very High")} -> Moderate
A124: ZL100122 | B124: https://www.zalando.de/odlo-print-polo---denim-blue-zl100122/ | C124: Odlo | D124: Print POLO - DENIM BLUE | E124: Men's T-Shirts & Polos | F124: Polo Shirts | G124: Basic Polos | H124: Denim Blue | I124: XS | J124: 29.25 | K124: 29.25 | L124: Regular Price | M124: EUR | N124: 620 | O124: 4.1 | P124: 38.0 | S124: Yes | T124: 44955 | U124: https://img01.ztat.net/article/ZL100122.jpg | V124: =(Sales[[#This Row],[Price_retail]]-Sales[[#This Row],[Price_current]])/Sales[[#This Row],[Price_retail]] -> 0 | W124: {=_xlfn.IFS(Sales[[#This Row],[Discount]]=0%,"No Discount",Sales[[#This Row],[Discount]]<=20%,"Light",Sales[[#This Row],[Discount]]<=50%,"Moderate",Sales[[#This Row],[Discount]]<=80%,"High", TRUE,"Very High")} -> No Discount
A125: ZL100123 | B125: https://www.zalando.de/adidas-performance-basic-polo---beige-zl100123/ | C125: Adidas Performance | D125: Basic POLO - BEIGE | E125: Men's T-Shirts & Polos | F125: Polo Shirts | G125: Basic Polos | H125: Beige | I125: S | J125: 13.03 | K125: 8.54 | L125: SALE | M125: EUR | N125: 371 | O125: 4.5 | P125: 41.0 | S125: No | T125: 44955 | U125: https://img01.ztat.net/article/ZL100123.jpg | V125: =(Sales[[#This Row],[Price_retail]]-Sales[[#This Row],[Price_current]])/Sales[[#This Row],[Price_retail]] -> 0.34458941 | W125: {=_xlfn.IFS(Sales[[#This Row],[Discount]]=0%,"No Discount",Sales[[#This Row],[Discount]]<=20%,"Light",Sales[[#This Row],[Discount]]<=50%,"Moderate",Sales[[#This Row],[Discount]]<=80%,"High", TRUE,"Very High")} -> Moderate
A126: ZL100124 | B126: https://www.zalando.de/craft-regular-fit-t-shirt---denim-blue-zl100124/ | C126: Craft | D126: Regular Fit T-SHIRT - DENIM BLUE | E126: Men's T-Shirts & Polos | F126: T-Shirts | G126: Print T-Shirts | H126: Denim Blue | I126: S | J126: 21.98 | K126: 21.98 | L126: Regular Price | M126: EUR | N126: 427 | O126: 0 | P126: 42.0 | S126: Yes | T126: 44955 | U126: https://img01.ztat.net/article/ZL100124.jpg | V126: =(Sales[[#This Row],[Price_retail]]-Sales[[#This Row],[Price_current]])/Sales[[#This Row],[Price_retail]] -> 0 | W126: {=_xlfn.IFS(Sales[[#This Row],[Discount]]=0%,"No Discount",Sales[[#This Row],[Discount]]<=20%,"Light",Sales[[#This Row],[Discount]]<=50%,"Moderate",Sales[[#This Row],[Discount]]<=80%,"High", TRUE,"Very High")} -> No Discount
A127: ZL100125 | B127: https://www.zalando.de/zalando-essentials-slim-fit-t-shirt---off-white-zl100125/ | C127: Zalando Essentials | D127: Slim Fit T-SHIRT - OFF WHITE | E127: Men's T-Shirts & Polos | F127: T-Shirts | G127: Basic T-Shirts | H127: Off White | J127: 11.86 | K127: 8.64 | L127: SALE | M127: EUR | N127: 632 | O127: 0 | P127: 42.0 | S127: No | T127: 44955 | U127: https://img01.ztat.net/article/ZL100125.jpg | V127: =(Sales[[#This Row],[Price_retail]]-Sales[[#This Row],[Price_current]])/Sales[[#This Row],[Price_retail]] -> 0.27150084 | W127: {=_xlfn.IFS(Sales[[#This Row],[Discount]]=0%,"No Discount",Sales[[#This Row],[Discount]]<=20%,"Light",Sales[[#This Row],[Discount]]<=50%,"Moderate",Sales[[#This Row],[Discount]]<=80%,"High", TRUE,"Very High")} -> Moderate
A128: ZL100126 | B128: https://www.zalando.de/adidas-performance-essential-t-shirt---black-zl100126/ | C128: Adidas Performance | D128: Essential T-SHIRT - BLACK | E128: Men's T-Shirts & Polos | F128: T-Shirts | G128: Print T-Shirts | H128: Black | I128: S | J128: 12.44 | K128: 12.44 | L128: Regular Price | M128: EUR | N128: 585 | O128: 3.8 | P128: 45.0 | S128: No | T128: 44955 | U128: https://img01.ztat.net/article/ZL100126.jpg | V128: =(Sales[[#This Row],[Price_retail]]-Sales[[#This Row],[Price_current]])/Sales[[#This Row],[Price_retail]] -> 0 | W128: {=_xlfn.IFS(Sales[[#This Row],[Discount]]=0%,"No Discount",Sales[[#This Row],[Discount]]<=20%,"Light",Sales[[#This Row],[Discount]]<=50%,"Moderate",Sales[[#This Row],[Discount]]<=80%,"High", TRUE,"Very High")} -> No Discount
A129: ZL100127 | B129: https://www.zalando.de/nike-regular-fit-polo---olive-zl100127/ | C129: Nike | D129: Regular Fit POLO - OLIVE | E129: Men's T-Shirts & Polos | F129: Polo Shirts | G129: Slim Fit Polos | H129: Olive | I129: XS | J129: 21.02 | K129: 21.02 | L129: Regular Price | M129: EUR | N129: 329 | O129: 4.7 | P129: 0 | S129: Yes | T129: 44955 | U129: https://img01.ztat.net/article/ZL100127.jpg | V129: =(Sales[[#This Row],[Price_retail]]-Sales[[#This Row],[Price_current]])/Sales[[#This Row],[Price_retail]] -> 0 | W129: {=_xlfn.IFS(Sales[[#This Row],[Discount]]=0%,"No Discount",Sales[[#This Row],[Discount]]<=20%,"Light",Sales[[#This Row],[Discount]]<=50%,"Moderate",Sales[[#This Row],[Discount]]<=80%,"High", TRUE,"Very High")} -> No Discount
A130: ZL100128 | B130: https://www.zalando.de/boss-slim-fit-t-shirt---mint-zl100128/ | C130: Boss | D130: Slim Fit T-SHIRT - MINT | E130: Men's T-Shirts & Polos | F130: T-Shirts | G130: Print T-Shirts | I130: XS | J130: 20.77 | K130: 11.98 | L130: SALE | M130: EUR | N130: 863 | O130: 4.0 | P130: 35.0 | S130: No | T130: 44955 | U130: https://img01.ztat.net/article/ZL100128.jpg | V130: =(Sales[[#This Row],[Price_retail]]-Sales[[#This Row],[Price_current]])/Sales[[#This Row],[Price_retail]] -> 0.42320655 | W130: {=_xlfn.IFS(Sales[[#This Row],[Discount]]=0%,"No Discount",Sales[[#This Row],[Discount]]<=20%,"Light",Sales[[#This Row],[Discount]]<=50%,"Moderate",Sales[[#This Row],[Discount]]<=80%,"High", TRUE,"Very High")} -> Moderate
A131: ZL100129 | B131: https://www.zalando.de/converse-basic-t-shirt---white-zl100129/ | C131: Converse | D131: Basic T-SHIRT - WHITE | E131: Men's T-Shirts & Polos | F131: T-Shirts | G131: Long Sleeve T-Shirts | H131: White | I131: M | J131: 30.17 | K131: 30.17 | L131: Regular Price | M131: EUR | N131: 469 | O131: 0 | P131: 36.0 | S131: Yes | T131: 44955 | U131: https://img01.ztat.net/article/ZL100129.jpg | V131: =(Sales[[#This Row],[Price_retail]]-Sales[[#This Row],[Price_current]])/Sales[[#This Row],[Price_retail]] -> 0 | W131: {=_xlfn.IFS(Sales[[#This Row],[Discount]]=0%,"No Discount",Sales[[#This Row],[Discount]]<=20%,"Light",Sales[[#This Row],[Discount]]<=50%,"Moderate",Sales[[#This Row],[Discount]]<=80%,"High", TRUE,"Very High")} -> No Discount
A132: ZL100130 | B132: https://www.zalando.de/salomon-essential-polo---denim-blue-zl100130/ | C132: Salomon | D132: Essential POLO - DENIM BLUE | E132: Men's T-Shirts & Polos | F132: Polo Shirts | G132: Slim Fit Polos | H132: Denim Blue | I132: S | J132: 16.5 | K132: 16.5 | L132: Regular Price | M132: EUR | N132: 658 | O132: 3.1 | P132: 31.0 | S132: Yes | T132: 44955 | U132: https://img01.ztat.net/article/ZL100130.jpg | V132: =(Sales[[#This Row],[Price_retail]]-Sales[[#This Row],[Price_current]])/Sales[[#This Row],[Price_retail]] -> 0 | W132: {=_xlfn.IFS(Sales[[#This Row],[Discount]]=0%,"No Discount",Sales[[#This Row],[Discount]]<=20%,"Light",Sales[[#This Row],[Discount]]<=50%,"Moderate",Sales[[#This Row],[Discount]]<=80%,"High", TRUE,"Very High")} -> No Discount
A133: ZL100131 | B133: https://www.zalando.de/cars-print-t-shirt---bordeaux-zl100131/ | C133: Cars Jeans | D133: Print T-SHIRT - BORDEAUX | E133: Men's T-Shirts & Polos | F133: T-Shirts | G133: Long Sleeve T-Shirts | H133: Bordeaux | I133: S | J133: 8.99 | K133: 8.99 | L133: Regular Price | M133: EUR | N133: 287 | O133: 0 | P133: 33.0 | S133: Yes | T133: 44955 | U133: https://img01.ztat.net/article/ZL100131.jpg | V133: =(Sales[[#This Row],[Price_retail]]-Sales[[#This Row],[Price_current]])/Sales[[#This Row],[Price_retail]] -> 0 | W133: {=_xlfn.IFS(Sales[[#This Row],[Discount]]=0%,"No Discount",Sales[[#This Row],[Discount]]<=20%,"Light",Sales[[#This Row],[Discount]]<=50%,"Moderate",Sales[[#This Row],[Discount]]<=80%,"High", TRUE,"Very High")} -> No Discount
A134: ZL100132 | B134: https://www.zalando.de/lacoste-print-t-shirt---anthracite-zl100132/ | C134: Lacoste | D134: Print T-SHIRT - ANTHRACITE | E134: Men's T-Shirts & Polos | F134: T-Shirts | G134: Print T-Shirts | H134: Anthracite | I134: M | J134: 22.14 | K134: 21.03 | L134: SALE | M134: EUR | N134: 912 | O134: 3.7 | P134: 38.0 | S134: Yes | T134: 44955 | U134: https://img01.ztat.net/article/ZL100132.jpg | V134: =(Sales[[#This Row],[Price_retail]]-Sales[[#This Row],[Price_current]])/Sales[[#This Row],[Price_retail]] -> 0.050135501 | W134: {=_xlfn.IFS(Sales[[#This Row],[Discount]]=0%,"No Discount",Sales[[#This Row],[Discount]]<=20%,"Light",Sales[[#This Row],[Discount]]<=50%,"Moderate",Sales[[#This Row],[Discount]]<=80%,"High", TRUE,"Very High")} -> Light
A135: ZL100133 | B135: https://www.zalando.de/jack-jones-junior-regular-fit-t-shirt---rust-zl100133/ | C135: Jack & Jones Junior | D135: Regular Fit T-SHIRT - RUST | E135: Men's T-Shirts & Polos | F135: T-Shirts | G135: Print T-Shirts | H135: Rust | I135: S | J135: 60.32 | K135: 50.85 | L135: SALE | M135: EUR | N135: 263 | O135: 0 | P135: 48.0 | S135: No | T135: 44955 | U135: https://img01.ztat.net/article/ZL100133.jpg | V135: =(Sales[[#This Row],[Price_retail]]-Sales[[#This Row],[Price_current]])/Sales[[#This Row],[Price_retail]] -> 0.15699602 | W135: {=_xlfn.IFS(Sales[[#This Row],[Discount]]=0%,"No Discount",Sales[[#This Row],[Discount]]<=20%,"Light",Sales[[#This Row],[Discount]]<=50%,"Moderate",Sales[[#This Row],[Discount]]<=80%,"High", TRUE,"Very High")} -> Light
A136: ZL100134 | B136: https://www.zalando.de/tommy-hilfiger-essential-polo---beige-zl100134/ | C136: Tommy Hilfiger | D136: Essential POLO - BEIGE | E136: Men's T-Shirts & Polos | F136: Polo Shirts | G136: Pique Polos | H136: Beige | I136: XS | J136: 16.61 | K136: 16.61 | L136: Regular Price | M136: EUR | N136: 939 | O136: 4.6 | P136: 38.0 | S136: Yes | T136: 44955 | U136: https://img01.ztat.net/article/ZL100134.jpg | V136: =(Sales[[#This Row],[Price_retail]]-Sales[[#This Row],[Price_current]])/Sales[[#This Row],[Price_retail]] -> 0 | W136: {=_xlfn.IFS(Sales[[#This Row],[Discount]]=0%,"No Discount",Sales[[#This Row],[Discount]]<=20%,"Light",Sales[[#This Row],[Discount]]<=50%,"Moderate",Sales[[#This Row],[Discount]]<=80%,"High", TRUE,"Very High")} -> No Discount
A137: ZL100135 | B137: https://www.zalando.de/lacoste-regular-fit-t-shirt---dark-green-zl100135/ | C137: Lacoste | D137: Regular Fit T-SHIRT - DARK GREEN | E137: Men's T-Shirts & Polos | F137: T-Shirts | G137: Basic T-Shirts | H137: Dark Green | I137: S | J137: 8.99 | K137: 6.55 | L137: SALE | M137: EUR | N137: 323 | O137: 3.2 | P137: 47.0 | S137: Yes | T137: 44955 | U137: https://img01.ztat.net/article/ZL100135.jpg | V137: =(Sales[[#This Row],[Price_retail]]-Sales[[#This Row],[Price_current]])/Sales[[#This Row],[Price_retail]] -> 0.27141268 | W137: {=_xlfn.IFS(Sales[[#This Row],[Discount]]=0%,"No Discount",Sales[[#This Row],[Discount]]<=20%,"Light",Sales[[#This Row],[Discount]]<=50%,"Moderate",Sales[[#This Row],[Discount]]<=80%,"High", TRUE,"Very High")} -> Moderate
A138: ZL100136 | B138: https://www.zalando.de/windsor.-essential-t-shirt---royal-blue-zl100136/ | C138: Windsor. | D138: Essential T-SHIRT - ROYAL BLUE | E138: Men's T-Shirts & Polos | F138: T-Shirts | G138: Long Sleeve T-Shirts | H138: Royal Blue | I138: S | J138: 31.33 | K138: 31.33 | L138: Regular Price | M138: EUR | N138: 257 | O138: 4.2 | P138: 30.0 | S138: Yes | T138: 44955 | U138: https://img01.ztat.net/article/ZL100136.jpg | V138: =(Sales[[#This Row],[Price_retail]]-Sales[[#This Row],[Price_current]])/Sales[[#This Row],[Price_retail]] -> 0 | W138: {=_xlfn.IFS(Sales[[#This Row],[Discount]]=0%,"No Discount",Sales[[#This Row],[Discount]]<=20%,"Light",Sales[[#This Row],[Discount]]<=50%,"Moderate",Sales[[#This Row],[Discount]]<=80%,"High", TRUE,"Very High")} -> No Discount
A139: ZL100137 | B139: https://www.zalando.de/boss-print-polo---denim-blue-zl100137/ | C139: Boss | D139: Print POLO - DENIM BLUE | E139: Men's T-Shirts & Polos | F139: Polo Shirts | G139: Slim Fit Polos | H139: Denim Blue | I139: S | J139: 15.62 | K139: 15.62 | L139: Regular Price | M139: EUR | N139: 351 | O139: 4.1 | P139: 33.0 | S139: Yes | T139: 44955 | U139: https://img01.ztat.net/article/ZL100137.jpg | V139: =(Sales[[#This Row],[Price_retail]]-Sales[[#This Row],[Price_current]])/Sales[[#This Row],[Price_retail]] -> 0 | W139: {=_xlfn.IFS(Sales[[#This Row],[Discount]]=0%,"No Discount",Sales[[#This Row],[Discount]]<=20%,"Light",Sales[[#This Row],[Discount]]<=50%,"Moderate",Sales[[#This Row],[Discount]]<=80%,"High", TRUE,"Very High")} -> No Discount
